Workbook
Name ChronologieNative_Delivery1: #N/A
Name ChronologieNative_Delivery11: #N/A
Name Début_HCME: PlanFinance!$B$3
Name Délai_Vente: PlanFinance!$C$7
Name Frais_de_Création: PlanFinance!$C$36
Name MarkUp: PlanFinance!$C$6
Name Rglt_à_ESMTP: PlanFinance!$C$13
Name Rglt_à_HCME: PlanFinance!$C$24
Name Segment_Client1: #N/A
Name Segment_Client11: #N/A
Name Segment_LivrAn: #N/A
Name Segment_Site1: #N/A
Name Segment_Site11: #N/A
Name Segment_Status: #N/A
Name Segment_Status11: #N/A
Name Segment_Status111: #N/A
Name Segment_Sub_Dealer: #N/A
Name Segment_Sub_Dealer1: #N/A
Name Segment_Sub_Dealer11: #N/A
Name Segment_Ton.: #N/A
Name TVA: PlanFinance!$C$11
Name VENTE_stock: PlanFinance!$D$7

Sheet Liste Machines
E1: Sous-TOTAL : | F1: =SUBTOTAL(9,LstMachines[Nbre]) -> 63 | G1: machines pr un montant de | I1: =SUBTOTAL(9,LstMachines[Budget]) -> 2765 | J1: k€ | X1: Réception de la machine | Z1: Paiement à HCME | AB1: Livraison des Cdes | AD1: Estim. vente stock | AF1: Rglt si Commande | AH1: Rglt si Vte Stock
B3: Category | C3: Model | D3: Ton. | E3: Model-Spec | F3: Sub-Dealer | G3: Site | H3: Nbre | I3: Budget | J3: Delivery | K3: Status | L3: OriginInfo | M3: Remarque | N3: OrderDate | O3: LivrMois | P3: LivrAn | Q3: OrderNum | R3: OrderPrice | S3: Financement | T3: Confirm | U3: Destination | V3: MachineId | W3: Client | X3: DateLivr | Y3: MoisLivr | Z3: DatePaie | AA3: MoisPaie | AB3: Distrib | AC3: MoisDistrib | AD3: VteESM | AE3: MoisVteESM | AF3: RgltDistrib | AG3: MoisRgltDistrib | AH3: RgltVteESM | AI3: MoisRgltVteESM | AJ3: PayMonth | AK3: PayYear | AL3: - | AM3: Délai souhaité
B4: Mini Pelle | C4: ZX19 | D4: 19 | E4: ZX19U-5 | F4: BTPS | G4: ORTHEZ | H4: 1 | I4: =IF(LstMachines[[#This Row],[Delivery]]<Début_HCME, 0, IFERROR( LstMachines[[#This Row],[Nbre]] * INDEX(TabModelSpecs[],MATCH(LstMachines[[#This Row],[Model-Spec]],TabModelSpecs[ModelSpec],0),MATCH("2018",TabModelSpecs[#Headers],0)), LstMachines[[#This Row],[Nbre]]*ROUND(AVERAGEIF(TabModelSpecs[Machine],LstMachines[[#This Row],[Model]],TabModelSpecs[Price]),0) ) ) -> 0 | J4: 42856 | K4: 1-Forecast | L4: 2017-11 BTPS | O4: =MONTH(LstMachines[[#This Row],[Delivery]]) -> 5 | P4: =FIXED(YEAR(LstMachines[[#This Row],[Delivery]]),0,TRUE) -> 2017 | X4: =LstMachines[[#This Row],[Delivery]] -> 42856 | Y4: =IF(MONTH(LstMachines[[#This Row],[DateLivr]])<10,"0","") & MONTH(LstMachines[[#This Row],[DateLivr]]) &"-"&YEAR(LstMachines[[#This Row],[DateLivr]]) -> 05-2017 | Z4: =LstMachines[[#This Row],[Delivery]]+Rglt_à_HCME -> 42916 | AA4: =IF(MONTH(LstMachines[[#This Row],[DatePaie]])<10,"0","") & MONTH(LstMachines[[#This Row],[DatePaie]])&"-"&YEAR(LstMachines[[#This Row],[DatePaie]]) -> 06-2017 | AB4: =LstMachines[[#This Row],[DateLivr]]+1 -> 42857 | AC4: =IF(MONTH(LstMachines[[#This Row],[Distrib]])<10,"0","") & MONTH(LstMachines[[#This Row],[Distrib]]) & "-" & YEAR(LstMachines[[#This Row],[Distrib]]) -> 05-2017 | AD4: =LstMachines[[#This Row],[DateLivr]]+Délai_Vente -> 42976 | AE4: =IF(MONTH(LstMachines[[#This Row],[VteESM]])<10,"0","") & MONTH(LstMachines[[#This Row],[VteESM]]) & "-" & YEAR(LstMachines[[#This Row],[VteESM]]) -> 08-2017 | AF4: =LstMachines[[#This Row],[DateLivr]]+Rglt_à_ESMTP -> 42916 | AG4: =IF(MONTH(LstMachines[[#This Row],[RgltDistrib]])<10,"0","") & MONTH(LstMachines[[#This Row],[RgltDistrib]]) & "-" & YEAR(LstMachines[[#This Row],[RgltDistrib]]) -> 06-2017 | AH4: =LstMachines[[#This Row],[VteESM]]+Rglt_à_ESMTP -> 43036 | AI4: =IF(MONTH(LstMachines[[#This Row],[RgltVteESM]])<10,"0","") & MONTH(LstMachines[[#This Row],[RgltVteESM]]) & "-" & YEAR(LstMachines[[#This Row],[RgltVteESM]]) -> 10-2017 | AJ4: =MONTH(LstMachines[[#This Row],[DatePaie]]) -> 6 | AK4: =FIXED(YEAR(LstMachines[[#This Row],[DatePaie]]),0,TRUE) -> 2017
B5: Mini Pelle | C5: ZX55 | D5: 55 | E5: ZX55U-5-CLRNH | F5: BTPS | G5: ORTHEZ | H5: 1 | I5: =IF(LstMachines[[#This Row],[Delivery]]<Début_HCME, 0, IFERROR( LstMachines[[#This Row],[Nbre]] * INDEX(TabModelSpecs[],MATCH(LstMachines[[#This Row],[Model-Spec]],TabModelSpecs[ModelSpec],0),MATCH("2018",TabModelSpecs[#Headers],0)), LstMachines[[#This Row],[Nbre]]*ROUND(AVERAGEIF(TabModelSpecs[Machine],LstMachines[[#This Row],[Model]],TabModelSpecs[Price]),0) ) ) -> 0 | J5: 42870 | K5: 1-Forecast | L5: 2017-11 BTPS | O5: =MONTH(LstMachines[[#This Row],[Delivery]]) -> 5 | P5: =FIXED(YEAR(LstMachines[[#This Row],[Delivery]]),0,TRUE) -> 2017 | X5: =LstMachines[[#This Row],[Delivery]] -> 42870 | Y5: =IF(MONTH(LstMachines[[#This Row],[DateLivr]])<10,"0","") & MONTH(LstMachines[[#This Row],[DateLivr]]) &"-"&YEAR(LstMachines[[#This Row],[DateLivr]]) -> 05-2017 | Z5: =LstMachines[[#This Row],[Delivery]]+Rglt_à_HCME -> 42930 | AA5: =IF(MONTH(LstMachines[[#This Row],[DatePaie]])<10,"0","") & MONTH(LstMachines[[#This Row],[DatePaie]])&"-"&YEAR(LstMachines[[#This Row],[DatePaie]]) -> 07-2017 | AB5: =LstMachines[[#This Row],[DateLivr]]+1 -> 42871 | AC5: =IF(MONTH(LstMachines[[#This Row],[Distrib]])<10,"0","") & MONTH(LstMachines[[#This Row],[Distrib]]) & "-" & YEAR(LstMachines[[#This Row],[Distrib]]) -> 05-2017 | AD5: =LstMachines[[#This Row],[DateLivr]]+Délai_Vente -> 42990 | AE5: =IF(MONTH(LstMachines[[#This Row],[VteESM]])<10,"0","") & MONTH(LstMachines[[#This Row],[VteESM]]) & "-" & YEAR(LstMachines[[#This Row],[VteESM]]) -> 09-2017 | AF5: =LstMachines[[#This Row],[DateLivr]]+Rglt_à_ESMTP -> 42930 | AG5: =IF(MONTH(LstMachines[[#This Row],[RgltDistrib]])<10,"0","") & MONTH(LstMachines[[#This Row],[RgltDistrib]]) & "-" & YEAR(LstMachines[[#This Row],[RgltDistrib]]) -> 07-2017 | AH5: =LstMachines[[#This Row],[VteESM]]+Rglt_à_ESMTP -> 43050 | AI5: =IF(MONTH(LstMachines[[#This Row],[RgltVteESM]])<10,"0","") & MONTH(LstMachines[[#This Row],[RgltVteESM]]) & "-" & YEAR(LstMachines[[#This Row],[RgltVteESM]]) -> 11-2017 | AJ5: =MONTH(LstMachines[[#This Row],[DatePaie]]) -> 7 | AK5: =FIXED(YEAR(LstMachines[[#This Row],[DatePaie]]),0,TRUE) -> 2017
B6: Pelle/Chenilles | C6: ZX85 | D6: 85 | E6: ZX85USB-5A-Mono | F6: BTPS | G6: ORTHEZ | H6: 1 | I6: =IF(LstMachines[[#This Row],[Delivery]]<Début_HCME, 0, IFERROR( LstMachines[[#This Row],[Nbre]] * INDEX(TabModelSpecs[],MATCH(LstMachines[[#This Row],[Model-Spec]],TabModelSpecs[ModelSpec],0),MATCH("2018",TabModelSpecs[#Headers],0)), LstMachines[[#This Row],[Nbre]]*ROUND(AVERAGEIF(TabModelSpecs[Machine],LstMachines[[#This Row],[Model]],TabModelSpecs[Price]),0) ) ) -> 0 | J6: 42870 | K6: 1-Forecast | L6: 2017-11 BTPS | O6: =MONTH(LstMachines[[#This Row],[Delivery]]) -> 5 | P6: =FIXED(YEAR(LstMachines[[#This Row],[Delivery]]),0,TRUE) -> 2017 | X6: =LstMachines[[#This Row],[Delivery]] -> 42870 | Y6: =IF(MONTH(LstMachines[[#This Row],[DateLivr]])<10,"0","") & MONTH(LstMachines[[#This Row],[DateLivr]]) &"-"&YEAR(LstMachines[[#This Row],[DateLivr]]) -> 05-2017 | Z6: =LstMachines[[#This Row],[Delivery]]+Rglt_à_HCME -> 42930 | AA6: =IF(MONTH(LstMachines[[#This Row],[DatePaie]])<10,"0","") & MONTH(LstMachines[[#This Row],[DatePaie]])&"-"&YEAR(LstMachines[[#This Row],[DatePaie]]) -> 07-2017 | AB6: =LstMachines[[#This Row],[DateLivr]]+1 -> 42871 | AC6: =IF(MONTH(LstMachines[[#This Row],[Distrib]])<10,"0","") & MONTH(LstMachines[[#This Row],[Distrib]]) & "-" & YEAR(LstMachines[[#This Row],[Distrib]]) -> 05-2017 | AD6: =LstMachines[[#This Row],[DateLivr]]+Délai_Vente -> 42990 | AE6: =IF(MONTH(LstMachines[[#This Row],[VteESM]])<10,"0","") & MONTH(LstMachines[[#This Row],[VteESM]]) & "-" & YEAR(LstMachines[[#This Row],[VteESM]]) -> 09-2017 | AF6: =LstMachines[[#This Row],[DateLivr]]+Rglt_à_ESMTP -> 42930 | AG6: =IF(MONTH(LstMachines[[#This Row],[RgltDistrib]])<10,"0","") & MONTH(LstMachines[[#This Row],[RgltDistrib]]) & "-" & YEAR(LstMachines[[#This Row],[RgltDistrib]]) -> 07-2017 | AH6: =LstMachines[[#This Row],[VteESM]]+Rglt_à_ESMTP -> 43050 | AI6: =IF(MONTH(LstMachines[[#This Row],[RgltVteESM]])<10,"0","") & MONTH(LstMachines[[#This Row],[RgltVteESM]]) & "-" & YEAR(LstMachines[[#This Row],[RgltVteESM]]) -> 11-2017 | AJ6: =MONTH(LstMachines[[#This Row],[DatePaie]]) -> 7 | AK6: =FIXED(YEAR(LstMachines[[#This Row],[DatePaie]]),0,TRUE) -> 2017
B7: Pelle/Chenilles | C7: ZX190 | D7: 190 | E7: ZX190LC-6-MN | F7: SETP | G7: RABASTENS | H7: 1 | I7: =IF(LstMachines[[#This Row],[Delivery]]<Début_HCME, 0, IFERROR( LstMachines[[#This Row],[Nbre]] * INDEX(TabModelSpecs[],MATCH(LstMachines[[#This Row],[Model-Spec]],TabModelSpecs[ModelSpec],0),MATCH("2018",TabModelSpecs[#Headers],0)), LstMachines[[#This Row],[Nbre]]*ROUND(AVERAGEIF(TabModelSpecs[Machine],LstMachines[[#This Row],[Model]],TabModelSpecs[Price]),0) ) ) -> 0 | J7: 42901 | K7: 5-Livrée | L7: 2017-05 Forecast | O7: =MONTH(LstMachines[[#This Row],[Delivery]]) -> 6 | P7: =FIXED(YEAR(LstMachines[[#This Row],[Delivery]]),0,TRUE) -> 2017 | U7: VENTE | W7: _Location | X7: =LstMachines[[#This Row],[Delivery]] -> 42901 | Y7: =IF(MONTH(LstMachines[[#This Row],[DateLivr]])<10,"0","") & MONTH(LstMachines[[#This Row],[DateLivr]]) &"-"&YEAR(LstMachines[[#This Row],[DateLivr]]) -> 06-2017 | Z7: =LstMachines[[#This Row],[Delivery]]+Rglt_à_HCME -> 42961 | AA7: =IF(MONTH(LstMachines[[#This Row],[DatePaie]])<10,"0","") & MONTH(LstMachines[[#This Row],[DatePaie]])&"-"&YEAR(LstMachines[[#This Row],[DatePaie]]) -> 08-2017 | AB7: =LstMachines[[#This Row],[DateLivr]]+1 -> 42902 | AC7: =IF(MONTH(LstMachines[[#This Row],[Distrib]])<10,"0","") & MONTH(LstMachines[[#This Row],[Distrib]]) & "-" & YEAR(LstMachines[[#This Row],[Distrib]]) -> 06-2017 | AD7: =LstMachines[[#This Row],[DateLivr]]+Délai_Vente -> 43021 | AE7: =IF(MONTH(LstMachines[[#This Row],[VteESM]])<10,"0","") & MONTH(LstMachines[[#This Row],[VteESM]]) & "-" & YEAR(LstMachines[[#This Row],[VteESM]]) -> 10-2017 | AF7: =LstMachines[[#This Row],[DateLivr]]+Rglt_à_ESMTP -> 42961 | AG7: =IF(MONTH(LstMachines[[#This Row],[RgltDistrib]])<10,"0","") & MONTH(LstMachines[[#This Row],[RgltDistrib]]) & "-" & YEAR(LstMachines[[#This Row],[RgltDistrib]]) -> 08-2017 | AH7: =LstMachines[[#This Row],[VteESM]]+Rglt_à_ESMTP -> 43081 | AI7: =IF(MONTH(LstMachines[[#This Row],[RgltVteESM]])<10,"0","") & MONTH(LstMachines[[#This Row],[RgltVteESM]]) & "-" & YEAR(LstMachines[[#This Row],[RgltVteESM]]) -> 12-2017 | AJ7: =MONTH(LstMachines[[#This Row],[DatePaie]]) -> 8 | AK7: =FIXED(YEAR(LstMachines[[#This Row],[DatePaie]]),0,TRUE) -> 2017
B8: Pelle/Chenilles | C8: ZX300 | D8: 300 | E8: ZX300LCN-6-MN | F8: SETP | H8: 1 | I8: =IF(LstMachines[[#This Row],[Delivery]]<Début_HCME, 0, IFERROR( LstMachines[[#This Row],[Nbre]] * INDEX(TabModelSpecs[],MATCH(LstMachines[[#This Row],[Model-Spec]],TabModelSpecs[ModelSpec],0),MATCH("2018",TabModelSpecs[#Headers],0)), LstMachines[[#This Row],[Nbre]]*ROUND(AVERAGEIF(TabModelSpecs[Machine],LstMachines[[#This Row],[Model]],TabModelSpecs[Price]),0) ) ) -> 0 | J8: 42901 | K8: 5-Livrée | L8: 2017-10 ADV | N8: 42795 | O8: =MONTH(LstMachines[[#This Row],[Delivery]]) -> 6 | P8: =FIXED(YEAR(LstMachines[[#This Row],[Delivery]]),0,TRUE) -> 2017 | X8: =LstMachines[[#This Row],[Delivery]] -> 42901 | Y8: =IF(MONTH(LstMachines[[#This Row],[DateLivr]])<10,"0","") & MONTH(LstMachines[[#This Row],[DateLivr]]) &"-"&YEAR(LstMachines[[#This Row],[DateLivr]]) -> 06-2017 | Z8: =LstMachines[[#This Row],[Delivery]]+Rglt_à_HCME -> 42961 | AA8: =IF(MONTH(LstMachines[[#This Row],[DatePaie]])<10,"0","") & MONTH(LstMachines[[#This Row],[DatePaie]])&"-"&YEAR(LstMachines[[#This Row],[DatePaie]]) -> 08-2017 | AB8: =LstMachines[[#This Row],[DateLivr]]+1 -> 42902 | AC8: =IF(MONTH(LstMachines[[#This Row],[Distrib]])<10,"0","") & MONTH(LstMachines[[#This Row],[Distrib]]) & "-" & YEAR(LstMachines[[#This Row],[Distrib]]) -> 06-2017 | AD8: =LstMachines[[#This Row],[DateLivr]]+Délai_Vente -> 43021 | AE8: =IF(MONTH(LstMachines[[#This Row],[VteESM]])<10,"0","") & MONTH(LstMachines[[#This Row],[VteESM]]) & "-" & YEAR(LstMachines[[#This Row],[VteESM]]) -> 10-2017 | AF8: =LstMachines[[#This Row],[DateLivr]]+Rglt_à_ESMTP -> 42961 | AG8: =IF(MONTH(LstMachines[[#This Row],[RgltDistrib]])<10,"0","") & MONTH(LstMachines[[#This Row],[RgltDistrib]]) & "-" & YEAR(LstMachines[[#This Row],[RgltDistrib]]) -> 08-2017 | AH8: =LstMachines[[#This Row],[VteESM]]+Rglt_à_ESMTP -> 43081 | AI8: =IF(MONTH(LstMachines[[#This Row],[RgltVteESM]])<10,"0","") & MONTH(LstMachines[[#This Row],[RgltVteESM]]) & "-" & YEAR(LstMachines[[#This Row],[RgltVteESM]]) -> 12-2017 | AJ8: =MONTH(LstMachines[[#This Row],[DatePaie]]) -> 8 | AK8: =FIXED(YEAR(LstMachines[[#This Row],[DatePaie]]),0,TRUE) -> 2017
B9: Pelle/Chenilles | C9: ZX85 | D9: 85 | E9: ZX85USB-5A-Mono | F9: SETP | G9: RABASTENS | H9: 1 | I9: =IF(LstMachines[[#This Row],[Delivery]]<Début_HCME, 0, IFERROR( LstMachines[[#This Row],[Nbre]] * INDEX(TabModelSpecs[],MATCH(LstMachines[[#This Row],[Model-Spec]],TabModelSpecs[ModelSpec],0),MATCH("2018",TabModelSpecs[#Headers],0)), LstMachines[[#This Row],[Nbre]]*ROUND(AVERAGEIF(TabModelSpecs[Machine],LstMachines[[#This Row],[Model]],TabModelSpecs[Price]),0) ) ) -> 0 | J9: 42931 | K9: 5-Livrée | L9: 2017-10 ADV | N9: 42853 | O9: =MONTH(LstMachines[[#This Row],[Delivery]]) -> 7 | P9: =FIXED(YEAR(LstMachines[[#This Row],[Delivery]]),0,TRUE) -> 2017 | Q9: 17040041 | R9: 56981 | T9: 1-05114-1 | U9: VENTE | V9: 4111 | W9: RECTANGLE BLEU | X9: =LstMachines[[#This Row],[Delivery]] -> 42931 | Y9: =IF(MONTH(LstMachines[[#This Row],[DateLivr]])<10,"0","") & MONTH(LstMachines[[#This Row],[DateLivr]]) &"-"&YEAR(LstMachines[[#This Row],[DateLivr]]) -> 07-2017 | Z9: =LstMachines[[#This Row],[Delivery]]+Rglt_à_HCME -> 42991 | AA9: =IF(MONTH(LstMachines[[#This Row],[DatePaie]])<10,"0","") & MONTH(LstMachines[[#This Row],[DatePaie]])&"-"&YEAR(LstMachines[[#This Row],[DatePaie]]) -> 09-2017 | AB9: =LstMachines[[#This Row],[DateLivr]]+1 -> 42932 | AC9: =IF(MONTH(LstMachines[[#This Row],[Distrib]])<10,"0","") & MONTH(LstMachines[[#This Row],[Distrib]]) & "-" & YEAR(LstMachines[[#This Row],[Distrib]]) -> 07-2017 | AD9: =LstMachines[[#This Row],[DateLivr]]+Délai_Vente -> 43051 | AE9: =IF(MONTH(LstMachines[[#This Row],[VteESM]])<10,"0","") & MONTH(LstMachines[[#This Row],[VteESM]]) & "-" & YEAR(LstMachines[[#This Row],[VteESM]]) -> 11-2017 | AF9: =LstMachines[[#This Row],[DateLivr]]+Rglt_à_ESMTP -> 42991 | AG9: =IF(MONTH(LstMachines[[#This Row],[RgltDistrib]])<10,"0","") & MONTH(LstMachines[[#This Row],[RgltDistrib]]) & "-" & YEAR(LstMachines[[#This Row],[RgltDistrib]]) -> 09-2017 | AH9: =LstMachines[[#This Row],[VteESM]]+Rglt_à_ESMTP -> 43111 | AI9: =IF(MONTH(LstMachines[[#This Row],[RgltVteESM]])<10,"0","") & MONTH(LstMachines[[#This Row],[RgltVteESM]]) & "-" & YEAR(LstMachines[[#This Row],[RgltVteESM]]) -> 01-2018 | AJ9: =MONTH(LstMachines[[#This Row],[DatePaie]]) -> 9 | AK9: =FIXED(YEAR(LstMachines[[#This Row],[DatePaie]]),0,TRUE) -> 2017
B10: Chargeuse | C10: ZW180 | D10: 180 | E10: ZW180-6-TPD | F10: SETP | G10: RABASTENS | H10: 1 | I10: =IF(LstMachines[[#This Row],[Delivery]]<Début_HCME, 0, IFERROR( LstMachines[[#This Row],[Nbre]] * INDEX(TabModelSpecs[],MATCH(LstMachines[[#This Row],[Model-Spec]],TabModelSpecs[ModelSpec],0),MATCH("2018",TabModelSpecs[#Headers],0)), LstMachines[[#This Row],[Nbre]]*ROUND(AVERAGEIF(TabModelSpecs[Machine],LstMachines[[#This Row],[Model]],TabModelSpecs[Price]),0) ) ) -> 0 | J10: 42962 | K10: 5-Livrée | L10: 2017-12-06 ADV | N10: 42853 | O10: =MONTH(LstMachines[[#This Row],[Delivery]]) -> 8 | P10: =FIXED(YEAR(LstMachines[[#This Row],[Delivery]]),0,TRUE) -> 2017 | Q10: 17040092 | R10: 101896 | T10: 1-04917-1 798 | U10: VENTE | V10: 4118 | W10: CARCELLER | X10: =LstMachines[[#This Row],[Delivery]] -> 42962 | Y10: =IF(MONTH(LstMachines[[#This Row],[DateLivr]])<10,"0","") & MONTH(LstMachines[[#This Row],[DateLivr]]) &"-"&YEAR(LstMachines[[#This Row],[DateLivr]]) -> 08-2017 | Z10: =LstMachines[[#This Row],[Delivery]]+Rglt_à_HCME -> 43022 | AA10: =IF(MONTH(LstMachines[[#This Row],[DatePaie]])<10,"0","") & MONTH(LstMachines[[#This Row],[DatePaie]])&"-"&YEAR(LstMachines[[#This Row],[DatePaie]]) -> 10-2017 | AB10: =LstMachines[[#This Row],[DateLivr]]+1 -> 42963 | AC10: =IF(MONTH(LstMachines[[#This Row],[Distrib]])<10,"0","") & MONTH(LstMachines[[#This Row],[Distrib]]) & "-" & YEAR(LstMachines[[#This Row],[Distrib]]) -> 08-2017 | AD10: =LstMachines[[#This Row],[DateLivr]]+Délai_Vente -> 43082 | AE10: =IF(MONTH(LstMachines[[#This Row],[VteESM]])<10,"0","") & MONTH(LstMachines[[#This Row],[VteESM]]) & "-" & YEAR(LstMachines[[#This Row],[VteESM]]) -> 12-2017 | AF10: =LstMachines[[#This Row],[DateLivr]]+Rglt_à_ESMTP -> 43022 | AG10: =IF(MONTH(LstMachines[[#This Row],[RgltDistrib]])<10,"0","") & MONTH(LstMachines[[#This Row],[RgltDistrib]]) & "-" & YEAR(LstMachines[[#This Row],[RgltDistrib]]) -> 10-2017 | AH10: =LstMachines[[#This Row],[VteESM]]+Rglt_à_ESMTP -> 43142 | AI10: =IF(MONTH(LstMachines[[#This Row],[RgltVteESM]])<10,"0","") & MONTH(LstMachines[[#This Row],[RgltVteESM]]) & "-" & YEAR(LstMachines[[#This Row],[RgltVteESM]]) -> 02-2018 | AJ10: =MONTH(LstMachines[[#This Row],[DatePaie]]) -> 10 | AK10: =FIXED(YEAR(LstMachines[[#This Row],[DatePaie]]),0,TRUE) -> 2017
B11: Pelle/Chenilles | C11: ZX135 | D11: 135 | E11: ZX135US-6-2P-BL | F11: SETP | G11: RABASTENS | H11: 1 | I11: =IF(LstMachines[[#This Row],[Delivery]]<Début_HCME, 0, IFERROR( LstMachines[[#This Row],[Nbre]] * INDEX(TabModelSpecs[],MATCH(LstMachines[[#This Row],[Model-Spec]],TabModelSpecs[ModelSpec],0),MATCH("2018",TabModelSpecs[#Headers],0)), LstMachines[[#This Row],[Nbre]]*ROUND(AVERAGEIF(TabModelSpecs[Machine],LstMachines[[#This Row],[Model]],TabModelSpecs[Price]),0) ) ) -> 0 | J11: 42962 | K11: 5-Livrée | L11: 2017-10 ADV | N11: 42794 | O11: =MONTH(LstMachines[[#This Row],[Delivery]]) -> 8 | P11: =FIXED(YEAR(LstMachines[[#This Row],[Delivery]]),0,TRUE) -> 2017 | Q11: 17020004 | R11: 105100 | T11: 1-04628-1 821 | U11: VENTE | V11: 4188 | W11: NEROCAN | X11: =LstMachines[[#This Row],[Delivery]] -> 42962 | Y11: =IF(MONTH(LstMachines[[#This Row],[DateLivr]])<10,"0","") & MONTH(LstMachines[[#This Row],[DateLivr]]) &"-"&YEAR(LstMachines[[#This Row],[DateLivr]]) -> 08-2017 | Z11: =LstMachines[[#This Row],[Delivery]]+Rglt_à_HCME -> 43022 | AA11: =IF(MONTH(LstMachines[[#This Row],[DatePaie]])<10,"0","") & MONTH(LstMachines[[#This Row],[DatePaie]])&"-"&YEAR(LstMachines[[#This Row],[DatePaie]]) -> 10-2017 | AB11: =LstMachines[[#This Row],[DateLivr]]+1 -> 42963 | AC11: =IF(MONTH(LstMachines[[#This Row],[Distrib]])<10,"0","") & MONTH(LstMachines[[#This Row],[Distrib]]) & "-" & YEAR(LstMachines[[#This Row],[Distrib]]) -> 08-2017 | AD11: =LstMachines[[#This Row],[DateLivr]]+Délai_Vente -> 43082 | AE11: =IF(MONTH(LstMachines[[#This Row],[VteESM]])<10,"0","") & MONTH(LstMachines[[#This Row],[VteESM]]) & "-" & YEAR(LstMachines[[#This Row],[VteESM]]) -> 12-2017 | AF11: =LstMachines[[#This Row],[DateLivr]]+Rglt_à_ESMTP -> 43022 | AG11: =IF(MONTH(LstMachines[[#This Row],[RgltDistrib]])<10,"0","") & MONTH(LstMachines[[#This Row],[RgltDistrib]]) & "-" & YEAR(LstMachines[[#This Row],[RgltDistrib]]) -> 10-2017 | AH11: =LstMachines[[#This Row],[VteESM]]+Rglt_à_ESMTP -> 43142 | AI11: =IF(MONTH(LstMachines[[#This Row],[RgltVteESM]])<10,"0","") & MONTH(LstMachines[[#This Row],[RgltVteESM]]) & "-" & YEAR(LstMachines[[#This Row],[RgltVteESM]]) -> 02-2018 | AJ11: =MONTH(LstMachines[[#This Row],[DatePaie]]) -> 10 | AK11: =FIXED(YEAR(LstMachines[[#This Row],[DatePaie]]),0,TRUE) -> 2017
B12: Pelle/Chenilles | C12: ZX85 | D12: 85 | E12: ZX85USB-5A-Mono | F12: SETP | G12: RABASTENS | H12: 1 | I12: =IF(LstMachines[[#This Row],[Delivery]]<Début_HCME, 0, IFERROR( LstMachines[[#This Row],[Nbre]] * INDEX(TabModelSpecs[],MATCH(LstMachines[[#This Row],[Model-Spec]],TabModelSpecs[ModelSpec],0),MATCH("2018",TabModelSpecs[#Headers],0)), LstMachines[[#This Row],[Nbre]]*ROUND(AVERAGEIF(TabModelSpecs[Machine],LstMachines[[#This Row],[Model]],TabModelSpecs[Price]),0) ) ) -> 0 | J12: 42962 | K12: 5-Livrée | L12: 2017-10 ADV | N12: 42853 | O12: =MONTH(LstMachines[[#This Row],[Delivery]]) -> 8 | P12: =FIXED(YEAR(LstMachines[[#This Row],[Delivery]]),0,TRUE) -> 2017 | Q12: 17040042 | R12: 56981 | T12: 1-05115-1 820 | U12: VENTE | V12: 4112 | W12: PRUNET | X12: =LstMachines[[#This Row],[Delivery]] -> 42962 | Y12: =IF(MONTH(LstMachines[[#This Row],[DateLivr]])<10,"0","") & MONTH(LstMachines[[#This Row],[DateLivr]]) &"-"&YEAR(LstMachines[[#This Row],[DateLivr]]) -> 08-2017 | Z12: =LstMachines[[#This Row],[Delivery]]+Rglt_à_HCME -> 43022 | AA12: =IF(MONTH(LstMachines[[#This Row],[DatePaie]])<10,"0","") & MONTH(LstMachines[[#This Row],[DatePaie]])&"-"&YEAR(LstMachines[[#This Row],[DatePaie]]) -> 10-2017 | AB12: =LstMachines[[#This Row],[DateLivr]]+1 -> 42963 | AC12: =IF(MONTH(LstMachines[[#This Row],[Distrib]])<10,"0","") & MONTH(LstMachines[[#This Row],[Distrib]]) & "-" & YEAR(LstMachines[[#This Row],[Distrib]]) -> 08-2017 | AD12: =LstMachines[[#This Row],[DateLivr]]+Délai_Vente -> 43082 | AE12: =IF(MONTH(LstMachines[[#This Row],[VteESM]])<10,"0","") & MONTH(LstMachines[[#This Row],[VteESM]]) & "-" & YEAR(LstMachines[[#This Row],[VteESM]]) -> 12-2017 | AF12: =LstMachines[[#This Row],[DateLivr]]+Rglt_à_ESMTP -> 43022 | AG12: =IF(MONTH(LstMachines[[#This Row],[RgltDistrib]])<10,"0","") & MONTH(LstMachines[[#This Row],[RgltDistrib]]) & "-" & YEAR(LstMachines[[#This Row],[RgltDistrib]]) -> 10-2017 | AH12: =LstMachines[[#This Row],[VteESM]]+Rglt_à_ESMTP -> 43142 | AI12: =IF(MONTH(LstMachines[[#This Row],[RgltVteESM]])<10,"0","") & MONTH(LstMachines[[#This Row],[RgltVteESM]]) & "-" & YEAR(LstMachines[[#This Row],[RgltVteESM]]) -> 02-2018 | AJ12: =MONTH(LstMachines[[#This Row],[DatePaie]]) -> 10 | AK12: =FIXED(YEAR(LstMachines[[#This Row],[DatePaie]]),0,TRUE) -> 2017
B13: Pelle/Pneus | C13: ZX145 | D13: 145 | E13: ZX145W-6-2P | F13: SETP | G13: RABASTENS | H13: 1 | I13: =IF(LstMachines[[#This Row],[Delivery]]<Début_HCME, 0, IFERROR( LstMachines[[#This Row],[Nbre]] * INDEX(TabModelSpecs[],MATCH(LstMachines[[#This Row],[Model-Spec]],TabModelSpecs[ModelSpec],0),MATCH("2018",TabModelSpecs[#Headers],0)), LstMachines[[#This Row],[Nbre]]*ROUND(AVERAGEIF(TabModelSpecs[Machine],LstMachines[[#This Row],[Model]],TabModelSpecs[Price]),0) ) ) -> 0 | J13: 42962 | K13: ** Lost ** | L13: 2017-10 ADV | M13: ** Lost ** | N13: 42887 | O13: =MONTH(LstMachines[[#This Row],[Delivery]]) -> 8 | P13: =FIXED(YEAR(LstMachines[[#This Row],[Delivery]]),0,TRUE) -> 2017 | X13: =LstMachines[[#This Row],[Delivery]] -> 42962 | Y13: =IF(MONTH(LstMachines[[#This Row],[DateLivr]])<10,"0","") & MONTH(LstMachines[[#This Row],[DateLivr]]) &"-"&YEAR(LstMachines[[#This Row],[DateLivr]]) -> 08-2017 | Z13: =LstMachines[[#This Row],[Delivery]]+Rglt_à_HCME -> 43022 | AA13: =IF(MONTH(LstMachines[[#This Row],[DatePaie]])<10,"0","") & MONTH(LstMachines[[#This Row],[DatePaie]])&"-"&YEAR(LstMachines[[#This Row],[DatePaie]]) -> 10-2017 | AB13: =LstMachines[[#This Row],[DateLivr]]+1 -> 42963 | AC13: =IF(MONTH(LstMachines[[#This Row],[Distrib]])<10,"0","") & MONTH(LstMachines[[#This Row],[Distrib]]) & "-" & YEAR(LstMachines[[#This Row],[Distrib]]) -> 08-2017 | AD13: =LstMachines[[#This Row],[DateLivr]]+Délai_Vente -> 43082 | AE13: =IF(MONTH(LstMachines[[#This Row],[VteESM]])<10,"0","") & MONTH(LstMachines[[#This Row],[VteESM]]) & "-" & YEAR(LstMachines[[#This Row],[VteESM]]) -> 12-2017 | AF13: =LstMachines[[#This Row],[DateLivr]]+Rglt_à_ESMTP -> 43022 | AG13: =IF(MONTH(LstMachines[[#This Row],[RgltDistrib]])<10,"0","") & MONTH(LstMachines[[#This Row],[RgltDistrib]]) & "-" & YEAR(LstMachines[[#This Row],[RgltDistrib]]) -> 10-2017 | AH13: =LstMachines[[#This Row],[VteESM]]+Rglt_à_ESMTP -> 43142 | AI13: =IF(MONTH(LstMachines[[#This Row],[RgltVteESM]])<10,"0","") & MONTH(LstMachines[[#This Row],[RgltVteESM]]) & "-" & YEAR(LstMachines[[#This Row],[RgltVteESM]]) -> 02-2018 | AJ13: =MONTH(LstMachines[[#This Row],[DatePaie]]) -> 10 | AK13: =FIXED(YEAR(LstMachines[[#This Row],[DatePaie]]),0,TRUE) -> 2017
B14: Pelle/Chenilles | C14: ZX225 | D14: 225 | E14: ZX225USLC-6-2P-BL | F14: SETP | G14: RABASTENS | H14: 1 | I14: =IF(LstMachines[[#This Row],[Delivery]]<Début_HCME, 0, IFERROR( LstMachines[[#This Row],[Nbre]] * INDEX(TabModelSpecs[],MATCH(LstMachines[[#This Row],[Model-Spec]],TabModelSpecs[ModelSpec],0),MATCH("2018",TabModelSpecs[#Headers],0)), LstMachines[[#This Row],[Nbre]]*ROUND(AVERAGEIF(TabModelSpecs[Machine],LstMachines[[#This Row],[Model]],TabModelSpecs[Price]),0) ) ) -> 0 | J14: 42993 | K14: 5-Livrée | L14: 2017-10 ADV | N14: 42901 | O14: =MONTH(LstMachines[[#This Row],[Delivery]]) -> 9 | P14: =FIXED(YEAR(LstMachines[[#This Row],[Delivery]]),0,TRUE) -> 2017 | U14: VENTE | W14: TDA | X14: =LstMachines[[#This Row],[Delivery]] -> 42993 | Y14: =IF(MONTH(LstMachines[[#This Row],[DateLivr]])<10,"0","") & MONTH(LstMachines[[#This Row],[DateLivr]]) &"-"&YEAR(LstMachines[[#This Row],[DateLivr]]) -> 09-2017 | Z14: =LstMachines[[#This Row],[Delivery]]+Rglt_à_HCME -> 43053 | AA14: =IF(MONTH(LstMachines[[#This Row],[DatePaie]])<10,"0","") & MONTH(LstMachines[[#This Row],[DatePaie]])&"-"&YEAR(LstMachines[[#This Row],[DatePaie]]) -> 11-2017 | AB14: =LstMachines[[#This Row],[DateLivr]]+1 -> 42994 | AC14: =IF(MONTH(LstMachines[[#This Row],[Distrib]])<10,"0","") & MONTH(LstMachines[[#This Row],[Distrib]]) & "-" & YEAR(LstMachines[[#This Row],[Distrib]]) -> 09-2017 | AD14: =LstMachines[[#This Row],[DateLivr]]+Délai_Vente -> 43113 | AE14: =IF(MONTH(LstMachines[[#This Row],[VteESM]])<10,"0","") & MONTH(LstMachines[[#This Row],[VteESM]]) & "-" & YEAR(LstMachines[[#This Row],[VteESM]]) -> 01-2018 | AF14: =LstMachines[[#This Row],[DateLivr]]+Rglt_à_ESMTP -> 43053 | AG14: =IF(MONTH(LstMachines[[#This Row],[RgltDistrib]])<10,"0","") & MONTH(LstMachines[[#This Row],[RgltDistrib]]) & "-" & YEAR(LstMachines[[#This Row],[RgltDistrib]]) -> 11-2017 | AH14: =LstMachines[[#This Row],[VteESM]]+Rglt_à_ESMTP -> 43173 | AI14: =IF(MONTH(LstMachines[[#This Row],[RgltVteESM]])<10,"0","") & MONTH(LstMachines[[#This Row],[RgltVteESM]]) & "-" & YEAR(LstMachines[[#This Row],[RgltVteESM]]) -> 03-2018 | AJ14: =MONTH(LstMachines[[#This Row],[DatePaie]]) -> 11 | AK14: =FIXED(YEAR(LstMachines[[#This Row],[DatePaie]]),0,TRUE) -> 2017
B15: Mini Pelle | C15: ZX33 | D15: 33 | E15: ZX33U-5-CLR | F15: SETP | G15: RABASTENS | H15: 1 | I15: =IF(LstMachines[[#This Row],[Delivery]]<Début_HCME, 0, IFERROR( LstMachines[[#This Row],[Nbre]] * INDEX(TabModelSpecs[],MATCH(LstMachines[[#This Row],[Model-Spec]],TabModelSpecs[ModelSpec],0),MATCH("2018",TabModelSpecs[#Headers],0)), LstMachines[[#This Row],[Nbre]]*ROUND(AVERAGEIF(TabModelSpecs[Machine],LstMachines[[#This Row],[Model]],TabModelSpecs[Price]),0) ) ) -> 0 | J15: 42993 | K15: 5-Livrée | L15: 2017-10 ADV | N15: 42822 | O15: =MONTH(LstMachines[[#This Row],[Delivery]]) -> 9 | P15: =FIXED(YEAR(LstMachines[[#This Row],[Delivery]]),0,TRUE) -> 2017 | Q15: 17030057 | R15: 29000 | S15: à financer | T15: 1-04906-1 792 | U15: VENTE | V15: 4094 | W15: CITELIUM | X15: =LstMachines[[#This Row],[Delivery]] -> 42993 | Y15: =IF(MONTH(LstMachines[[#This Row],[DateLivr]])<10,"0","") & MONTH(LstMachines[[#This Row],[DateLivr]]) &"-"&YEAR(LstMachines[[#This Row],[DateLivr]]) -> 09-2017 | Z15: =LstMachines[[#This Row],[Delivery]]+Rglt_à_HCME -> 43053 | AA15: =IF(MONTH(LstMachines[[#This Row],[DatePaie]])<10,"0","") & MONTH(LstMachines[[#This Row],[DatePaie]])&"-"&YEAR(LstMachines[[#This Row],[DatePaie]]) -> 11-2017 | AB15: =LstMachines[[#This Row],[DateLivr]]+1 -> 42994 | AC15: =IF(MONTH(LstMachines[[#This Row],[Distrib]])<10,"0","") & MONTH(LstMachines[[#This Row],[Distrib]]) & "-" & YEAR(LstMachines[[#This Row],[Distrib]]) -> 09-2017 | AD15: =LstMachines[[#This Row],[DateLivr]]+Délai_Vente -> 43113 | AE15: =IF(MONTH(LstMachines[[#This Row],[VteESM]])<10,"0","") & MONTH(LstMachines[[#This Row],[VteESM]]) & "-" & YEAR(LstMachines[[#This Row],[VteESM]]) -> 01-2018 | AF15: =LstMachines[[#This Row],[DateLivr]]+Rglt_à_ESMTP -> 43053 | AG15: =IF(MONTH(LstMachines[[#This Row],[RgltDistrib]])<10,"0","") & MONTH(LstMachines[[#This Row],[RgltDistrib]]) & "-" & YEAR(LstMachines[[#This Row],[RgltDistrib]]) -> 11-2017 | AH15: =LstMachines[[#This Row],[VteESM]]+Rglt_à_ESMTP -> 43173 | AI15: =IF(MONTH(LstMachines[[#This Row],[RgltVteESM]])<10,"0","") & MONTH(LstMachines[[#This Row],[RgltVteESM]]) & "-" & YEAR(LstMachines[[#This Row],[RgltVteESM]]) -> 03-2018 | AJ15: =MONTH(LstMachines[[#This Row],[DatePaie]]) -> 11 | AK15: =FIXED(YEAR(LstMachines[[#This Row],[DatePaie]]),0,TRUE) -> 2017
B16: Pelle/Chenilles | C16: ZX85 | D16: 85 | E16: ZX85USB-5A-Mono | F16: SETP | G16: RABASTENS | H16: 1 | I16: =IF(LstMachines[[#This Row],[Delivery]]<Début_HCME, 0, IFERROR( LstMachines[[#This Row],[Nbre]] * INDEX(TabModelSpecs[],MATCH(LstMachines[[#This Row],[Model-Spec]],TabModelSpecs[ModelSpec],0),MATCH("2018",TabModelSpecs[#Headers],0)), LstMachines[[#This Row],[Nbre]]*ROUND(AVERAGEIF(TabModelSpecs[Machine],LstMachines[[#This Row],[Model]],TabModelSpecs[Price]),0) ) ) -> 0 | J16: 42993 | K16: 5-Livrée | L16: 2017-10 ADV | N16: 42975 | O16: =MONTH(LstMachines[[#This Row],[Delivery]]) -> 9 | P16: =FIXED(YEAR(LstMachines[[#This Row],[Delivery]]),0,TRUE) -> 2017 | Q16: 17080105 | R16: 56981 | U16: VENTE | V16: 4183 | W16: TEPASSO | X16: =LstMachines[[#This Row],[Delivery]] -> 42993 | Y16: =IF(MONTH(LstMachines[[#This Row],[DateLivr]])<10,"0","") & MONTH(LstMachines[[#This Row],[DateLivr]]) &"-"&YEAR(LstMachines[[#This Row],[DateLivr]]) -> 09-2017 | Z16: =LstMachines[[#This Row],[Delivery]]+Rglt_à_HCME -> 43053 | AA16: =IF(MONTH(LstMachines[[#This Row],[DatePaie]])<10,"0","") & MONTH(LstMachines[[#This Row],[DatePaie]])&"-"&YEAR(LstMachines[[#This Row],[DatePaie]]) -> 11-2017 | AB16: =LstMachines[[#This Row],[DateLivr]]+1 -> 42994 | AC16: =IF(MONTH(LstMachines[[#This Row],[Distrib]])<10,"0","") & MONTH(LstMachines[[#This Row],[Distrib]]) & "-" & YEAR(LstMachines[[#This Row],[Distrib]]) -> 09-2017 | AD16: =LstMachines[[#This Row],[DateLivr]]+Délai_Vente -> 43113 | AE16: =IF(MONTH(LstMachines[[#This Row],[VteESM]])<10,"0","") & MONTH(LstMachines[[#This Row],[VteESM]]) & "-" & YEAR(LstMachines[[#This Row],[VteESM]]) -> 01-2018 | AF16: =LstMachines[[#This Row],[DateLivr]]+Rglt_à_ESMTP -> 43053 | AG16: =IF(MONTH(LstMachines[[#This Row],[RgltDistrib]])<10,"0","") & MONTH(LstMachines[[#This Row],[RgltDistrib]]) & "-" & YEAR(LstMachines[[#This Row],[RgltDistrib]]) -> 11-2017 | AH16: =LstMachines[[#This Row],[VteESM]]+Rglt_à_ESMTP -> 43173 | AI16: =IF(MONTH(LstMachines[[#This Row],[RgltVteESM]])<10,"0","") & MONTH(LstMachines[[#This Row],[RgltVteESM]]) & "-" & YEAR(LstMachines[[#This Row],[RgltVteESM]]) -> 03-2018 | AJ16: =MONTH(LstMachines[[#This Row],[DatePaie]]) -> 11 | AK16: =FIXED(YEAR(LstMachines[[#This Row],[DatePaie]]),0,TRUE) -> 2017
B17: Pelle/Chenilles | C17: ZX300 | D17: 300 | E17: ZX300LCN-6-MN | F17: SETP | G17: RABASTENS | H17: 1 | I17: =IF(LstMachines[[#This Row],[Delivery]]<Début_HCME, 0, IFERROR( LstMachines[[#This Row],[Nbre]] * INDEX(TabModelSpecs[],MATCH(LstMachines[[#This Row],[Model-Spec]],TabModelSpecs[ModelSpec],0),MATCH("2018",TabModelSpecs[#Headers],0)), LstMachines[[#This Row],[Nbre]]*ROUND(AVERAGEIF(TabModelSpecs[Machine],LstMachines[[#This Row],[Model]],TabModelSpecs[Price]),0) ) ) -> 0 | J17: 42993 | K17: 1-Forecast | L17: 2017-05 Forecast | O17: =MONTH(LstMachines[[#This Row],[Delivery]]) -> 9 | P17: =FIXED(YEAR(LstMachines[[#This Row],[Delivery]]),0,TRUE) -> 2017 | U17: VENTE | W17: _Stock | X17: =LstMachines[[#This Row],[Delivery]] -> 42993 | Y17: =IF(MONTH(LstMachines[[#This Row],[DateLivr]])<10,"0","") & MONTH(LstMachines[[#This Row],[DateLivr]]) &"-"&YEAR(LstMachines[[#This Row],[DateLivr]]) -> 09-2017 | Z17: =LstMachines[[#This Row],[Delivery]]+Rglt_à_HCME -> 43053 | AA17: =IF(MONTH(LstMachines[[#This Row],[DatePaie]])<10,"0","") & MONTH(LstMachines[[#This Row],[DatePaie]])&"-"&YEAR(LstMachines[[#This Row],[DatePaie]]) -> 11-2017 | AB17: =LstMachines[[#This Row],[DateLivr]]+1 -> 42994 | AC17: =IF(MONTH(LstMachines[[#This Row],[Distrib]])<10,"0","") & MONTH(LstMachines[[#This Row],[Distrib]]) & "-" & YEAR(LstMachines[[#This Row],[Distrib]]) -> 09-2017 | AD17: =LstMachines[[#This Row],[DateLivr]]+Délai_Vente -> 43113 | AE17: =IF(MONTH(LstMachines[[#This Row],[VteESM]])<10,"0","") & MONTH(LstMachines[[#This Row],[VteESM]]) & "-" & YEAR(LstMachines[[#This Row],[VteESM]]) -> 01-2018 | AF17: =LstMachines[[#This Row],[DateLivr]]+Rglt_à_ESMTP -> 43053 | AG17: =IF(MONTH(LstMachines[[#This Row],[RgltDistrib]])<10,"0","") & MONTH(LstMachines[[#This Row],[RgltDistrib]]) & "-" & YEAR(LstMachines[[#This Row],[RgltDistrib]]) -> 11-2017 | AH17: =LstMachines[[#This Row],[VteESM]]+Rglt_à_ESMTP -> 43173 | AI17: =IF(MONTH(LstMachines[[#This Row],[RgltVteESM]])<10,"0","") & MONTH(LstMachines[[#This Row],[RgltVteESM]]) & "-" & YEAR(LstMachines[[#This Row],[RgltVteESM]]) -> 03-2018 | AJ17: =MONTH(LstMachines[[#This Row],[DatePaie]]) -> 11 | AK17: =FIXED(YEAR(LstMachines[[#This Row],[DatePaie]]),0,TRUE) -> 2017
B18: Pelle/Pneus | C18: ZX145 | D18: 145 | E18: ZX145W-6-2P | F18: SETP | G18: RABASTENS | H18: 1 | I18: =IF(LstMachines[[#This Row],[Delivery]]<Début_HCME, 0, IFERROR( LstMachines[[#This Row],[Nbre]] * INDEX(TabModelSpecs[],MATCH(LstMachines[[#This Row],[Model-Spec]],TabModelSpecs[ModelSpec],0),MATCH("2018",TabModelSpecs[#Headers],0)), LstMachines[[#This Row],[Nbre]]*ROUND(AVERAGEIF(TabModelSpecs[Machine],LstMachines[[#This Row],[Model]],TabModelSpecs[Price]),0) ) ) -> 0 | J18: 42993 | K18: ** Lost ** | L18: 2017-10 ADV | M18: ** Lost ** | N18: 42979 | O18: =MONTH(LstMachines[[#This Row],[Delivery]]) -> 9 | P18: =FIXED(YEAR(LstMachines[[#This Row],[Delivery]]),0,TRUE) -> 2017 | X18: =LstMachines[[#This Row],[Delivery]] -> 42993 | Y18: =IF(MONTH(LstMachines[[#This Row],[DateLivr]])<10,"0","") & MONTH(LstMachines[[#This Row],[DateLivr]]) &"-"&YEAR(LstMachines[[#This Row],[DateLivr]]) -> 09-2017 | Z18: =LstMachines[[#This Row],[Delivery]]+Rglt_à_HCME -> 43053 | AA18: =IF(MONTH(LstMachines[[#This Row],[DatePaie]])<10,"0","") & MONTH(LstMachines[[#This Row],[DatePaie]])&"-"&YEAR(LstMachines[[#This Row],[DatePaie]]) -> 11-2017 | AB18: =LstMachines[[#This Row],[DateLivr]]+1 -> 42994 | AC18: =IF(MONTH(LstMachines[[#This Row],[Distrib]])<10,"0","") & MONTH(LstMachines[[#This Row],[Distrib]]) & "-" & YEAR(LstMachines[[#This Row],[Distrib]]) -> 09-2017 | AD18: =LstMachines[[#This Row],[DateLivr]]+Délai_Vente -> 43113 | AE18: =IF(MONTH(LstMachines[[#This Row],[VteESM]])<10,"0","") & MONTH(LstMachines[[#This Row],[VteESM]]) & "-" & YEAR(LstMachines[[#This Row],[VteESM]]) -> 01-2018 | AF18: =LstMachines[[#This Row],[DateLivr]]+Rglt_à_ESMTP -> 43053 | AG18: =IF(MONTH(LstMachines[[#This Row],[RgltDistrib]])<10,"0","") & MONTH(LstMachines[[#This Row],[RgltDistrib]]) & "-" & YEAR(LstMachines[[#This Row],[RgltDistrib]]) -> 11-2017 | AH18: =LstMachines[[#This Row],[VteESM]]+Rglt_à_ESMTP -> 43173 | AI18: =IF(MONTH(LstMachines[[#This Row],[RgltVteESM]])<10,"0","") & MONTH(LstMachines[[#This Row],[RgltVteESM]]) & "-" & YEAR(LstMachines[[#This Row],[RgltVteESM]]) -> 03-2018 | AJ18: =MONTH(LstMachines[[#This Row],[DatePaie]]) -> 11 | AK18: =FIXED(YEAR(LstMachines[[#This Row],[DatePaie]]),0,TRUE) -> 2017
B19: Mini Pelle | C19: ZX65 | D19: 65 | E19: ZX65USB-5-CLP | F19: SETP | G19: RABASTENS | H19: 1 | I19: =IF(LstMachines[[#This Row],[Delivery]]<Début_HCME, 0, IFERROR( LstMachines[[#This Row],[Nbre]] * INDEX(TabModelSpecs[],MATCH(LstMachines[[#This Row],[Model-Spec]],TabModelSpecs[ModelSpec],0),MATCH("2018",TabModelSpecs[#Headers],0)), LstMachines[[#This Row],[Nbre]]*ROUND(AVERAGEIF(TabModelSpecs[Machine],LstMachines[[#This Row],[Model]],TabModelSpecs[Price]),0) ) ) -> 0 | J19: 43023 | K19: 5-Livrée | L19: 2017-10 ADV | M19: REGULARISER STE SUR REGIE (setp) | N19: 42975 | O19: =MONTH(LstMachines[[#This Row],[Delivery]]) -> 10 | P19: =FIXED(YEAR(LstMachines[[#This Row],[Delivery]]),0,TRUE) -> 2017 | Q19: 16080003 | U19: VENTE | V19: 3959 | W19: SANCHEZ | X19: =LstMachines[[#This Row],[Delivery]] -> 43023 | Y19: =IF(MONTH(LstMachines[[#This Row],[DateLivr]])<10,"0","") & MONTH(LstMachines[[#This Row],[DateLivr]]) &"-"&YEAR(LstMachines[[#This Row],[DateLivr]]) -> 10-2017 | Z19: =LstMachines[[#This Row],[Delivery]]+Rglt_à_HCME -> 43083 | AA19: =IF(MONTH(LstMachines[[#This Row],[DatePaie]])<10,"0","") & MONTH(LstMachines[[#This Row],[DatePaie]])&"-"&YEAR(LstMachines[[#This Row],[DatePaie]]) -> 12-2017 | AB19: =LstMachines[[#This Row],[DateLivr]]+1 -> 43024 | AC19: =IF(MONTH(LstMachines[[#This Row],[Distrib]])<10,"0","") & MONTH(LstMachines[[#This Row],[Distrib]]) & "-" & YEAR(LstMachines[[#This Row],[Distrib]]) -> 10-2017 | AD19: =LstMachines[[#This Row],[DateLivr]]+Délai_Vente -> 43143 | AE19: =IF(MONTH(LstMachines[[#This Row],[VteESM]])<10,"0","") & MONTH(LstMachines[[#This Row],[VteESM]]) & "-" & YEAR(LstMachines[[#This Row],[VteESM]]) -> 02-2018 | AF19: =LstMachines[[#This Row],[DateLivr]]+Rglt_à_ESMTP -> 43083 | AG19: =IF(MONTH(LstMachines[[#This Row],[RgltDistrib]])<10,"0","") & MONTH(LstMachines[[#This Row],[RgltDistrib]]) & "-" & YEAR(LstMachines[[#This Row],[RgltDistrib]]) -> 12-2017 | AH19: =LstMachines[[#This Row],[VteESM]]+Rglt_à_ESMTP -> 43203 | AI19: =IF(MONTH(LstMachines[[#This Row],[RgltVteESM]])<10,"0","") & MONTH(LstMachines[[#This Row],[RgltVteESM]]) & "-" & YEAR(LstMachines[[#This Row],[RgltVteESM]]) -> 04-2018 | AJ19: =MONTH(LstMachines[[#This Row],[DatePaie]]) -> 12 | AK19: =FIXED(YEAR(LstMachines[[#This Row],[DatePaie]]),0,TRUE) -> 2017
B20: Pelle/Chenilles | C20: ZX85 | D20: 85 | E20: ZX85USB-5A-Mono | F20: SETP | G20: RABASTENS | H20: 1 | I20: =IF(LstMachines[[#This Row],[Delivery]]<Début_HCME, 0, IFERROR( LstMachines[[#This Row],[Nbre]] * INDEX(TabModelSpecs[],MATCH(LstMachines[[#This Row],[Model-Spec]],TabModelSpecs[ModelSpec],0),MATCH("2018",TabModelSpecs[#Headers],0)), LstMachines[[#This Row],[Nbre]]*ROUND(AVERAGEIF(TabModelSpecs[Machine],LstMachines[[#This Row],[Model]],TabModelSpecs[Price]),0) ) ) -> 0 | J20: 43023 | K20: 5-Livrée | L20: 2017-10 ADV | N20: 42822 | O20: =MONTH(LstMachines[[#This Row],[Delivery]]) -> 10 | P20: =FIXED(YEAR(LstMachines[[#This Row],[Delivery]]),0,TRUE) -> 2017 | Q20: 17030033 | R20: 52800 | U20: VENTE | V20: 4086 | W20: GINESTE | X20: =LstMachines[[#This Row],[Delivery]] -> 43023 | Y20: =IF(MONTH(LstMachines[[#This Row],[DateLivr]])<10,"0","") & MONTH(LstMachines[[#This Row],[DateLivr]]) &"-"&YEAR(LstMachines[[#This Row],[DateLivr]]) -> 10-2017 | Z20: =LstMachines[[#This Row],[Delivery]]+Rglt_à_HCME -> 43083 | AA20: =IF(MONTH(LstMachines[[#This Row],[DatePaie]])<10,"0","") & MONTH(LstMachines[[#This Row],[DatePaie]])&"-"&YEAR(LstMachines[[#This Row],[DatePaie]]) -> 12-2017 | AB20: =LstMachines[[#This Row],[DateLivr]]+1 -> 43024 | AC20: =IF(MONTH(LstMachines[[#This Row],[Distrib]])<10,"0","") & MONTH(LstMachines[[#This Row],[Distrib]]) & "-" & YEAR(LstMachines[[#This Row],[Distrib]]) -> 10-2017 | AD20: =LstMachines[[#This Row],[DateLivr]]+Délai_Vente -> 43143 | AE20: =IF(MONTH(LstMachines[[#This Row],[VteESM]])<10,"0","") & MONTH(LstMachines[[#This Row],[VteESM]]) & "-" & YEAR(LstMachines[[#This Row],[VteESM]]) -> 02-2018 | AF20: =LstMachines[[#This Row],[DateLivr]]+Rglt_à_ESMTP -> 43083 | AG20: =IF(MONTH(LstMachines[[#This Row],[RgltDistrib]])<10,"0","") & MONTH(LstMachines[[#This Row],[RgltDistrib]]) & "-" & YEAR(LstMachines[[#This Row],[RgltDistrib]]) -> 12-2017 | AH20: =LstMachines[[#This Row],[VteESM]]+Rglt_à_ESMTP -> 43203 | AI20: =IF(MONTH(LstMachines[[#This Row],[RgltVteESM]])<10,"0","") & MONTH(LstMachines[[#This Row],[RgltVteESM]]) & "-" & YEAR(LstMachines[[#This Row],[RgltVteESM]]) -> 04-2018 | AJ20: =MONTH(LstMachines[[#This Row],[DatePaie]]) -> 12 | AK20: =FIXED(YEAR(LstMachines[[#This Row],[DatePaie]]),0,TRUE) -> 2017
B21: Mini Pelle | C21: ZX26 | D21: 26 | E21: ZX26U-5-CLR | F21: SETP | G21: LÉZIGNAN | H21: 1 | I21: =IF(LstMachines[[#This Row],[Delivery]]<Début_HCME, 0, IFERROR( LstMachines[[#This Row],[Nbre]] * INDEX(TabModelSpecs[],MATCH(LstMachines[[#This Row],[Model-Spec]],TabModelSpecs[ModelSpec],0),MATCH("2018",TabModelSpecs[#Headers],0)), LstMachines[[#This Row],[Nbre]]*ROUND(AVERAGEIF(TabModelSpecs[Machine],LstMachines[[#This Row],[Model]],TabModelSpecs[Price]),0) ) ) -> 0 | J21: 43023 | K21: 5-Livrée | L21: 2017-12-06 ADV | M21: livrée directement à Lezignan | N21: 42914 | O21: =MONTH(LstMachines[[#This Row],[Delivery]]) -> 10 | P21: =FIXED(YEAR(LstMachines[[#This Row],[Delivery]]),0,TRUE) -> 2017 | Q21: 17060095 | R21: 22700 | T21: 1-04964-1 794 | U21: VENTE | V21: 4148 | W21: SAS SRI TRAL | X21: =LstMachines[[#This Row],[Delivery]] -> 43023 | Y21: =IF(MONTH(LstMachines[[#This Row],[DateLivr]])<10,"0","") & MONTH(LstMachines[[#This Row],[DateLivr]]) &"-"&YEAR(LstMachines[[#This Row],[DateLivr]]) -> 10-2017 | Z21: =LstMachines[[#This Row],[Delivery]]+Rglt_à_HCME -> 43083 | AA21: =IF(MONTH(LstMachines[[#This Row],[DatePaie]])<10,"0","") & MONTH(LstMachines[[#This Row],[DatePaie]])&"-"&YEAR(LstMachines[[#This Row],[DatePaie]]) -> 12-2017 | AB21: =LstMachines[[#This Row],[DateLivr]]+1 -> 43024 | AC21: =IF(MONTH(LstMachines[[#This Row],[Distrib]])<10,"0","") & MONTH(LstMachines[[#This Row],[Distrib]]) & "-" & YEAR(LstMachines[[#This Row],[Distrib]]) -> 10-2017 | AD21: =LstMachines[[#This Row],[DateLivr]]+Délai_Vente -> 43143 | AE21: =IF(MONTH(LstMachines[[#This Row],[VteESM]])<10,"0","") & MONTH(LstMachines[[#This Row],[VteESM]]) & "-" & YEAR(LstMachines[[#This Row],[VteESM]]) -> 02-2018 | AF21: =LstMachines[[#This Row],[DateLivr]]+Rglt_à_ESMTP -> 43083 | AG21: =IF(MONTH(LstMachines[[#This Row],[RgltDistrib]])<10,"0","") & MONTH(LstMachines[[#This Row],[RgltDistrib]]) & "-" & YEAR(LstMachines[[#This Row],[RgltDistrib]]) -> 12-2017 | AH21: =LstMachines[[#This Row],[VteESM]]+Rglt_à_ESMTP -> 43203 | AI21: =IF(MONTH(LstMachines[[#This Row],[RgltVteESM]])<10,"0","") & MONTH(LstMachines[[#This Row],[RgltVteESM]]) & "-" & YEAR(LstMachines[[#This Row],[RgltVteESM]]) -> 04-2018 | AJ21: =MONTH(LstMachines[[#This Row],[DatePaie]]) -> 12 | AK21: =FIXED(YEAR(LstMachines[[#This Row],[DatePaie]]),0,TRUE) -> 2017
B22: Mini Pelle | C22: ZX19 | D22: 19 | E22: ZX19U-5 | F22: BTPS | G22: ORTHEZ | H22: 1 | I22: =IF(LstMachines[[#This Row],[Delivery]]<Début_HCME, 0, IFERROR( LstMachines[[#This Row],[Nbre]] * INDEX(TabModelSpecs[],MATCH(LstMachines[[#This Row],[Model-Spec]],TabModelSpecs[ModelSpec],0),MATCH("2018",TabModelSpecs[#Headers],0)), LstMachines[[#This Row],[Nbre]]*ROUND(AVERAGEIF(TabModelSpecs[Machine],LstMachines[[#This Row],[Model]],TabModelSpecs[Price]),0) ) ) -> 0 | J22: 43054 | K22: 3-Commande | L22: 2017-11 BTPS | O22: =MONTH(LstMachines[[#This Row],[Delivery]]) -> 11 | P22: =FIXED(YEAR(LstMachines[[#This Row],[Delivery]]),0,TRUE) -> 2017 | X22: =LstMachines[[#This Row],[Delivery]] -> 43054 | Y22: =IF(MONTH(LstMachines[[#This Row],[DateLivr]])<10,"0","") & MONTH(LstMachines[[#This Row],[DateLivr]]) &"-"&YEAR(LstMachines[[#This Row],[DateLivr]]) -> 11-2017 | Z22: =LstMachines[[#This Row],[Delivery]]+Rglt_à_HCME -> 43114 | AA22: =IF(MONTH(LstMachines[[#This Row],[DatePaie]])<10,"0","") & MONTH(LstMachines[[#This Row],[DatePaie]])&"-"&YEAR(LstMachines[[#This Row],[DatePaie]]) -> 01-2018 | AB22: =LstMachines[[#This Row],[DateLivr]]+1 -> 43055 | AC22: =IF(MONTH(LstMachines[[#This Row],[Distrib]])<10,"0","") & MONTH(LstMachines[[#This Row],[Distrib]]) & "-" & YEAR(LstMachines[[#This Row],[Distrib]]) -> 11-2017 | AD22: =LstMachines[[#This Row],[DateLivr]]+Délai_Vente -> 43174 | AE22: =IF(MONTH(LstMachines[[#This Row],[VteESM]])<10,"0","") & MONTH(LstMachines[[#This Row],[VteESM]]) & "-" & YEAR(LstMachines[[#This Row],[VteESM]]) -> 03-2018 | AF22: =LstMachines[[#This Row],[DateLivr]]+Rglt_à_ESMTP -> 43114 | AG22: =IF(MONTH(LstMachines[[#This Row],[RgltDistrib]])<10,"0","") & MONTH(LstMachines[[#This Row],[RgltDistrib]]) & "-" & YEAR(LstMachines[[#This Row],[RgltDistrib]]) -> 01-2018 | AH22: =LstMachines[[#This Row],[VteESM]]+Rglt_à_ESMTP -> 43234 | AI22: =IF(MONTH(LstMachines[[#This Row],[RgltVteESM]])<10,"0","") & MONTH(LstMachines[[#This Row],[RgltVteESM]]) & "-" & YEAR(LstMachines[[#This Row],[RgltVteESM]]) -> 05-2018 | AJ22: =MONTH(LstMachines[[#This Row],[DatePaie]]) -> 1 | AK22: =FIXED(YEAR(LstMachines[[#This Row],[DatePaie]]),0,TRUE) -> 2018
B23: Mini Pelle | C23: ZX26 | D23: 26 | E23: ZX26U-5-YLR | F23: BTPS | G23: ORTHEZ | H23: 1 | I23: =IF(LstMachines[[#This Row],[Delivery]]<Début_HCME, 0, IFERROR( LstMachines[[#This Row],[Nbre]] * INDEX(TabModelSpecs[],MATCH(LstMachines[[#This Row],[Model-Spec]],TabModelSpecs[ModelSpec],0),MATCH("2018",TabModelSpecs[#Headers],0)), LstMachines[[#This Row],[Nbre]]*ROUND(AVERAGEIF(TabModelSpecs[Machine],LstMachines[[#This Row],[Model]],TabModelSpecs[Price]),0) ) ) -> 0 | J23: 43054 | K23: 3-Commande | L23: 2017-11 BTPS | O23: =MONTH(LstMachines[[#This Row],[Delivery]]) -> 11 | P23: =FIXED(YEAR(LstMachines[[#This Row],[Delivery]]),0,TRUE) -> 2017 | X23: =LstMachines[[#This Row],[Delivery]] -> 43054 | Y23: =IF(MONTH(LstMachines[[#This Row],[DateLivr]])<10,"0","") & MONTH(LstMachines[[#This Row],[DateLivr]]) &"-"&YEAR(LstMachines[[#This Row],[DateLivr]]) -> 11-2017 | Z23: =LstMachines[[#This Row],[Delivery]]+Rglt_à_HCME -> 43114 | AA23: =IF(MONTH(LstMachines[[#This Row],[DatePaie]])<10,"0","") & MONTH(LstMachines[[#This Row],[DatePaie]])&"-"&YEAR(LstMachines[[#This Row],[DatePaie]]) -> 01-2018 | AB23: =LstMachines[[#This Row],[DateLivr]]+1 -> 43055 | AC23: =IF(MONTH(LstMachines[[#This Row],[Distrib]])<10,"0","") & MONTH(LstMachines[[#This Row],[Distrib]]) & "-" & YEAR(LstMachines[[#This Row],[Distrib]]) -> 11-2017 | AD23: =LstMachines[[#This Row],[DateLivr]]+Délai_Vente -> 43174 | AE23: =IF(MONTH(LstMachines[[#This Row],[VteESM]])<10,"0","") & MONTH(LstMachines[[#This Row],[VteESM]]) & "-" & YEAR(LstMachines[[#This Row],[VteESM]]) -> 03-2018 | AF23: =LstMachines[[#This Row],[DateLivr]]+Rglt_à_ESMTP -> 43114 | AG23: =IF(MONTH(LstMachines[[#This Row],[RgltDistrib]])<10,"0","") & MONTH(LstMachines[[#This Row],[RgltDistrib]]) & "-" & YEAR(LstMachines[[#This Row],[RgltDistrib]]) -> 01-2018 | AH23: =LstMachines[[#This Row],[VteESM]]+Rglt_à_ESMTP -> 43234 | AI23: =IF(MONTH(LstMachines[[#This Row],[RgltVteESM]])<10,"0","") & MONTH(LstMachines[[#This Row],[RgltVteESM]]) & "-" & YEAR(LstMachines[[#This Row],[RgltVteESM]]) -> 05-2018 | AJ23: =MONTH(LstMachines[[#This Row],[DatePaie]]) -> 1 | AK23: =FIXED(YEAR(LstMachines[[#This Row],[DatePaie]]),0,TRUE) -> 2018
B24: Pelle/Chenilles | C24: ZX350 | D24: 350 | E24: ZX350LCN-6-MN | F24: BTPS | G24: ORTHEZ | H24: 1 | I24: =IF(LstMachines[[#This Row],[Delivery]]<Début_HCME, 0, IFERROR( LstMachines[[#This Row],[Nbre]] * INDEX(TabModelSpecs[],MATCH(LstMachines[[#This Row],[Model-Spec]],TabModelSpecs[ModelSpec],0),MATCH("2018",TabModelSpecs[#Headers],0)), LstMachines[[#This Row],[Nbre]]*ROUND(AVERAGEIF(TabModelSpecs[Machine],LstMachines[[#This Row],[Model]],TabModelSpecs[Price]),0) ) ) -> 0 | J24: 43054 | K24: 3-Commande | L24: 2017-11 BTPS | O24: =MONTH(LstMachines[[#This Row],[Delivery]]) -> 11 | P24: =FIXED(YEAR(LstMachines[[#This Row],[Delivery]]),0,TRUE) -> 2017 | X24: =LstMachines[[#This Row],[Delivery]] -> 43054 | Y24: =IF(MONTH(LstMachines[[#This Row],[DateLivr]])<10,"0","") & MONTH(LstMachines[[#This Row],[DateLivr]]) &"-"&YEAR(LstMachines[[#This Row],[DateLivr]]) -> 11-2017 | Z24: =LstMachines[[#This Row],[Delivery]]+Rglt_à_HCME -> 43114 | AA24: =IF(MONTH(LstMachines[[#This Row],[DatePaie]])<10,"0","") & MONTH(LstMachines[[#This Row],[DatePaie]])&"-"&YEAR(LstMachines[[#This Row],[DatePaie]]) -> 01-2018 | AB24: =LstMachines[[#This Row],[DateLivr]]+1 -> 43055 | AC24: =IF(MONTH(LstMachines[[#This Row],[Distrib]])<10,"0","") & MONTH(LstMachines[[#This Row],[Distrib]]) & "-" & YEAR(LstMachines[[#This Row],[Distrib]]) -> 11-2017 | AD24: =LstMachines[[#This Row],[DateLivr]]+Délai_Vente -> 43174 | AE24: =IF(MONTH(LstMachines[[#This Row],[VteESM]])<10,"0","") & MONTH(LstMachines[[#This Row],[VteESM]]) & "-" & YEAR(LstMachines[[#This Row],[VteESM]]) -> 03-2018 | AF24: =LstMachines[[#This Row],[DateLivr]]+Rglt_à_ESMTP -> 43114 | AG24: =IF(MONTH(LstMachines[[#This Row],[RgltDistrib]])<10,"0","") & MONTH(LstMachines[[#This Row],[RgltDistrib]]) & "-" & YEAR(LstMachines[[#This Row],[RgltDistrib]]) -> 01-2018 | AH24: =LstMachines[[#This Row],[VteESM]]+Rglt_à_ESMTP -> 43234 | AI24: =IF(MONTH(LstMachines[[#This Row],[RgltVteESM]])<10,"0","") & MONTH(LstMachines[[#This Row],[RgltVteESM]]) & "-" & YEAR(LstMachines[[#This Row],[RgltVteESM]]) -> 05-2018 | AJ24: =MONTH(LstMachines[[#This Row],[DatePaie]]) -> 1 | AK24: =FIXED(YEAR(LstMachines[[#This Row],[DatePaie]]),0,TRUE) -> 2018
B25: Pelle/Chenilles | C25: ZX490 | D25: 490 | E25: ZX490-6-BE | F25: BTPS | G25: ORTHEZ | H25: 1 | I25: =IF(LstMachines[[#This Row],[Delivery]]<Début_HCME, 0, IFERROR( LstMachines[[#This Row],[Nbre]] * INDEX(TabModelSpecs[],MATCH(LstMachines[[#This Row],[Model-Spec]],TabModelSpecs[ModelSpec],0),MATCH("2018",TabModelSpecs[#Headers],0)), LstMachines[[#This Row],[Nbre]]*ROUND(AVERAGEIF(TabModelSpecs[Machine],LstMachines[[#This Row],[Model]],TabModelSpecs[Price]),0) ) ) -> 0 | J25: 43054 | K25: 3-Commande | L25: 2017-11 BTPS | O25: =MONTH(LstMachines[[#This Row],[Delivery]]) -> 11 | P25: =FIXED(YEAR(LstMachines[[#This Row],[Delivery]]),0,TRUE) -> 2017 | X25: =LstMachines[[#This Row],[Delivery]] -> 43054 | Y25: =IF(MONTH(LstMachines[[#This Row],[DateLivr]])<10,"0","") & MONTH(LstMachines[[#This Row],[DateLivr]]) &"-"&YEAR(LstMachines[[#This Row],[DateLivr]]) -> 11-2017 | Z25: =LstMachines[[#This Row],[Delivery]]+Rglt_à_HCME -> 43114 | AA25: =IF(MONTH(LstMachines[[#This Row],[DatePaie]])<10,"0","") & MONTH(LstMachines[[#This Row],[DatePaie]])&"-"&YEAR(LstMachines[[#This Row],[DatePaie]]) -> 01-2018 | AB25: =LstMachines[[#This Row],[DateLivr]]+1 -> 43055 | AC25: =IF(MONTH(LstMachines[[#This Row],[Distrib]])<10,"0","") & MONTH(LstMachines[[#This Row],[Distrib]]) & "-" & YEAR(LstMachines[[#This Row],[Distrib]]) -> 11-2017 | AD25: =LstMachines[[#This Row],[DateLivr]]+Délai_Vente -> 43174 | AE25: =IF(MONTH(LstMachines[[#This Row],[VteESM]])<10,"0","") & MONTH(LstMachines[[#This Row],[VteESM]]) & "-" & YEAR(LstMachines[[#This Row],[VteESM]]) -> 03-2018 | AF25: =LstMachines[[#This Row],[DateLivr]]+Rglt_à_ESMTP -> 43114 | AG25: =IF(MONTH(LstMachines[[#This Row],[RgltDistrib]])<10,"0","") & MONTH(LstMachines[[#This Row],[RgltDistrib]]) & "-" & YEAR(LstMachines[[#This Row],[RgltDistrib]]) -> 01-2018 | AH25: =LstMachines[[#This Row],[VteESM]]+Rglt_à_ESMTP -> 43234 | AI25: =IF(MONTH(LstMachines[[#This Row],[RgltVteESM]])<10,"0","") & MONTH(LstMachines[[#This Row],[RgltVteESM]]) & "-" & YEAR(LstMachines[[#This Row],[RgltVteESM]]) -> 05-2018 | AJ25: =MONTH(LstMachines[[#This Row],[DatePaie]]) -> 1 | AK25: =FIXED(YEAR(LstMachines[[#This Row],[DatePaie]]),0,TRUE) -> 2018
B26: Mini Pelle | C26: ZX65 | D26: 65 | E26: ZX65USB-5-CLRNH | F26: BTPS | G26: ORTHEZ | H26: 1 | I26: =IF(LstMachines[[#This Row],[Delivery]]<Début_HCME, 0, IFERROR( LstMachines[[#This Row],[Nbre]] * INDEX(TabModelSpecs[],MATCH(LstMachines[[#This Row],[Model-Spec]],TabModelSpecs[ModelSpec],0),MATCH("2018",TabModelSpecs[#Headers],0)), LstMachines[[#This Row],[Nbre]]*ROUND(AVERAGEIF(TabModelSpecs[Machine],LstMachines[[#This Row],[Model]],TabModelSpecs[Price]),0) ) ) -> 0 | J26: 43054 | K26: 3-Commande | L26: 2017-11 BTPS | O26: =MONTH(LstMachines[[#This Row],[Delivery]]) -> 11 | P26: =FIXED(YEAR(LstMachines[[#This Row],[Delivery]]),0,TRUE) -> 2017 | X26: =LstMachines[[#This Row],[Delivery]] -> 43054 | Y26: =IF(MONTH(LstMachines[[#This Row],[DateLivr]])<10,"0","") & MONTH(LstMachines[[#This Row],[DateLivr]]) &"-"&YEAR(LstMachines[[#This Row],[DateLivr]]) -> 11-2017 | Z26: =LstMachines[[#This Row],[Delivery]]+Rglt_à_HCME -> 43114 | AA26: =IF(MONTH(LstMachines[[#This Row],[DatePaie]])<10,"0","") & MONTH(LstMachines[[#This Row],[DatePaie]])&"-"&YEAR(LstMachines[[#This Row],[DatePaie]]) -> 01-2018 | AB26: =LstMachines[[#This Row],[DateLivr]]+1 -> 43055 | AC26: =IF(MONTH(LstMachines[[#This Row],[Distrib]])<10,"0","") & MONTH(LstMachines[[#This Row],[Distrib]]) & "-" & YEAR(LstMachines[[#This Row],[Distrib]]) -> 11-2017 | AD26: =LstMachines[[#This Row],[DateLivr]]+Délai_Vente -> 43174 | AE26: =IF(MONTH(LstMachines[[#This Row],[VteESM]])<10,"0","") & MONTH(LstMachines[[#This Row],[VteESM]]) & "-" & YEAR(LstMachines[[#This Row],[VteESM]]) -> 03-2018 | AF26: =LstMachines[[#This Row],[DateLivr]]+Rglt_à_ESMTP -> 43114 | AG26: =IF(MONTH(LstMachines[[#This Row],[RgltDistrib]])<10,"0","") & MONTH(LstMachines[[#This Row],[RgltDistrib]]) & "-" & YEAR(LstMachines[[#This Row],[RgltDistrib]]) -> 01-2018 | AH26: =LstMachines[[#This Row],[VteESM]]+Rglt_à_ESMTP -> 43234 | AI26: =IF(MONTH(LstMachines[[#This Row],[RgltVteESM]])<10,"0","") & MONTH(LstMachines[[#This Row],[RgltVteESM]]) & "-" & YEAR(LstMachines[[#This Row],[RgltVteESM]]) -> 05-2018 | AJ26: =MONTH(LstMachines[[#This Row],[DatePaie]]) -> 1 | AK26: =FIXED(YEAR(LstMachines[[#This Row],[DatePaie]]),0,TRUE) -> 2018
B27: Mini Pelle | C27: ZX65 | D27: 65 | E27: ZX65USB-5-CLRNH | F27: BTPS | G27: ORTHEZ | H27: 1 | I27: =IF(LstMachines[[#This Row],[Delivery]]<Début_HCME, 0, IFERROR( LstMachines[[#This Row],[Nbre]] * INDEX(TabModelSpecs[],MATCH(LstMachines[[#This Row],[Model-Spec]],TabModelSpecs[ModelSpec],0),MATCH("2018",TabModelSpecs[#Headers],0)), LstMachines[[#This Row],[Nbre]]*ROUND(AVERAGEIF(TabModelSpecs[Machine],LstMachines[[#This Row],[Model]],TabModelSpecs[Price]),0) ) ) -> 0 | J27: 43054 | K27: 3-Commande | L27: 2017-11 BTPS | O27: =MONTH(LstMachines[[#This Row],[Delivery]]) -> 11 | P27: =FIXED(YEAR(LstMachines[[#This Row],[Delivery]]),0,TRUE) -> 2017 | X27: =LstMachines[[#This Row],[Delivery]] -> 43054 | Y27: =IF(MONTH(LstMachines[[#This Row],[DateLivr]])<10,"0","") & MONTH(LstMachines[[#This Row],[DateLivr]]) &"-"&YEAR(LstMachines[[#This Row],[DateLivr]]) -> 11-2017 | Z27: =LstMachines[[#This Row],[Delivery]]+Rglt_à_HCME -> 43114 | AA27: =IF(MONTH(LstMachines[[#This Row],[DatePaie]])<10,"0","") & MONTH(LstMachines[[#This Row],[DatePaie]])&"-"&YEAR(LstMachines[[#This Row],[DatePaie]]) -> 01-2018 | AB27: =LstMachines[[#This Row],[DateLivr]]+1 -> 43055 | AC27: =IF(MONTH(LstMachines[[#This Row],[Distrib]])<10,"0","") & MONTH(LstMachines[[#This Row],[Distrib]]) & "-" & YEAR(LstMachines[[#This Row],[Distrib]]) -> 11-2017 | AD27: =LstMachines[[#This Row],[DateLivr]]+Délai_Vente -> 43174 | AE27: =IF(MONTH(LstMachines[[#This Row],[VteESM]])<10,"0","") & MONTH(LstMachines[[#This Row],[VteESM]]) & "-" & YEAR(LstMachines[[#This Row],[VteESM]]) -> 03-2018 | AF27: =LstMachines[[#This Row],[DateLivr]]+Rglt_à_ESMTP -> 43114 | AG27: =IF(MONTH(LstMachines[[#This Row],[RgltDistrib]])<10,"0","") & MONTH(LstMachines[[#This Row],[RgltDistrib]]) & "-" & YEAR(LstMachines[[#This Row],[RgltDistrib]]) -> 01-2018 | AH27: =LstMachines[[#This Row],[VteESM]]+Rglt_à_ESMTP -> 43234 | AI27: =IF(MONTH(LstMachines[[#This Row],[RgltVteESM]])<10,"0","") & MONTH(LstMachines[[#This Row],[RgltVteESM]]) & "-" & YEAR(LstMachines[[#This Row],[RgltVteESM]]) -> 05-2018 | AJ27: =MONTH(LstMachines[[#This Row],[DatePaie]]) -> 1 | AK27: =FIXED(YEAR(LstMachines[[#This Row],[DatePaie]]),0,TRUE) -> 2018
B28: Mini Pelle | C28: ZX65 | D28: 65 | E28: ZX65USB-5-CLRNH | F28: BTPS | G28: ORTHEZ | H28: 1 | I28: =IF(LstMachines[[#This Row],[Delivery]]<Début_HCME, 0, IFERROR( LstMachines[[#This Row],[Nbre]] * INDEX(TabModelSpecs[],MATCH(LstMachines[[#This Row],[Model-Spec]],TabModelSpecs[ModelSpec],0),MATCH("2018",TabModelSpecs[#Headers],0)), LstMachines[[#This Row],[Nbre]]*ROUND(AVERAGEIF(TabModelSpecs[Machine],LstMachines[[#This Row],[Model]],TabModelSpecs[Price]),0) ) ) -> 0 | J28: 43054 | K28: 3-Commande | L28: 2017-11 BTPS | O28: =MONTH(LstMachines[[#This Row],[Delivery]]) -> 11 | P28: =FIXED(YEAR(LstMachines[[#This Row],[Delivery]]),0,TRUE) -> 2017 | X28: =LstMachines[[#This Row],[Delivery]] -> 43054 | Y28: =IF(MONTH(LstMachines[[#This Row],[DateLivr]])<10,"0","") & MONTH(LstMachines[[#This Row],[DateLivr]]) &"-"&YEAR(LstMachines[[#This Row],[DateLivr]]) -> 11-2017 | Z28: =LstMachines[[#This Row],[Delivery]]+Rglt_à_HCME -> 43114 | AA28: =IF(MONTH(LstMachines[[#This Row],[DatePaie]])<10,"0","") & MONTH(LstMachines[[#This Row],[DatePaie]])&"-"&YEAR(LstMachines[[#This Row],[DatePaie]]) -> 01-2018 | AB28: =LstMachines[[#This Row],[DateLivr]]+1 -> 43055 | AC28: =IF(MONTH(LstMachines[[#This Row],[Distrib]])<10,"0","") & MONTH(LstMachines[[#This Row],[Distrib]]) & "-" & YEAR(LstMachines[[#This Row],[Distrib]]) -> 11-2017 | AD28: =LstMachines[[#This Row],[DateLivr]]+Délai_Vente -> 43174 | AE28: =IF(MONTH(LstMachines[[#This Row],[VteESM]])<10,"0","") & MONTH(LstMachines[[#This Row],[VteESM]]) & "-" & YEAR(LstMachines[[#This Row],[VteESM]]) -> 03-2018 | AF28: =LstMachines[[#This Row],[DateLivr]]+Rglt_à_ESMTP -> 43114 | AG28: =IF(MONTH(LstMachines[[#This Row],[RgltDistrib]])<10,"0","") & MONTH(LstMachines[[#This Row],[RgltDistrib]]) & "-" & YEAR(LstMachines[[#This Row],[RgltDistrib]]) -> 01-2018 | AH28: =LstMachines[[#This Row],[VteESM]]+Rglt_à_ESMTP -> 43234 | AI28: =IF(MONTH(LstMachines[[#This Row],[RgltVteESM]])<10,"0","") & MONTH(LstMachines[[#This Row],[RgltVteESM]]) & "-" & YEAR(LstMachines[[#This Row],[RgltVteESM]]) -> 05-2018 | AJ28: =MONTH(LstMachines[[#This Row],[DatePaie]]) -> 1 | AK28: =FIXED(YEAR(LstMachines[[#This Row],[DatePaie]]),0,TRUE) -> 2018
B29: Pelle/Chenilles | C29: ZX85 | D29: 85 | E29: ZX85USB-5A-Mono | F29: BTPS | G29: ORTHEZ | H29: 1 | I29: =IF(LstMachines[[#This Row],[Delivery]]<Début_HCME, 0, IFERROR( LstMachines[[#This Row],[Nbre]] * INDEX(TabModelSpecs[],MATCH(LstMachines[[#This Row],[Model-Spec]],TabModelSpecs[ModelSpec],0),MATCH("2018",TabModelSpecs[#Headers],0)), LstMachines[[#This Row],[Nbre]]*ROUND(AVERAGEIF(TabModelSpecs[Machine],LstMachines[[#This Row],[Model]],TabModelSpecs[Price]),0) ) ) -> 0 | J29: 43054 | K29: 3-Commande | L29: 2017-11 BTPS | O29: =MONTH(LstMachines[[#This Row],[Delivery]]) -> 11 | P29: =FIXED(YEAR(LstMachines[[#This Row],[Delivery]]),0,TRUE) -> 2017 | X29: =LstMachines[[#This Row],[Delivery]] -> 43054 | Y29: =IF(MONTH(LstMachines[[#This Row],[DateLivr]])<10,"0","") & MONTH(LstMachines[[#This Row],[DateLivr]]) &"-"&YEAR(LstMachines[[#This Row],[DateLivr]]) -> 11-2017 | Z29: =LstMachines[[#This Row],[Delivery]]+Rglt_à_HCME -> 43114 | AA29: =IF(MONTH(LstMachines[[#This Row],[DatePaie]])<10,"0","") & MONTH(LstMachines[[#This Row],[DatePaie]])&"-"&YEAR(LstMachines[[#This Row],[DatePaie]]) -> 01-2018 | AB29: =LstMachines[[#This Row],[DateLivr]]+1 -> 43055 | AC29: =IF(MONTH(LstMachines[[#This Row],[Distrib]])<10,"0","") & MONTH(LstMachines[[#This Row],[Distrib]]) & "-" & YEAR(LstMachines[[#This Row],[Distrib]]) -> 11-2017 | AD29: =LstMachines[[#This Row],[DateLivr]]+Délai_Vente -> 43174 | AE29: =IF(MONTH(LstMachines[[#This Row],[VteESM]])<10,"0","") & MONTH(LstMachines[[#This Row],[VteESM]]) & "-" & YEAR(LstMachines[[#This Row],[VteESM]]) -> 03-2018 | AF29: =LstMachines[[#This Row],[DateLivr]]+Rglt_à_ESMTP -> 43114 | AG29: =IF(MONTH(LstMachines[[#This Row],[RgltDistrib]])<10,"0","") & MONTH(LstMachines[[#This Row],[RgltDistrib]]) & "-" & YEAR(LstMachines[[#This Row],[RgltDistrib]]) -> 01-2018 | AH29: =LstMachines[[#This Row],[VteESM]]+Rglt_à_ESMTP -> 43234 | AI29: =IF(MONTH(LstMachines[[#This Row],[RgltVteESM]])<10,"0","") & MONTH(LstMachines[[#This Row],[RgltVteESM]]) & "-" & YEAR(LstMachines[[#This Row],[RgltVteESM]]) -> 05-2018 | AJ29: =MONTH(LstMachines[[#This Row],[DatePaie]]) -> 1 | AK29: =FIXED(YEAR(LstMachines[[#This Row],[DatePaie]]),0,TRUE) -> 2018
B30: Chargeuse | C30: ZW310 | D30: 310 | E30: ZW310-6-TPD | F30: SETP | G30: RABASTENS | H30: 1 | I30: =IF(LstMachines[[#This Row],[Delivery]]<Début_HCME, 0, IFERROR( LstMachines[[#This Row],[Nbre]] * INDEX(TabModelSpecs[],MATCH(LstMachines[[#This Row],[Model-Spec]],TabModelSpecs[ModelSpec],0),MATCH("2018",TabModelSpecs[#Headers],0)), LstMachines[[#This Row],[Nbre]]*ROUND(AVERAGEIF(TabModelSpecs[Machine],LstMachines[[#This Row],[Model]],TabModelSpecs[Price]),0) ) ) -> 0 | J30: 43054 | K30: 5-Livrée | L30: 2017-10 ADV | N30: 42944 | O30: =MONTH(LstMachines[[#This Row],[Delivery]]) -> 11 | P30: =FIXED(YEAR(LstMachines[[#This Row],[Delivery]]),0,TRUE) -> 2017 | Q30: 17070020 | R30: 179279 | U30: VENTE | V30: 4173 | W30: STAP | X30: =LstMachines[[#This Row],[Delivery]] -> 43054 | Y30: =IF(MONTH(LstMachines[[#This Row],[DateLivr]])<10,"0","") & MONTH(LstMachines[[#This Row],[DateLivr]]) &"-"&YEAR(LstMachines[[#This Row],[DateLivr]]) -> 11-2017 | Z30: =LstMachines[[#This Row],[Delivery]]+Rglt_à_HCME -> 43114 | AA30: =IF(MONTH(LstMachines[[#This Row],[DatePaie]])<10,"0","") & MONTH(LstMachines[[#This Row],[DatePaie]])&"-"&YEAR(LstMachines[[#This Row],[DatePaie]]) -> 01-2018 | AB30: =LstMachines[[#This Row],[DateLivr]]+1 -> 43055 | AC30: =IF(MONTH(LstMachines[[#This Row],[Distrib]])<10,"0","") & MONTH(LstMachines[[#This Row],[Distrib]]) & "-" & YEAR(LstMachines[[#This Row],[Distrib]]) -> 11-2017 | AD30: =LstMachines[[#This Row],[DateLivr]]+Délai_Vente -> 43174 | AE30: =IF(MONTH(LstMachines[[#This Row],[VteESM]])<10,"0","") & MONTH(LstMachines[[#This Row],[VteESM]]) & "-" & YEAR(LstMachines[[#This Row],[VteESM]]) -> 03-2018 | AF30: =LstMachines[[#This Row],[DateLivr]]+Rglt_à_ESMTP -> 43114 | AG30: =IF(MONTH(LstMachines[[#This Row],[RgltDistrib]])<10,"0","") & MONTH(LstMachines[[#This Row],[RgltDistrib]]) & "-" & YEAR(LstMachines[[#This Row],[RgltDistrib]]) -> 01-2018 | AH30: =LstMachines[[#This Row],[VteESM]]+Rglt_à_ESMTP -> 43234 | AI30: =IF(MONTH(LstMachines[[#This Row],[RgltVteESM]])<10,"0","") & MONTH(LstMachines[[#This Row],[RgltVteESM]]) & "-" & YEAR(LstMachines[[#This Row],[RgltVteESM]]) -> 05-2018 | AJ30: =MONTH(LstMachines[[#This Row],[DatePaie]]) -> 1 | AK30: =FIXED(YEAR(LstMachines[[#This Row],[DatePaie]]),0,TRUE) -> 2018
B31: Mini Pelle | C31: ZX19 | D31: 19 | E31: ZX19U-5 | F31: BTPS | G31: ORTHEZ | H31: 1 | I31: =IF(LstMachines[[#This Row],[Delivery]]<Début_HCME, 0, IFERROR( LstMachines[[#This Row],[Nbre]] * INDEX(TabModelSpecs[],MATCH(LstMachines[[#This Row],[Model-Spec]],TabModelSpecs[ModelSpec],0),MATCH("2018",TabModelSpecs[#Headers],0)), LstMachines[[#This Row],[Nbre]]*ROUND(AVERAGEIF(TabModelSpecs[Machine],LstMachines[[#This Row],[Model]],TabModelSpecs[Price]),0) ) ) -> 0 | J31: 43084 | K31: 3-Commande | L31: 2017-11 BTPS | O31: =MONTH(LstMachines[[#This Row],[Delivery]]) -> 12 | P31: =FIXED(YEAR(LstMachines[[#This Row],[Delivery]]),0,TRUE) -> 2017 | X31: =LstMachines[[#This Row],[Delivery]] -> 43084 | Y31: =IF(MONTH(LstMachines[[#This Row],[DateLivr]])<10,"0","") & MONTH(LstMachines[[#This Row],[DateLivr]]) &"-"&YEAR(LstMachines[[#This Row],[DateLivr]]) -> 12-2017 | Z31: =LstMachines[[#This Row],[Delivery]]+Rglt_à_HCME -> 43144 | AA31: =IF(MONTH(LstMachines[[#This Row],[DatePaie]])<10,"0","") & MONTH(LstMachines[[#This Row],[DatePaie]])&"-"&YEAR(LstMachines[[#This Row],[DatePaie]]) -> 02-2018 | AB31: =LstMachines[[#This Row],[DateLivr]]+1 -> 43085 | AC31: =IF(MONTH(LstMachines[[#This Row],[Distrib]])<10,"0","") & MONTH(LstMachines[[#This Row],[Distrib]]) & "-" & YEAR(LstMachines[[#This Row],[Distrib]]) -> 12-2017 | AD31: =LstMachines[[#This Row],[DateLivr]]+Délai_Vente -> 43204 | AE31: =IF(MONTH(LstMachines[[#This Row],[VteESM]])<10,"0","") & MONTH(LstMachines[[#This Row],[VteESM]]) & "-" & YEAR(LstMachines[[#This Row],[VteESM]]) -> 04-2018 | AF31: =LstMachines[[#This Row],[DateLivr]]+Rglt_à_ESMTP -> 43144 | AG31: =IF(MONTH(LstMachines[[#This Row],[RgltDistrib]])<10,"0","") & MONTH(LstMachines[[#This Row],[RgltDistrib]]) & "-" & YEAR(LstMachines[[#This Row],[RgltDistrib]]) -> 02-2018 | AH31: =LstMachines[[#This Row],[VteESM]]+Rglt_à_ESMTP -> 43264 | AI31: =IF(MONTH(LstMachines[[#This Row],[RgltVteESM]])<10,"0","") & MONTH(LstMachines[[#This Row],[RgltVteESM]]) & "-" & YEAR(LstMachines[[#This Row],[RgltVteESM]]) -> 06-2018 | AJ31: =MONTH(LstMachines[[#This Row],[DatePaie]]) -> 2 | AK31: =FIXED(YEAR(LstMachines[[#This Row],[DatePaie]]),0,TRUE) -> 2018
B32: Mini Pelle | C32: ZX55 | D32: 55 | E32: ZX55U-5-CLRNH | F32: BTPS | G32: ORTHEZ | H32: 1 | I32: =IF(LstMachines[[#This Row],[Delivery]]<Début_HCME, 0, IFERROR( LstMachines[[#This Row],[Nbre]] * INDEX(TabModelSpecs[],MATCH(LstMachines[[#This Row],[Model-Spec]],TabModelSpecs[ModelSpec],0),MATCH("2018",TabModelSpecs[#Headers],0)), LstMachines[[#This Row],[Nbre]]*ROUND(AVERAGEIF(TabModelSpecs[Machine],LstMachines[[#This Row],[Model]],TabModelSpecs[Price]),0) ) ) -> 0 | J32: 43084 | K32: 3-Commande | L32: 2017-11 BTPS | O32: =MONTH(LstMachines[[#This Row],[Delivery]]) -> 12 | P32: =FIXED(YEAR(LstMachines[[#This Row],[Delivery]]),0,TRUE) -> 2017 | X32: =LstMachines[[#This Row],[Delivery]] -> 43084 | Y32: =IF(MONTH(LstMachines[[#This Row],[DateLivr]])<10,"0","") & MONTH(LstMachines[[#This Row],[DateLivr]]) &"-"&YEAR(LstMachines[[#This Row],[DateLivr]]) -> 12-2017 | Z32: =LstMachines[[#This Row],[Delivery]]+Rglt_à_HCME -> 43144 | AA32: =IF(MONTH(LstMachines[[#This Row],[DatePaie]])<10,"0","") & MONTH(LstMachines[[#This Row],[DatePaie]])&"-"&YEAR(LstMachines[[#This Row],[DatePaie]]) -> 02-2018 | AB32: =LstMachines[[#This Row],[DateLivr]]+1 -> 43085 | AC32: =IF(MONTH(LstMachines[[#This Row],[Distrib]])<10,"0","") & MONTH(LstMachines[[#This Row],[Distrib]]) & "-" & YEAR(LstMachines[[#This Row],[Distrib]]) -> 12-2017 | AD32: =LstMachines[[#This Row],[DateLivr]]+Délai_Vente -> 43204 | AE32: =IF(MONTH(LstMachines[[#This Row],[VteESM]])<10,"0","") & MONTH(LstMachines[[#This Row],[VteESM]]) & "-" & YEAR(LstMachines[[#This Row],[VteESM]]) -> 04-2018 | AF32: =LstMachines[[#This Row],[DateLivr]]+Rglt_à_ESMTP -> 43144 | AG32: =IF(MONTH(LstMachines[[#This Row],[RgltDistrib]])<10,"0","") & MONTH(LstMachines[[#This Row],[RgltDistrib]]) & "-" & YEAR(LstMachines[[#This Row],[RgltDistrib]]) -> 02-2018 | AH32: =LstMachines[[#This Row],[VteESM]]+Rglt_à_ESMTP -> 43264 | AI32: =IF(MONTH(LstMachines[[#This Row],[RgltVteESM]])<10,"0","") & MONTH(LstMachines[[#This Row],[RgltVteESM]]) & "-" & YEAR(LstMachines[[#This Row],[RgltVteESM]]) -> 06-2018 | AJ32: =MONTH(LstMachines[[#This Row],[DatePaie]]) -> 2 | AK32: =FIXED(YEAR(LstMachines[[#This Row],[DatePaie]]),0,TRUE) -> 2018
B33: Mini Pelle | C33: ZX65 | D33: 65 | E33: ZX65USB-5-CLRNH | F33: BTPS | G33: ORTHEZ | H33: 1 | I33: =IF(LstMachines[[#This Row],[Delivery]]<Début_HCME, 0, IFERROR( LstMachines[[#This Row],[Nbre]] * INDEX(TabModelSpecs[],MATCH(LstMachines[[#This Row],[Model-Spec]],TabModelSpecs[ModelSpec],0),MATCH("2018",TabModelSpecs[#Headers],0)), LstMachines[[#This Row],[Nbre]]*ROUND(AVERAGEIF(TabModelSpecs[Machine],LstMachines[[#This Row],[Model]],TabModelSpecs[Price]),0) ) ) -> 0 | J33: 43084 | K33: 3-Commande | L33: 2017-11 BTPS | O33: =MONTH(LstMachines[[#This Row],[Delivery]]) -> 12 | P33: =FIXED(YEAR(LstMachines[[#This Row],[Delivery]]),0,TRUE) -> 2017 | X33: =LstMachines[[#This Row],[Delivery]] -> 43084 | Y33: =IF(MONTH(LstMachines[[#This Row],[DateLivr]])<10,"0","") & MONTH(LstMachines[[#This Row],[DateLivr]]) &"-"&YEAR(LstMachines[[#This Row],[DateLivr]]) -> 12-2017 | Z33: =LstMachines[[#This Row],[Delivery]]+Rglt_à_HCME -> 43144 | AA33: =IF(MONTH(LstMachines[[#This Row],[DatePaie]])<10,"0","") & MONTH(LstMachines[[#This Row],[DatePaie]])&"-"&YEAR(LstMachines[[#This Row],[DatePaie]]) -> 02-2018 | AB33: =LstMachines[[#This Row],[DateLivr]]+1 -> 43085 | AC33: =IF(MONTH(LstMachines[[#This Row],[Distrib]])<10,"0","") & MONTH(LstMachines[[#This Row],[Distrib]]) & "-" & YEAR(LstMachines[[#This Row],[Distrib]]) -> 12-2017 | AD33: =LstMachines[[#This Row],[DateLivr]]+Délai_Vente -> 43204 | AE33: =IF(MONTH(LstMachines[[#This Row],[VteESM]])<10,"0","") & MONTH(LstMachines[[#This Row],[VteESM]]) & "-" & YEAR(LstMachines[[#This Row],[VteESM]]) -> 04-2018 | AF33: =LstMachines[[#This Row],[DateLivr]]+Rglt_à_ESMTP -> 43144 | AG33: =IF(MONTH(LstMachines[[#This Row],[RgltDistrib]])<10,"0","") & MONTH(LstMachines[[#This Row],[RgltDistrib]]) & "-" & YEAR(LstMachines[[#This Row],[RgltDistrib]]) -> 02-2018 | AH33: =LstMachines[[#This Row],[VteESM]]+Rglt_à_ESMTP -> 43264 | AI33: =IF(MONTH(LstMachines[[#This Row],[RgltVteESM]])<10,"0","") & MONTH(LstMachines[[#This Row],[RgltVteESM]]) & "-" & YEAR(LstMachines[[#This Row],[RgltVteESM]]) -> 06-2018 | AJ33: =MONTH(LstMachines[[#This Row],[DatePaie]]) -> 2 | AK33: =FIXED(YEAR(LstMachines[[#This Row],[DatePaie]]),0,TRUE) -> 2018
B34: Pelle/Chenilles | C34: ZX85 | D34: 85 | E34: ZX85USB-5A-Mono | F34: BTPS | G34: ORTHEZ | H34: 1 | I34: =IF(LstMachines[[#This Row],[Delivery]]<Début_HCME, 0, IFERROR( LstMachines[[#This Row],[Nbre]] * INDEX(TabModelSpecs[],MATCH(LstMachines[[#This Row],[Model-Spec]],TabModelSpecs[ModelSpec],0),MATCH("2018",TabModelSpecs[#Headers],0)), LstMachines[[#This Row],[Nbre]]*ROUND(AVERAGEIF(TabModelSpecs[Machine],LstMachines[[#This Row],[Model]],TabModelSpecs[Price]),0) ) ) -> 0 | J34: 43084 | K34: 3-Commande | L34: 2017-11 BTPS | O34: =MONTH(LstMachines[[#This Row],[Delivery]]) -> 12 | P34: =FIXED(YEAR(LstMachines[[#This Row],[Delivery]]),0,TRUE) -> 2017 | X34: =LstMachines[[#This Row],[Delivery]] -> 43084 | Y34: =IF(MONTH(LstMachines[[#This Row],[DateLivr]])<10,"0","") & MONTH(LstMachines[[#This Row],[DateLivr]]) &"-"&YEAR(LstMachines[[#This Row],[DateLivr]]) -> 12-2017 | Z34: =LstMachines[[#This Row],[Delivery]]+Rglt_à_HCME -> 43144 | AA34: =IF(MONTH(LstMachines[[#This Row],[DatePaie]])<10,"0","") & MONTH(LstMachines[[#This Row],[DatePaie]])&"-"&YEAR(LstMachines[[#This Row],[DatePaie]]) -> 02-2018 | AB34: =LstMachines[[#This Row],[DateLivr]]+1 -> 43085 | AC34: =IF(MONTH(LstMachines[[#This Row],[Distrib]])<10,"0","") & MONTH(LstMachines[[#This Row],[Distrib]]) & "-" & YEAR(LstMachines[[#This Row],[Distrib]]) -> 12-2017 | AD34: =LstMachines[[#This Row],[DateLivr]]+Délai_Vente -> 43204 | AE34: =IF(MONTH(LstMachines[[#This Row],[VteESM]])<10,"0","") & MONTH(LstMachines[[#This Row],[VteESM]]) & "-" & YEAR(LstMachines[[#This Row],[VteESM]]) -> 04-2018 | AF34: =LstMachines[[#This Row],[DateLivr]]+Rglt_à_ESMTP -> 43144 | AG34: =IF(MONTH(LstMachines[[#This Row],[RgltDistrib]])<10,"0","") & MONTH(LstMachines[[#This Row],[RgltDistrib]]) & "-" & YEAR(LstMachines[[#This Row],[RgltDistrib]]) -> 02-2018 | AH34: =LstMachines[[#This Row],[VteESM]]+Rglt_à_ESMTP -> 43264 | AI34: =IF(MONTH(LstMachines[[#This Row],[RgltVteESM]])<10,"0","") & MONTH(LstMachines[[#This Row],[RgltVteESM]]) & "-" & YEAR(LstMachines[[#This Row],[RgltVteESM]]) -> 06-2018 | AJ34: =MONTH(LstMachines[[#This Row],[DatePaie]]) -> 2 | AK34: =FIXED(YEAR(LstMachines[[#This Row],[DatePaie]]),0,TRUE) -> 2018
B35: Pelle/Chenilles | C35: ZX85 | D35: 85 | E35: ZX85USB-5A-Mono | F35: BTPS | G35: ORTHEZ | H35: 1 | I35: =IF(LstMachines[[#This Row],[Delivery]]<Début_HCME, 0, IFERROR( LstMachines[[#This Row],[Nbre]] * INDEX(TabModelSpecs[],MATCH(LstMachines[[#This Row],[Model-Spec]],TabModelSpecs[ModelSpec],0),MATCH("2018",TabModelSpecs[#Headers],0)), LstMachines[[#This Row],[Nbre]]*ROUND(AVERAGEIF(TabModelSpecs[Machine],LstMachines[[#This Row],[Model]],TabModelSpecs[Price]),0) ) ) -> 0 | J35: 43084 | K35: 3-Commande | L35: 2017-11 BTPS | O35: =MONTH(LstMachines[[#This Row],[Delivery]]) -> 12 | P35: =FIXED(YEAR(LstMachines[[#This Row],[Delivery]]),0,TRUE) -> 2017 | X35: =LstMachines[[#This Row],[Delivery]] -> 43084 | Y35: =IF(MONTH(LstMachines[[#This Row],[DateLivr]])<10,"0","") & MONTH(LstMachines[[#This Row],[DateLivr]]) &"-"&YEAR(LstMachines[[#This Row],[DateLivr]]) -> 12-2017 | Z35: =LstMachines[[#This Row],[Delivery]]+Rglt_à_HCME -> 43144 | AA35: =IF(MONTH(LstMachines[[#This Row],[DatePaie]])<10,"0","") & MONTH(LstMachines[[#This Row],[DatePaie]])&"-"&YEAR(LstMachines[[#This Row],[DatePaie]]) -> 02-2018 | AB35: =LstMachines[[#This Row],[DateLivr]]+1 -> 43085 | AC35: =IF(MONTH(LstMachines[[#This Row],[Distrib]])<10,"0","") & MONTH(LstMachines[[#This Row],[Distrib]]) & "-" & YEAR(LstMachines[[#This Row],[Distrib]]) -> 12-2017 | AD35: =LstMachines[[#This Row],[DateLivr]]+Délai_Vente -> 43204 | AE35: =IF(MONTH(LstMachines[[#This Row],[VteESM]])<10,"0","") & MONTH(LstMachines[[#This Row],[VteESM]]) & "-" & YEAR(LstMachines[[#This Row],[VteESM]]) -> 04-2018 | AF35: =LstMachines[[#This Row],[DateLivr]]+Rglt_à_ESMTP -> 43144 | AG35: =IF(MONTH(LstMachines[[#This Row],[RgltDistrib]])<10,"0","") & MONTH(LstMachines[[#This Row],[RgltDistrib]]) & "-" & YEAR(LstMachines[[#This Row],[RgltDistrib]]) -> 02-2018 | AH35: =LstMachines[[#This Row],[VteESM]]+Rglt_à_ESMTP -> 43264 | AI35: =IF(MONTH(LstMachines[[#This Row],[RgltVteESM]])<10,"0","") & MONTH(LstMachines[[#This Row],[RgltVteESM]]) & "-" & YEAR(LstMachines[[#This Row],[RgltVteESM]]) -> 06-2018 | AJ35: =MONTH(LstMachines[[#This Row],[DatePaie]]) -> 2 | AK35: =FIXED(YEAR(LstMachines[[#This Row],[DatePaie]]),0,TRUE) -> 2018
B36: Pelle/Chenilles | C36: ZX85 | D36: 85 | E36: ZX85USB-5A-Mono | F36: BTPS | G36: ORTHEZ | H36: 1 | I36: =IF(LstMachines[[#This Row],[Delivery]]<Début_HCME, 0, IFERROR( LstMachines[[#This Row],[Nbre]] * INDEX(TabModelSpecs[],MATCH(LstMachines[[#This Row],[Model-Spec]],TabModelSpecs[ModelSpec],0),MATCH("2018",TabModelSpecs[#Headers],0)), LstMachines[[#This Row],[Nbre]]*ROUND(AVERAGEIF(TabModelSpecs[Machine],LstMachines[[#This Row],[Model]],TabModelSpecs[Price]),0) ) ) -> 0 | J36: 43084 | K36: 3-Commande | L36: 2017-11 BTPS | O36: =MONTH(LstMachines[[#This Row],[Delivery]]) -> 12 | P36: =FIXED(YEAR(LstMachines[[#This Row],[Delivery]]),0,TRUE) -> 2017 | X36: =LstMachines[[#This Row],[Delivery]] -> 43084 | Y36: =IF(MONTH(LstMachines[[#This Row],[DateLivr]])<10,"0","") & MONTH(LstMachines[[#This Row],[DateLivr]]) &"-"&YEAR(LstMachines[[#This Row],[DateLivr]]) -> 12-2017 | Z36: =LstMachines[[#This Row],[Delivery]]+Rglt_à_HCME -> 43144 | AA36: =IF(MONTH(LstMachines[[#This Row],[DatePaie]])<10,"0","") & MONTH(LstMachines[[#This Row],[DatePaie]])&"-"&YEAR(LstMachines[[#This Row],[DatePaie]]) -> 02-2018 | AB36: =LstMachines[[#This Row],[DateLivr]]+1 -> 43085 | AC36: =IF(MONTH(LstMachines[[#This Row],[Distrib]])<10,"0","") & MONTH(LstMachines[[#This Row],[Distrib]]) & "-" & YEAR(LstMachines[[#This Row],[Distrib]]) -> 12-2017 | AD36: =LstMachines[[#This Row],[DateLivr]]+Délai_Vente -> 43204 | AE36: =IF(MONTH(LstMachines[[#This Row],[VteESM]])<10,"0","") & MONTH(LstMachines[[#This Row],[VteESM]]) & "-" & YEAR(LstMachines[[#This Row],[VteESM]]) -> 04-2018 | AF36: =LstMachines[[#This Row],[DateLivr]]+Rglt_à_ESMTP -> 43144 | AG36: =IF(MONTH(LstMachines[[#This Row],[RgltDistrib]])<10,"0","") & MONTH(LstMachines[[#This Row],[RgltDistrib]]) & "-" & YEAR(LstMachines[[#This Row],[RgltDistrib]]) -> 02-2018 | AH36: =LstMachines[[#This Row],[VteESM]]+Rglt_à_ESMTP -> 43264 | AI36: =IF(MONTH(LstMachines[[#This Row],[RgltVteESM]])<10,"0","") & MONTH(LstMachines[[#This Row],[RgltVteESM]]) & "-" & YEAR(LstMachines[[#This Row],[RgltVteESM]]) -> 06-2018 | AJ36: =MONTH(LstMachines[[#This Row],[DatePaie]]) -> 2 | AK36: =FIXED(YEAR(LstMachines[[#This Row],[DatePaie]]),0,TRUE) -> 2018
B37: Mini Pelle | C37: ZX26 | D37: 26 | E37: ZX26U-5-YLR | F37: SETP | G37: RABASTENS | H37: 1 | I37: =IF(LstMachines[[#This Row],[Delivery]]<Début_HCME, 0, IFERROR( LstMachines[[#This Row],[Nbre]] * INDEX(TabModelSpecs[],MATCH(LstMachines[[#This Row],[Model-Spec]],TabModelSpecs[ModelSpec],0),MATCH("2018",TabModelSpecs[#Headers],0)), LstMachines[[#This Row],[Nbre]]*ROUND(AVERAGEIF(TabModelSpecs[Machine],LstMachines[[#This Row],[Model]],TabModelSpecs[Price]),0) ) ) -> 0 | J37: 43084 | K37: 5-Livrée | L37: 2017-12-06 ADV | N37: 42914 | O37: =MONTH(LstMachines[[#This Row],[Delivery]]) -> 12 | P37: =FIXED(YEAR(LstMachines[[#This Row],[Delivery]]),0,TRUE) -> 2017 | Q37: 17060075 | R37: 20350 | T37: 1-05216-1 1041 | U37: VENTE | V37: 4143 | W37: STOCKBAT | X37: =LstMachines[[#This Row],[Delivery]] -> 43084 | Y37: =IF(MONTH(LstMachines[[#This Row],[DateLivr]])<10,"0","") & MONTH(LstMachines[[#This Row],[DateLivr]]) &"-"&YEAR(LstMachines[[#This Row],[DateLivr]]) -> 12-2017 | Z37: =LstMachines[[#This Row],[Delivery]]+Rglt_à_HCME -> 43144 | AA37: =IF(MONTH(LstMachines[[#This Row],[DatePaie]])<10,"0","") & MONTH(LstMachines[[#This Row],[DatePaie]])&"-"&YEAR(LstMachines[[#This Row],[DatePaie]]) -> 02-2018 | AB37: =LstMachines[[#This Row],[DateLivr]]+1 -> 43085 | AC37: =IF(MONTH(LstMachines[[#This Row],[Distrib]])<10,"0","") & MONTH(LstMachines[[#This Row],[Distrib]]) & "-" & YEAR(LstMachines[[#This Row],[Distrib]]) -> 12-2017 | AD37: =LstMachines[[#This Row],[DateLivr]]+Délai_Vente -> 43204 | AE37: =IF(MONTH(LstMachines[[#This Row],[VteESM]])<10,"0","") & MONTH(LstMachines[[#This Row],[VteESM]]) & "-" & YEAR(LstMachines[[#This Row],[VteESM]]) -> 04-2018 | AF37: =LstMachines[[#This Row],[DateLivr]]+Rglt_à_ESMTP -> 43144 | AG37: =IF(MONTH(LstMachines[[#This Row],[RgltDistrib]])<10,"0","") & MONTH(LstMachines[[#This Row],[RgltDistrib]]) & "-" & YEAR(LstMachines[[#This Row],[RgltDistrib]]) -> 02-2018 | AH37: =LstMachines[[#This Row],[VteESM]]+Rglt_à_ESMTP -> 43264 | AI37: =IF(MONTH(LstMachines[[#This Row],[RgltVteESM]])<10,"0","") & MONTH(LstMachines[[#This Row],[RgltVteESM]]) & "-" & YEAR(LstMachines[[#This Row],[RgltVteESM]]) -> 06-2018 | AJ37: =MONTH(LstMachines[[#This Row],[DatePaie]]) -> 2 | AK37: =FIXED(YEAR(LstMachines[[#This Row],[DatePaie]]),0,TRUE) -> 2018
B38: Chargeuse | C38: ZW75 | D38: 75 | E38: ZW75-6-TPD | F38: SETP | G38: RABASTENS | H38: 1 | I38: =IF(LstMachines[[#This Row],[Delivery]]<Début_HCME, 0, IFERROR( LstMachines[[#This Row],[Nbre]] * INDEX(TabModelSpecs[],MATCH(LstMachines[[#This Row],[Model-Spec]],TabModelSpecs[ModelSpec],0),MATCH("2018",TabModelSpecs[#Headers],0)), LstMachines[[#This Row],[Nbre]]*ROUND(AVERAGEIF(TabModelSpecs[Machine],LstMachines[[#This Row],[Model]],TabModelSpecs[Price]),0) ) ) -> 0 | J38: 43084 | K38: 3-Commande | L38: 2017-12-06 ADV | N38: 43067 | O38: =MONTH(LstMachines[[#This Row],[Delivery]]) -> 12 | P38: =FIXED(YEAR(LstMachines[[#This Row],[Delivery]]),0,TRUE) -> 2017 | Q38: 17110004 | R38: 38070 | U38: STOCK | V38: 4244 | W38: _Stock | X38: =LstMachines[[#This Row],[Delivery]] -> 43084 | Y38: =IF(MONTH(LstMachines[[#This Row],[DateLivr]])<10,"0","") & MONTH(LstMachines[[#This Row],[DateLivr]]) &"-"&YEAR(LstMachines[[#This Row],[DateLivr]]) -> 12-2017 | Z38: =LstMachines[[#This Row],[Delivery]]+Rglt_à_HCME -> 43144 | AA38: =IF(MONTH(LstMachines[[#This Row],[DatePaie]])<10,"0","") & MONTH(LstMachines[[#This Row],[DatePaie]])&"-"&YEAR(LstMachines[[#This Row],[DatePaie]]) -> 02-2018 | AB38: =LstMachines[[#This Row],[DateLivr]]+1 -> 43085 | AC38: =IF(MONTH(LstMachines[[#This Row],[Distrib]])<10,"0","") & MONTH(LstMachines[[#This Row],[Distrib]]) & "-" & YEAR(LstMachines[[#This Row],[Distrib]]) -> 12-2017 | AD38: =LstMachines[[#This Row],[DateLivr]]+Délai_Vente -> 43204 | AE38: =IF(MONTH(LstMachines[[#This Row],[VteESM]])<10,"0","") & MONTH(LstMachines[[#This Row],[VteESM]]) & "-" & YEAR(LstMachines[[#This Row],[VteESM]]) -> 04-2018 | AF38: =LstMachines[[#This Row],[DateLivr]]+Rglt_à_ESMTP -> 43144 | AG38: =IF(MONTH(LstMachines[[#This Row],[RgltDistrib]])<10,"0","") & MONTH(LstMachines[[#This Row],[RgltDistrib]]) & "-" & YEAR(LstMachines[[#This Row],[RgltDistrib]]) -> 02-2018 | AH38: =LstMachines[[#This Row],[VteESM]]+Rglt_à_ESMTP -> 43264 | AI38: =IF(MONTH(LstMachines[[#This Row],[RgltVteESM]])<10,"0","") & MONTH(LstMachines[[#This Row],[RgltVteESM]]) & "-" & YEAR(LstMachines[[#This Row],[RgltVteESM]]) -> 06-2018 | AJ38: =MONTH(LstMachines[[#This Row],[DatePaie]]) -> 2 | AK38: =FIXED(YEAR(LstMachines[[#This Row],[DatePaie]]),0,TRUE) -> 2018
B39: Mini Pelle | C39: ZX65 | D39: 65 | E39: ZX65USB-5-CLR | F39: SETP | G39: RABASTENS | H39: 1 | I39: =IF(LstMachines[[#This Row],[Delivery]]<Début_HCME, 0, IFERROR( LstMachines[[#This Row],[Nbre]] * INDEX(TabModelSpecs[],MATCH(LstMachines[[#This Row],[Model-Spec]],TabModelSpecs[ModelSpec],0),MATCH("2018",TabModelSpecs[#Headers],0)), LstMachines[[#This Row],[Nbre]]*ROUND(AVERAGEIF(TabModelSpecs[Machine],LstMachines[[#This Row],[Model]],TabModelSpecs[Price]),0) ) ) -> 0 | J39: 43084 | K39: 3-Commande | L39: 2017-12-06 ADV | M39: à donner à XMTP - délai décalé | N39: 42914 | O39: =MONTH(LstMachines[[#This Row],[Delivery]]) -> 12 | P39: =FIXED(YEAR(LstMachines[[#This Row],[Delivery]]),0,TRUE) -> 2017 | Q39: 17060097 | R39: 45000 | T39: 1-05174-1 1042 | U39: STOCK | V39: 4150 | W39: _Stock | X39: =LstMachines[[#This Row],[Delivery]] -> 43084 | Y39: =IF(MONTH(LstMachines[[#This Row],[DateLivr]])<10,"0","") & MONTH(LstMachines[[#This Row],[DateLivr]]) &"-"&YEAR(LstMachines[[#This Row],[DateLivr]]) -> 12-2017 | Z39: =LstMachines[[#This Row],[Delivery]]+Rglt_à_HCME -> 43144 | AA39: =IF(MONTH(LstMachines[[#This Row],[DatePaie]])<10,"0","") & MONTH(LstMachines[[#This Row],[DatePaie]])&"-"&YEAR(LstMachines[[#This Row],[DatePaie]]) -> 02-2018 | AB39: =LstMachines[[#This Row],[DateLivr]]+1 -> 43085 | AC39: =IF(MONTH(LstMachines[[#This Row],[Distrib]])<10,"0","") & MONTH(LstMachines[[#This Row],[Distrib]]) & "-" & YEAR(LstMachines[[#This Row],[Distrib]]) -> 12-2017 | AD39: =LstMachines[[#This Row],[DateLivr]]+Délai_Vente -> 43204 | AE39: =IF(MONTH(LstMachines[[#This Row],[VteESM]])<10,"0","") & MONTH(LstMachines[[#This Row],[VteESM]]) & "-" & YEAR(LstMachines[[#This Row],[VteESM]]) -> 04-2018 | AF39: =LstMachines[[#This Row],[DateLivr]]+Rglt_à_ESMTP -> 43144 | AG39: =IF(MONTH(LstMachines[[#This Row],[RgltDistrib]])<10,"0","") & MONTH(LstMachines[[#This Row],[RgltDistrib]]) & "-" & YEAR(LstMachines[[#This Row],[RgltDistrib]]) -> 02-2018 | AH39: =LstMachines[[#This Row],[VteESM]]+Rglt_à_ESMTP -> 43264 | AI39: =IF(MONTH(LstMachines[[#This Row],[RgltVteESM]])<10,"0","") & MONTH(LstMachines[[#This Row],[RgltVteESM]]) & "-" & YEAR(LstMachines[[#This Row],[RgltVteESM]]) -> 06-2018 | AJ39: =MONTH(LstMachines[[#This Row],[DatePaie]]) -> 2 | AK39: =FIXED(YEAR(LstMachines[[#This Row],[DatePaie]]),0,TRUE) -> 2018
B40: Pelle/Chenilles | C40: ZX85 | D40: 85 | E40: ZX85USB-5A-Mono | F40: SETP | G40: RABASTENS | H40: 1 | I40: =IF(LstMachines[[#This Row],[Delivery]]<Début_HCME, 0, IFERROR( LstMachines[[#This Row],[Nbre]] * INDEX(TabModelSpecs[],MATCH(LstMachines[[#This Row],[Model-Spec]],TabModelSpecs[ModelSpec],0),MATCH("2018",TabModelSpecs[#Headers],0)), LstMachines[[#This Row],[Nbre]]*ROUND(AVERAGEIF(TabModelSpecs[Machine],LstMachines[[#This Row],[Model]],TabModelSpecs[Price]),0) ) ) -> 0 | J40: 43084 | K40: ** Lost ** | L40: 2017-10 ADV | M40: ** Lost ** | N40: 43070 | O40: =MONTH(LstMachines[[#This Row],[Delivery]]) -> 12 | P40: =FIXED(YEAR(LstMachines[[#This Row],[Delivery]]),0,TRUE) -> 2017 | X40: =LstMachines[[#This Row],[Delivery]] -> 43084 | Y40: =IF(MONTH(LstMachines[[#This Row],[DateLivr]])<10,"0","") & MONTH(LstMachines[[#This Row],[DateLivr]]) &"-"&YEAR(LstMachines[[#This Row],[DateLivr]]) -> 12-2017 | Z40: =LstMachines[[#This Row],[Delivery]]+Rglt_à_HCME -> 43144 | AA40: =IF(MONTH(LstMachines[[#This Row],[DatePaie]])<10,"0","") & MONTH(LstMachines[[#This Row],[DatePaie]])&"-"&YEAR(LstMachines[[#This Row],[DatePaie]]) -> 02-2018 | AB40: =LstMachines[[#This Row],[DateLivr]]+1 -> 43085 | AC40: =IF(MONTH(LstMachines[[#This Row],[Distrib]])<10,"0","") & MONTH(LstMachines[[#This Row],[Distrib]]) & "-" & YEAR(LstMachines[[#This Row],[Distrib]]) -> 12-2017 | AD40: =LstMachines[[#This Row],[DateLivr]]+Délai_Vente -> 43204 | AE40: =IF(MONTH(LstMachines[[#This Row],[VteESM]])<10,"0","") & MONTH(LstMachines[[#This Row],[VteESM]]) & "-" & YEAR(LstMachines[[#This Row],[VteESM]]) -> 04-2018 | AF40: =LstMachines[[#This Row],[DateLivr]]+Rglt_à_ESMTP -> 43144 | AG40: =IF(MONTH(LstMachines[[#This Row],[RgltDistrib]])<10,"0","") & MONTH(LstMachines[[#This Row],[RgltDistrib]]) & "-" & YEAR(LstMachines[[#This Row],[RgltDistrib]]) -> 02-2018 | AH40: =LstMachines[[#This Row],[VteESM]]+Rglt_à_ESMTP -> 43264 | AI40: =IF(MONTH(LstMachines[[#This Row],[RgltVteESM]])<10,"0","") & MONTH(LstMachines[[#This Row],[RgltVteESM]]) & "-" & YEAR(LstMachines[[#This Row],[RgltVteESM]]) -> 06-2018 | AJ40: =MONTH(LstMachines[[#This Row],[DatePaie]]) -> 2 | AK40: =FIXED(YEAR(LstMachines[[#This Row],[DatePaie]]),0,TRUE) -> 2018
B41: Pelle/Chenilles | C41: ZX210 | D41: 210 | E41: ZX210LC-6-MN | F41: BTPS | G41: ORTHEZ | H41: 1 | I41: =IF(LstMachines[[#This Row],[Delivery]]<Début_HCME, 0, IFERROR( LstMachines[[#This Row],[Nbre]] * INDEX(TabModelSpecs[],MATCH(LstMachines[[#This Row],[Model-Spec]],TabModelSpecs[ModelSpec],0),MATCH("2018",TabModelSpecs[#Headers],0)), LstMachines[[#This Row],[Nbre]]*ROUND(AVERAGEIF(TabModelSpecs[Machine],LstMachines[[#This Row],[Model]],TabModelSpecs[Price]),0) ) ) -> 118 | J41: 43115 | K41: 3-Commande | L41: 2017-11 BTPS | O41: =MONTH(LstMachines[[#This Row],[Delivery]]) -> 1 | P41: =FIXED(YEAR(LstMachines[[#This Row],[Delivery]]),0,TRUE) -> 2018 | X41: =LstMachines[[#This Row],[Delivery]] -> 43115 | Y41: =IF(MONTH(LstMachines[[#This Row],[DateLivr]])<10,"0","") & MONTH(LstMachines[[#This Row],[DateLivr]]) &"-"&YEAR(LstMachines[[#This Row],[DateLivr]]) -> 01-2018 | Z41: =LstMachines[[#This Row],[Delivery]]+Rglt_à_HCME -> 43175 | AA41: =IF(MONTH(LstMachines[[#This Row],[DatePaie]])<10,"0","") & MONTH(LstMachines[[#This Row],[DatePaie]])&"-"&YEAR(LstMachines[[#This Row],[DatePaie]]) -> 03-2018 | AB41: =LstMachines[[#This Row],[DateLivr]]+1 -> 43116 | AC41: =IF(MONTH(LstMachines[[#This Row],[Distrib]])<10,"0","") & MONTH(LstMachines[[#This Row],[Distrib]]) & "-" & YEAR(LstMachines[[#This Row],[Distrib]]) -> 01-2018 | AD41: =LstMachines[[#This Row],[DateLivr]]+Délai_Vente -> 43235 | AE41: =IF(MONTH(LstMachines[[#This Row],[VteESM]])<10,"0","") & MONTH(LstMachines[[#This Row],[VteESM]]) & "-" & YEAR(LstMachines[[#This Row],[VteESM]]) -> 05-2018 | AF41: =LstMachines[[#This Row],[DateLivr]]+Rglt_à_ESMTP -> 43175 | AG41: =IF(MONTH(LstMachines[[#This Row],[RgltDistrib]])<10,"0","") & MONTH(LstMachines[[#This Row],[RgltDistrib]]) & "-" & YEAR(LstMachines[[#This Row],[RgltDistrib]]) -> 03-2018 | AH41: =LstMachines[[#This Row],[VteESM]]+Rglt_à_ESMTP -> 43295 | AI41: =IF(MONTH(LstMachines[[#This Row],[RgltVteESM]])<10,"0","") & MONTH(LstMachines[[#This Row],[RgltVteESM]]) & "-" & YEAR(LstMachines[[#This Row],[RgltVteESM]]) -> 07-2018 | AJ41: =MONTH(LstMachines[[#This Row],[DatePaie]]) -> 3 | AK41: =FIXED(YEAR(LstMachines[[#This Row],[DatePaie]]),0,TRUE) -> 2018
B42: Mini Pelle | C42: ZX26 | D42: 26 | E42: ZX26U-5-YLR | F42: BTPS | G42: ORTHEZ | H42: 1 | I42: =IF(LstMachines[[#This Row],[Delivery]]<Début_HCME, 0, IFERROR( LstMachines[[#This Row],[Nbre]] * INDEX(TabModelSpecs[],MATCH(LstMachines[[#This Row],[Model-Spec]],TabModelSpecs[ModelSpec],0),MATCH("2018",TabModelSpecs[#Headers],0)), LstMachines[[#This Row],[Nbre]]*ROUND(AVERAGEIF(TabModelSpecs[Machine],LstMachines[[#This Row],[Model]],TabModelSpecs[Price]),0) ) ) -> 22 | J42: 43115 | K42: 3-Commande | L42: 2017-11 BTPS | O42: =MONTH(LstMachines[[#This Row],[Delivery]]) -> 1 | P42: =FIXED(YEAR(LstMachines[[#This Row],[Delivery]]),0,TRUE) -> 2018 | X42: =LstMachines[[#This Row],[Delivery]] -> 43115 | Y42: =IF(MONTH(LstMachines[[#This Row],[DateLivr]])<10,"0","") & MONTH(LstMachines[[#This Row],[DateLivr]]) &"-"&YEAR(LstMachines[[#This Row],[DateLivr]]) -> 01-2018 | Z42: =LstMachines[[#This Row],[Delivery]]+Rglt_à_HCME -> 43175 | AA42: =IF(MONTH(LstMachines[[#This Row],[DatePaie]])<10,"0","") & MONTH(LstMachines[[#This Row],[DatePaie]])&"-"&YEAR(LstMachines[[#This Row],[DatePaie]]) -> 03-2018 | AB42: =LstMachines[[#This Row],[DateLivr]]+1 -> 43116 | AC42: =IF(MONTH(LstMachines[[#This Row],[Distrib]])<10,"0","") & MONTH(LstMachines[[#This Row],[Distrib]]) & "-" & YEAR(LstMachines[[#This Row],[Distrib]]) -> 01-2018 | AD42: =LstMachines[[#This Row],[DateLivr]]+Délai_Vente -> 43235 | AE42: =IF(MONTH(LstMachines[[#This Row],[VteESM]])<10,"0","") & MONTH(LstMachines[[#This Row],[VteESM]]) & "-" & YEAR(LstMachines[[#This Row],[VteESM]]) -> 05-2018 | AF42: =LstMachines[[#This Row],[DateLivr]]+Rglt_à_ESMTP -> 43175 | AG42: =IF(MONTH(LstMachines[[#This Row],[RgltDistrib]])<10,"0","") & MONTH(LstMachines[[#This Row],[RgltDistrib]]) & "-" & YEAR(LstMachines[[#This Row],[RgltDistrib]]) -> 03-2018 | AH42: =LstMachines[[#This Row],[VteESM]]+Rglt_à_ESMTP -> 43295 | AI42: =IF(MONTH(LstMachines[[#This Row],[RgltVteESM]])<10,"0","") & MONTH(LstMachines[[#This Row],[RgltVteESM]]) & "-" & YEAR(LstMachines[[#This Row],[RgltVteESM]]) -> 07-2018 | AJ42: =MONTH(LstMachines[[#This Row],[DatePaie]]) -> 3 | AK42: =FIXED(YEAR(LstMachines[[#This Row],[DatePaie]]),0,TRUE) -> 2018
B43: Mini Pelle | C43: ZX26 | D43: 26 | E43: ZX26U-5-YLR | F43: BTPS | G43: ORTHEZ | H43: 1 | I43: =IF(LstMachines[[#This Row],[Delivery]]<Début_HCME, 0, IFERROR( LstMachines[[#This Row],[Nbre]] * INDEX(TabModelSpecs[],MATCH(LstMachines[[#This Row],[Model-Spec]],TabModelSpecs[ModelSpec],0),MATCH("2018",TabModelSpecs[#Headers],0)), LstMachines[[#This Row],[Nbre]]*ROUND(AVERAGEIF(TabModelSpecs[Machine],LstMachines[[#This Row],[Model]],TabModelSpecs[Price]),0) ) ) -> 22 | J43: 43115 | K43: 3-Commande | L43: 2017-11 BTPS | O43: =MONTH(LstMachines[[#This Row],[Delivery]]) -> 1 | P43: =FIXED(YEAR(LstMachines[[#This Row],[Delivery]]),0,TRUE) -> 2018 | X43: =LstMachines[[#This Row],[Delivery]] -> 43115 | Y43: =IF(MONTH(LstMachines[[#This Row],[DateLivr]])<10,"0","") & MONTH(LstMachines[[#This Row],[DateLivr]]) &"-"&YEAR(LstMachines[[#This Row],[DateLivr]]) -> 01-2018 | Z43: =LstMachines[[#This Row],[Delivery]]+Rglt_à_HCME -> 43175 | AA43: =IF(MONTH(LstMachines[[#This Row],[DatePaie]])<10,"0","") & MONTH(LstMachines[[#This Row],[DatePaie]])&"-"&YEAR(LstMachines[[#This Row],[DatePaie]]) -> 03-2018 | AB43: =LstMachines[[#This Row],[DateLivr]]+1 -> 43116 | AC43: =IF(MONTH(LstMachines[[#This Row],[Distrib]])<10,"0","") & MONTH(LstMachines[[#This Row],[Distrib]]) & "-" & YEAR(LstMachines[[#This Row],[Distrib]]) -> 01-2018 | AD43: =LstMachines[[#This Row],[DateLivr]]+Délai_Vente -> 43235 | AE43: =IF(MONTH(LstMachines[[#This Row],[VteESM]])<10,"0","") & MONTH(LstMachines[[#This Row],[VteESM]]) & "-" & YEAR(LstMachines[[#This Row],[VteESM]]) -> 05-2018 | AF43: =LstMachines[[#This Row],[DateLivr]]+Rglt_à_ESMTP -> 43175 | AG43: =IF(MONTH(LstMachines[[#This Row],[RgltDistrib]])<10,"0","") & MONTH(LstMachines[[#This Row],[RgltDistrib]]) & "-" & YEAR(LstMachines[[#This Row],[RgltDistrib]]) -> 03-2018 | AH43: =LstMachines[[#This Row],[VteESM]]+Rglt_à_ESMTP -> 43295 | AI43: =IF(MONTH(LstMachines[[#This Row],[RgltVteESM]])<10,"0","") & MONTH(LstMachines[[#This Row],[RgltVteESM]]) & "-" & YEAR(LstMachines[[#This Row],[RgltVteESM]]) -> 07-2018 | AJ43: =MONTH(LstMachines[[#This Row],[DatePaie]]) -> 3 | AK43: =FIXED(YEAR(LstMachines[[#This Row],[DatePaie]]),0,TRUE) -> 2018
B44: Mini Pelle | C44: ZX26 | D44: 26 | E44: ZX26U-5-YLR | F44: BTPS | G44: ORTHEZ | H44: 1 | I44: =IF(LstMachines[[#This Row],[Delivery]]<Début_HCME, 0, IFERROR( LstMachines[[#This Row],[Nbre]] * INDEX(TabModelSpecs[],MATCH(LstMachines[[#This Row],[Model-Spec]],TabModelSpecs[ModelSpec],0),MATCH("2018",TabModelSpecs[#Headers],0)), LstMachines[[#This Row],[Nbre]]*ROUND(AVERAGEIF(TabModelSpecs[Machine],LstMachines[[#This Row],[Model]],TabModelSpecs[Price]),0) ) ) -> 22 | J44: 43115 | K44: 3-Commande | L44: 2017-11 BTPS | O44: =MONTH(LstMachines[[#This Row],[Delivery]]) -> 1 | P44: =FIXED(YEAR(LstMachines[[#This Row],[Delivery]]),0,TRUE) -> 2018 | X44: =LstMachines[[#This Row],[Delivery]] -> 43115 | Y44: =IF(MONTH(LstMachines[[#This Row],[DateLivr]])<10,"0","") & MONTH(LstMachines[[#This Row],[DateLivr]]) &"-"&YEAR(LstMachines[[#This Row],[DateLivr]]) -> 01-2018 | Z44: =LstMachines[[#This Row],[Delivery]]+Rglt_à_HCME -> 43175 | AA44: =IF(MONTH(LstMachines[[#This Row],[DatePaie]])<10,"0","") & MONTH(LstMachines[[#This Row],[DatePaie]])&"-"&YEAR(LstMachines[[#This Row],[DatePaie]]) -> 03-2018 | AB44: =LstMachines[[#This Row],[DateLivr]]+1 -> 43116 | AC44: =IF(MONTH(LstMachines[[#This Row],[Distrib]])<10,"0","") & MONTH(LstMachines[[#This Row],[Distrib]]) & "-" & YEAR(LstMachines[[#This Row],[Distrib]]) -> 01-2018 | AD44: =LstMachines[[#This Row],[DateLivr]]+Délai_Vente -> 43235 | AE44: =IF(MONTH(LstMachines[[#This Row],[VteESM]])<10,"0","") & MONTH(LstMachines[[#This Row],[VteESM]]) & "-" & YEAR(LstMachines[[#This Row],[VteESM]]) -> 05-2018 | AF44: =LstMachines[[#This Row],[DateLivr]]+Rglt_à_ESMTP -> 43175 | AG44: =IF(MONTH(LstMachines[[#This Row],[RgltDistrib]])<10,"0","") & MONTH(LstMachines[[#This Row],[RgltDistrib]]) & "-" & YEAR(LstMachines[[#This Row],[RgltDistrib]]) -> 03-2018 | AH44: =LstMachines[[#This Row],[VteESM]]+Rglt_à_ESMTP -> 43295 | AI44: =IF(MONTH(LstMachines[[#This Row],[RgltVteESM]])<10,"0","") & MONTH(LstMachines[[#This Row],[RgltVteESM]]) & "-" & YEAR(LstMachines[[#This Row],[RgltVteESM]]) -> 07-2018 | AJ44: =MONTH(LstMachines[[#This Row],[DatePaie]]) -> 3 | AK44: =FIXED(YEAR(LstMachines[[#This Row],[DatePaie]]),0,TRUE) -> 2018
B45: Mini Pelle | C45: ZX19 | D45: 19 | E45: ZX19U-5 | F45: BTPS | G45: ORTHEZ | H45: 1 | I45: =IF(LstMachines[[#This Row],[Delivery]]<Début_HCME, 0, IFERROR( LstMachines[[#This Row],[Nbre]] * INDEX(TabModelSpecs[],MATCH(LstMachines[[#This Row],[Model-Spec]],TabModelSpecs[ModelSpec],0),MATCH("2018",TabModelSpecs[#Headers],0)), LstMachines[[#This Row],[Nbre]]*ROUND(AVERAGEIF(TabModelSpecs[Machine],LstMachines[[#This Row],[Model]],TabModelSpecs[Price]),0) ) ) -> 18 | J45: 43115 | K45: 1-Forecast | L45: 2017-11 BTPS | O45: =MONTH(LstMachines[[#This Row],[Delivery]]) -> 1 | P45: =FIXED(YEAR(LstMachines[[#This Row],[Delivery]]),0,TRUE) -> 2018 | X45: =LstMachines[[#This Row],[Delivery]] -> 43115 | Y45: =IF(MONTH(LstMachines[[#This Row],[DateLivr]])<10,"0","") & MONTH(LstMachines[[#This Row],[DateLivr]]) &"-"&YEAR(LstMachines[[#This Row],[DateLivr]]) -> 01-2018 | Z45: =LstMachines[[#This Row],[Delivery]]+Rglt_à_HCME -> 43175 | AA45: =IF(MONTH(LstMachines[[#This Row],[DatePaie]])<10,"0","") & MONTH(LstMachines[[#This Row],[DatePaie]])&"-"&YEAR(LstMachines[[#This Row],[DatePaie]]) -> 03-2018 | AB45: =LstMachines[[#This Row],[DateLivr]]+1 -> 43116 | AC45: =IF(MONTH(LstMachines[[#This Row],[Distrib]])<10,"0","") & MONTH(LstMachines[[#This Row],[Distrib]]) & "-" & YEAR(LstMachines[[#This Row],[Distrib]]) -> 01-2018 | AD45: =LstMachines[[#This Row],[DateLivr]]+Délai_Vente -> 43235 | AE45: =IF(MONTH(LstMachines[[#This Row],[VteESM]])<10,"0","") & MONTH(LstMachines[[#This Row],[VteESM]]) & "-" & YEAR(LstMachines[[#This Row],[VteESM]]) -> 05-2018 | AF45: =LstMachines[[#This Row],[DateLivr]]+Rglt_à_ESMTP -> 43175 | AG45: =IF(MONTH(LstMachines[[#This Row],[RgltDistrib]])<10,"0","") & MONTH(LstMachines[[#This Row],[RgltDistrib]]) & "-" & YEAR(LstMachines[[#This Row],[RgltDistrib]]) -> 03-2018 | AH45: =LstMachines[[#This Row],[VteESM]]+Rglt_à_ESMTP -> 43295 | AI45: =IF(MONTH(LstMachines[[#This Row],[RgltVteESM]])<10,"0","") & MONTH(LstMachines[[#This Row],[RgltVteESM]]) & "-" & YEAR(LstMachines[[#This Row],[RgltVteESM]]) -> 07-2018 | AJ45: =MONTH(LstMachines[[#This Row],[DatePaie]]) -> 3 | AK45: =FIXED(YEAR(LstMachines[[#This Row],[DatePaie]]),0,TRUE) -> 2018
B46: Chargeuse | C46: ZW95 | D46: 95 | E46: ZW95-6 | F46: LIMA TP | G46: BOISSEUIL | H46: 1 | I46: =IF(LstMachines[[#This Row],[Delivery]]<Début_HCME, 0, IFERROR( LstMachines[[#This Row],[Nbre]] * INDEX(TabModelSpecs[],MATCH(LstMachines[[#This Row],[Model-Spec]],TabModelSpecs[ModelSpec],0),MATCH("2018",TabModelSpecs[#Headers],0)), LstMachines[[#This Row],[Nbre]]*ROUND(AVERAGEIF(TabModelSpecs[Machine],LstMachines[[#This Row],[Model]],TabModelSpecs[Price]),0) ) ) -> 75 | J46: 43115 | K46: 3-Commande | L46: 2017-12-29 LIMA | O46: =MONTH(LstMachines[[#This Row],[Delivery]]) -> 1 | P46: =FIXED(YEAR(LstMachines[[#This Row],[Delivery]]),0,TRUE) -> 2018 | W46: _Client x | X46: =LstMachines[[#This Row],[Delivery]] -> 43115 | Y46: =IF(MONTH(LstMachines[[#This Row],[DateLivr]])<10,"0","") & MONTH(LstMachines[[#This Row],[DateLivr]]) &"-"&YEAR(LstMachines[[#This Row],[DateLivr]]) -> 01-2018 | Z46: =LstMachines[[#This Row],[Delivery]]+Rglt_à_HCME -> 43175 | AA46: =IF(MONTH(LstMachines[[#This Row],[DatePaie]])<10,"0","") & MONTH(LstMachines[[#This Row],[DatePaie]])&"-"&YEAR(LstMachines[[#This Row],[DatePaie]]) -> 03-2018 | AB46: =LstMachines[[#This Row],[DateLivr]]+1 -> 43116 | AC46: =IF(MONTH(LstMachines[[#This Row],[Distrib]])<10,"0","") & MONTH(LstMachines[[#This Row],[Distrib]]) & "-" & YEAR(LstMachines[[#This Row],[Distrib]]) -> 01-2018 | AD46: =LstMachines[[#This Row],[DateLivr]]+Délai_Vente -> 43235 | AE46: =IF(MONTH(LstMachines[[#This Row],[VteESM]])<10,"0","") & MONTH(LstMachines[[#This Row],[VteESM]]) & "-" & YEAR(LstMachines[[#This Row],[VteESM]]) -> 05-2018 | AF46: =LstMachines[[#This Row],[DateLivr]]+Rglt_à_ESMTP -> 43175 | AG46: =IF(MONTH(LstMachines[[#This Row],[RgltDistrib]])<10,"0","") & MONTH(LstMachines[[#This Row],[RgltDistrib]]) & "-" & YEAR(LstMachines[[#This Row],[RgltDistrib]]) -> 03-2018 | AH46: =LstMachines[[#This Row],[VteESM]]+Rglt_à_ESMTP -> 43295 | AI46: =IF(MONTH(LstMachines[[#This Row],[RgltVteESM]])<10,"0","") & MONTH(LstMachines[[#This Row],[RgltVteESM]]) & "-" & YEAR(LstMachines[[#This Row],[RgltVteESM]]) -> 07-2018 | AJ46: =MONTH(LstMachines[[#This Row],[DatePaie]]) -> 3 | AK46: =FIXED(YEAR(LstMachines[[#This Row],[DatePaie]]),0,TRUE) -> 2018
B47: Pelle/Chenilles | C47: ZX85 | D47: 85 | E47: ZX85USB-5A-Mono | F47: LIMA TP | G47: BOISSEUIL | H47: 1 | I47: =IF(LstMachines[[#This Row],[Delivery]]<Début_HCME, 0, IFERROR( LstMachines[[#This Row],[Nbre]] * INDEX(TabModelSpecs[],MATCH(LstMachines[[#This Row],[Model-Spec]],TabModelSpecs[ModelSpec],0),MATCH("2018",TabModelSpecs[#Headers],0)), LstMachines[[#This Row],[Nbre]]*ROUND(AVERAGEIF(TabModelSpecs[Machine],LstMachines[[#This Row],[Model]],TabModelSpecs[Price]),0) ) ) -> 64 | J47: 43115 | K47: 3-Commande | L47: 2017-12-29 LIMA | O47: =MONTH(LstMachines[[#This Row],[Delivery]]) -> 1 | P47: =FIXED(YEAR(LstMachines[[#This Row],[Delivery]]),0,TRUE) -> 2018 | W47: _Client x | X47: =LstMachines[[#This Row],[Delivery]] -> 43115 | Y47: =IF(MONTH(LstMachines[[#This Row],[DateLivr]])<10,"0","") & MONTH(LstMachines[[#This Row],[DateLivr]]) &"-"&YEAR(LstMachines[[#This Row],[DateLivr]]) -> 01-2018 | Z47: =LstMachines[[#This Row],[Delivery]]+Rglt_à_HCME -> 43175 | AA47: =IF(MONTH(LstMachines[[#This Row],[DatePaie]])<10,"0","") & MONTH(LstMachines[[#This Row],[DatePaie]])&"-"&YEAR(LstMachines[[#This Row],[DatePaie]]) -> 03-2018 | AB47: =LstMachines[[#This Row],[DateLivr]]+1 -> 43116 | AC47: =IF(MONTH(LstMachines[[#This Row],[Distrib]])<10,"0","") & MONTH(LstMachines[[#This Row],[Distrib]]) & "-" & YEAR(LstMachines[[#This Row],[Distrib]]) -> 01-2018 | AD47: =LstMachines[[#This Row],[DateLivr]]+Délai_Vente -> 43235 | AE47: =IF(MONTH(LstMachines[[#This Row],[VteESM]])<10,"0","") & MONTH(LstMachines[[#This Row],[VteESM]]) & "-" & YEAR(LstMachines[[#This Row],[VteESM]]) -> 05-2018 | AF47: =LstMachines[[#This Row],[DateLivr]]+Rglt_à_ESMTP -> 43175 | AG47: =IF(MONTH(LstMachines[[#This Row],[RgltDistrib]])<10,"0","") & MONTH(LstMachines[[#This Row],[RgltDistrib]]) & "-" & YEAR(LstMachines[[#This Row],[RgltDistrib]]) -> 03-2018 | AH47: =LstMachines[[#This Row],[VteESM]]+Rglt_à_ESMTP -> 43295 | AI47: =IF(MONTH(LstMachines[[#This Row],[RgltVteESM]])<10,"0","") & MONTH(LstMachines[[#This Row],[RgltVteESM]]) & "-" & YEAR(LstMachines[[#This Row],[RgltVteESM]]) -> 07-2018 | AJ47: =MONTH(LstMachines[[#This Row],[DatePaie]]) -> 3 | AK47: =FIXED(YEAR(LstMachines[[#This Row],[DatePaie]]),0,TRUE) -> 2018
B48: Mini Pelle | C48: ZX26 | D48: 26 | E48: ZX26U-5-CLR | F48: LIMA TP | G48: BOISSEUIL | H48: 1 | I48: 23 | J48: 43115 | K48: 3-Commande | L48: 2017-12-29 LIMA | O48: =MONTH(LstMachines[[#This Row],[Delivery]]) -> 1 | P48: =FIXED(YEAR(LstMachines[[#This Row],[Delivery]]),0,TRUE) -> 2018 | W48: _Stock | X48: =LstMachines[[#This Row],[Delivery]] -> 43115 | Y48: =IF(MONTH(LstMachines[[#This Row],[DateLivr]])<10,"0","") & MONTH(LstMachines[[#This Row],[DateLivr]]) &"-"&YEAR(LstMachines[[#This Row],[DateLivr]]) -> 01-2018 | Z48: =LstMachines[[#This Row],[Delivery]]+Rglt_à_HCME -> 43175 | AA48: =IF(MONTH(LstMachines[[#This Row],[DatePaie]])<10,"0","") & MONTH(LstMachines[[#This Row],[DatePaie]])&"-"&YEAR(LstMachines[[#This Row],[DatePaie]]) -> 03-2018 | AB48: =LstMachines[[#This Row],[DateLivr]]+1 -> 43116 | AC48: =IF(MONTH(LstMachines[[#This Row],[Distrib]])<10,"0","") & MONTH(LstMachines[[#This Row],[Distrib]]) & "-" & YEAR(LstMachines[[#This Row],[Distrib]]) -> 01-2018 | AD48: =LstMachines[[#This Row],[DateLivr]]+Délai_Vente -> 43235 | AE48: =IF(MONTH(LstMachines[[#This Row],[VteESM]])<10,"0","") & MONTH(LstMachines[[#This Row],[VteESM]]) & "-" & YEAR(LstMachines[[#This Row],[VteESM]]) -> 05-2018 | AF48: =LstMachines[[#This Row],[DateLivr]]+Rglt_à_ESMTP -> 43175 | AG48: =IF(MONTH(LstMachines[[#This Row],[RgltDistrib]])<10,"0","") & MONTH(LstMachines[[#This Row],[RgltDistrib]]) & "-" & YEAR(LstMachines[[#This Row],[RgltDistrib]]) -> 03-2018 | AH48: =LstMachines[[#This Row],[VteESM]]+Rglt_à_ESMTP -> 43295 | AI48: =IF(MONTH(LstMachines[[#This Row],[RgltVteESM]])<10,"0","") & MONTH(LstMachines[[#This Row],[RgltVteESM]]) & "-" & YEAR(LstMachines[[#This Row],[RgltVteESM]]) -> 07-2018 | AJ48: =MONTH(LstMachines[[#This Row],[DatePaie]]) -> 3 | AK48: =FIXED(YEAR(LstMachines[[#This Row],[DatePaie]]),0,TRUE) -> 2018
B49: Mini Pelle | C49: ZX26 | D49: 26 | E49: ZX26U-5-YLR | F49: SETP | G49: RABASTENS | H49: 1 | I49: =IF(LstMachines[[#This Row],[Delivery]]<Début_HCME, 0, IFERROR( LstMachines[[#This Row],[Nbre]] * INDEX(TabModelSpecs[],MATCH(LstMachines[[#This Row],[Model-Spec]],TabModelSpecs[ModelSpec],0),MATCH("2018",TabModelSpecs[#Headers],0)), LstMachines[[#This Row],[Nbre]]*ROUND(AVERAGEIF(TabModelSpecs[Machine],LstMachines[[#This Row],[Model]],TabModelSpecs[Price]),0) ) ) -> 22 | J49: 43115 | K49: 3-Commande | L49: 2017-12-06 ADV | N49: 42914 | O49: =MONTH(LstMachines[[#This Row],[Delivery]]) -> 1 | P49: =FIXED(YEAR(LstMachines[[#This Row],[Delivery]]),0,TRUE) -> 2018 | Q49: 17060093 | R49: 20350 | U49: VENTE | V49: 4146 | W49: STOCKBAT | X49: =LstMachines[[#This Row],[Delivery]] -> 43115 | Y49: =IF(MONTH(LstMachines[[#This Row],[DateLivr]])<10,"0","") & MONTH(LstMachines[[#This Row],[DateLivr]]) &"-"&YEAR(LstMachines[[#This Row],[DateLivr]]) -> 01-2018 | Z49: =LstMachines[[#This Row],[Delivery]]+Rglt_à_HCME -> 43175 | AA49: =IF(MONTH(LstMachines[[#This Row],[DatePaie]])<10,"0","") & MONTH(LstMachines[[#This Row],[DatePaie]])&"-"&YEAR(LstMachines[[#This Row],[DatePaie]]) -> 03-2018 | AB49: =LstMachines[[#This Row],[DateLivr]]+1 -> 43116 | AC49: =IF(MONTH(LstMachines[[#This Row],[Distrib]])<10,"0","") & MONTH(LstMachines[[#This Row],[Distrib]]) & "-" & YEAR(LstMachines[[#This Row],[Distrib]]) -> 01-2018 | AD49: =LstMachines[[#This Row],[DateLivr]]+Délai_Vente -> 43235 | AE49: =IF(MONTH(LstMachines[[#This Row],[VteESM]])<10,"0","") & MONTH(LstMachines[[#This Row],[VteESM]]) & "-" & YEAR(LstMachines[[#This Row],[VteESM]]) -> 05-2018 | AF49: =LstMachines[[#This Row],[DateLivr]]+Rglt_à_ESMTP -> 43175 | AG49: =IF(MONTH(LstMachines[[#This Row],[RgltDistrib]])<10,"0","") & MONTH(LstMachines[[#This Row],[RgltDistrib]]) & "-" & YEAR(LstMachines[[#This Row],[RgltDistrib]]) -> 03-2018 | AH49: =LstMachines[[#This Row],[VteESM]]+Rglt_à_ESMTP -> 43295 | AI49: =IF(MONTH(LstMachines[[#This Row],[RgltVteESM]])<10,"0","") & MONTH(LstMachines[[#This Row],[RgltVteESM]]) & "-" & YEAR(LstMachines[[#This Row],[RgltVteESM]]) -> 07-2018 | AJ49: =MONTH(LstMachines[[#This Row],[DatePaie]]) -> 3 | AK49: =FIXED(YEAR(LstMachines[[#This Row],[DatePaie]]),0,TRUE) -> 2018
B50: Pelle/Chenilles | C50: ZX85 | D50: 85 | E50: ZX85USB-5A-Mono | F50: SETP | G50: RABASTENS | H50: 1 | I50: =IF(LstMachines[[#This Row],[Delivery]]<Début_HCME, 0, IFERROR( LstMachines[[#This Row],[Nbre]] * INDEX(TabModelSpecs[],MATCH(LstMachines[[#This Row],[Model-Spec]],TabModelSpecs[ModelSpec],0),MATCH("2018",TabModelSpecs[#Headers],0)), LstMachines[[#This Row],[Nbre]]*ROUND(AVERAGEIF(TabModelSpecs[Machine],LstMachines[[#This Row],[Model]],TabModelSpecs[Price]),0) ) ) -> 64 | J50: 43115 | K50: 3-Commande | L50: 2017-12-06 ADV | N50: 42979 | O50: =MONTH(LstMachines[[#This Row],[Delivery]]) -> 1 | P50: =FIXED(YEAR(LstMachines[[#This Row],[Delivery]]),0,TRUE) -> 2018 | Q50: 17100055 | R50: 59260 | U50: VENTE | V50: 4222 | W50: LOC PLUS | X50: =LstMachines[[#This Row],[Delivery]] -> 43115 | Y50: =IF(MONTH(LstMachines[[#This Row],[DateLivr]])<10,"0","") & MONTH(LstMachines[[#This Row],[DateLivr]]) &"-"&YEAR(LstMachines[[#This Row],[DateLivr]]) -> 01-2018 | Z50: =LstMachines[[#This Row],[Delivery]]+Rglt_à_HCME -> 43175 | AA50: =IF(MONTH(LstMachines[[#This Row],[DatePaie]])<10,"0","") & MONTH(LstMachines[[#This Row],[DatePaie]])&"-"&YEAR(LstMachines[[#This Row],[DatePaie]]) -> 03-2018 | AB50: =LstMachines[[#This Row],[DateLivr]]+1 -> 43116 | AC50: =IF(MONTH(LstMachines[[#This Row],[Distrib]])<10,"0","") & MONTH(LstMachines[[#This Row],[Distrib]]) & "-" & YEAR(LstMachines[[#This Row],[Distrib]]) -> 01-2018 | AD50: =LstMachines[[#This Row],[DateLivr]]+Délai_Vente -> 43235 | AE50: =IF(MONTH(LstMachines[[#This Row],[VteESM]])<10,"0","") & MONTH(LstMachines[[#This Row],[VteESM]]) & "-" & YEAR(LstMachines[[#This Row],[VteESM]]) -> 05-2018 | AF50: =LstMachines[[#This Row],[DateLivr]]+Rglt_à_ESMTP -> 43175 | AG50: =IF(MONTH(LstMachines[[#This Row],[RgltDistrib]])<10,"0","") & MONTH(LstMachines[[#This Row],[RgltDistrib]]) & "-" & YEAR(LstMachines[[#This Row],[RgltDistrib]]) -> 03-2018 | AH50: =LstMachines[[#This Row],[VteESM]]+Rglt_à_ESMTP -> 43295 | AI50: =IF(MONTH(LstMachines[[#This Row],[RgltVteESM]])<10,"0","") & MONTH(LstMachines[[#This Row],[RgltVteESM]]) & "-" & YEAR(LstMachines[[#This Row],[RgltVteESM]]) -> 07-2018 | AJ50: =MONTH(LstMachines[[#This Row],[DatePaie]]) -> 3 | AK50: =FIXED(YEAR(LstMachines[[#This Row],[DatePaie]]),0,TRUE) -> 2018
B51: Pelle/Chenilles | C51: ZX135 | D51: 135 | E51: ZX135US-6-2P-BL | F51: SETP | G51: LÉZIGNAN | H51: 1 | I51: =IF(LstMachines[[#This Row],[Delivery]]<Début_HCME, 0, IFERROR( LstMachines[[#This Row],[Nbre]] * INDEX(TabModelSpecs[],MATCH(LstMachines[[#This Row],[Model-Spec]],TabModelSpecs[ModelSpec],0),MATCH("2018",TabModelSpecs[#Headers],0)), LstMachines[[#This Row],[Nbre]]*ROUND(AVERAGEIF(TabModelSpecs[Machine],LstMachines[[#This Row],[Model]],TabModelSpecs[Price]),0) ) ) -> 102 | J51: 43115 | K51: 3-Commande | L51: 2017-12-06 ADV | N51: 42975 | O51: =MONTH(LstMachines[[#This Row],[Delivery]]) -> 1 | P51: =FIXED(YEAR(LstMachines[[#This Row],[Delivery]]),0,TRUE) -> 2018 | Q51: 17080106 | R51: 104000 | U51: LOCATION | V51: 4185 | W51: _TPAL | X51: =LstMachines[[#This Row],[Delivery]] -> 43115 | Y51: =IF(MONTH(LstMachines[[#This Row],[DateLivr]])<10,"0","") & MONTH(LstMachines[[#This Row],[DateLivr]]) &"-"&YEAR(LstMachines[[#This Row],[DateLivr]]) -> 01-2018 | Z51: =LstMachines[[#This Row],[Delivery]]+Rglt_à_HCME -> 43175 | AA51: =IF(MONTH(LstMachines[[#This Row],[DatePaie]])<10,"0","") & MONTH(LstMachines[[#This Row],[DatePaie]])&"-"&YEAR(LstMachines[[#This Row],[DatePaie]]) -> 03-2018 | AB51: =LstMachines[[#This Row],[DateLivr]]+1 -> 43116 | AC51: =IF(MONTH(LstMachines[[#This Row],[Distrib]])<10,"0","") & MONTH(LstMachines[[#This Row],[Distrib]]) & "-" & YEAR(LstMachines[[#This Row],[Distrib]]) -> 01-2018 | AD51: =LstMachines[[#This Row],[DateLivr]]+Délai_Vente -> 43235 | AE51: =IF(MONTH(LstMachines[[#This Row],[VteESM]])<10,"0","") & MONTH(LstMachines[[#This Row],[VteESM]]) & "-" & YEAR(LstMachines[[#This Row],[VteESM]]) -> 05-2018 | AF51: =LstMachines[[#This Row],[DateLivr]]+Rglt_à_ESMTP -> 43175 | AG51: =IF(MONTH(LstMachines[[#This Row],[RgltDistrib]])<10,"0","") & MONTH(LstMachines[[#This Row],[RgltDistrib]]) & "-" & YEAR(LstMachines[[#This Row],[RgltDistrib]]) -> 03-2018 | AH51: =LstMachines[[#This Row],[VteESM]]+Rglt_à_ESMTP -> 43295 | AI51: =IF(MONTH(LstMachines[[#This Row],[RgltVteESM]])<10,"0","") & MONTH(LstMachines[[#This Row],[RgltVteESM]]) & "-" & YEAR(LstMachines[[#This Row],[RgltVteESM]]) -> 07-2018 | AJ51: =MONTH(LstMachines[[#This Row],[DatePaie]]) -> 3 | AK51: =FIXED(YEAR(LstMachines[[#This Row],[DatePaie]]),0,TRUE) -> 2018
B52: Pelle/Chenilles | C52: ZX210 | D52: 210 | E52: ZX210LC-6-MN | F52: XMTP | G52: BORDEAUX | H52: 1 | I52: =IF(LstMachines[[#This Row],[Delivery]]<Début_HCME, 0, IFERROR( LstMachines[[#This Row],[Nbre]] * INDEX(TabModelSpecs[],MATCH(LstMachines[[#This Row],[Model-Spec]],TabModelSpecs[ModelSpec],0),MATCH("2018",TabModelSpecs[#Headers],0)), LstMachines[[#This Row],[Nbre]]*ROUND(AVERAGEIF(TabModelSpecs[Machine],LstMachines[[#This Row],[Model]],TabModelSpecs[Price]),0) ) ) -> 118 | J52: 43115 | K52: 5-Livrée | L52: 2018-02-06 XMTP | O52: =MONTH(LstMachines[[#This Row],[Delivery]]) -> 1 | P52: =FIXED(YEAR(LstMachines[[#This Row],[Delivery]]),0,TRUE) -> 2018 | X52: =LstMachines[[#This Row],[Delivery]] -> 43115 | Y52: =IF(MONTH(LstMachines[[#This Row],[DateLivr]])<10,"0","") & MONTH(LstMachines[[#This Row],[DateLivr]]) &"-"&YEAR(LstMachines[[#This Row],[DateLivr]]) -> 01-2018 | Z52: =LstMachines[[#This Row],[Delivery]]+Rglt_à_HCME -> 43175 | AA52: =IF(MONTH(LstMachines[[#This Row],[DatePaie]])<10,"0","") & MONTH(LstMachines[[#This Row],[DatePaie]])&"-"&YEAR(LstMachines[[#This Row],[DatePaie]]) -> 03-2018 | AB52: =LstMachines[[#This Row],[DateLivr]]+1 -> 43116 | AC52: =IF(MONTH(LstMachines[[#This Row],[Distrib]])<10,"0","") & MONTH(LstMachines[[#This Row],[Distrib]]) & "-" & YEAR(LstMachines[[#This Row],[Distrib]]) -> 01-2018 | AD52: =LstMachines[[#This Row],[DateLivr]]+Délai_Vente -> 43235 | AE52: =IF(MONTH(LstMachines[[#This Row],[VteESM]])<10,"0","") & MONTH(LstMachines[[#This Row],[VteESM]]) & "-" & YEAR(LstMachines[[#This Row],[VteESM]]) -> 05-2018 | AF52: =LstMachines[[#This Row],[DateLivr]]+Rglt_à_ESMTP -> 43175 | AG52: =IF(MONTH(LstMachines[[#This Row],[RgltDistrib]])<10,"0","") & MONTH(LstMachines[[#This Row],[RgltDistrib]]) & "-" & YEAR(LstMachines[[#This Row],[RgltDistrib]]) -> 03-2018 | AH52: =LstMachines[[#This Row],[VteESM]]+Rglt_à_ESMTP -> 43295 | AI52: =IF(MONTH(LstMachines[[#This Row],[RgltVteESM]])<10,"0","") & MONTH(LstMachines[[#This Row],[RgltVteESM]]) & "-" & YEAR(LstMachines[[#This Row],[RgltVteESM]]) -> 07-2018 | AJ52: =MONTH(LstMachines[[#This Row],[DatePaie]]) -> 3 | AK52: =FIXED(YEAR(LstMachines[[#This Row],[DatePaie]]),0,TRUE) -> 2018
B53: Mini Pelle | C53: ZX55 | D53: 55 | E53: ZX55U-5-CLR | F53: XMTP | G53: BORDEAUX | H53: 2 | I53: =IF(LstMachines[[#This Row],[Delivery]]<Début_HCME, 0, IFERROR( LstMachines[[#This Row],[Nbre]] * INDEX(TabModelSpecs[],MATCH(LstMachines[[#This Row],[Model-Spec]],TabModelSpecs[ModelSpec],0),MATCH("2018",TabModelSpecs[#Headers],0)), LstMachines[[#This Row],[Nbre]]*ROUND(AVERAGEIF(TabModelSpecs[Machine],LstMachines[[#This Row],[Model]],TabModelSpecs[Price]),0) ) ) -> 86 | J53: 43115 | K53: 5-Livrée | L53: 2017-12 XMTP | O53: =MONTH(LstMachines[[#This Row],[Delivery]]) -> 1 | P53: =FIXED(YEAR(LstMachines[[#This Row],[Delivery]]),0,TRUE) -> 2018 | U53: VENTE | W53: _Stock | X53: =LstMachines[[#This Row],[Delivery]] -> 43115 | Y53: =IF(MONTH(LstMachines[[#This Row],[DateLivr]])<10,"0","") & MONTH(LstMachines[[#This Row],[DateLivr]]) &"-"&YEAR(LstMachines[[#This Row],[DateLivr]]) -> 01-2018 | Z53: =LstMachines[[#This Row],[Delivery]]+Rglt_à_HCME -> 43175 | AA53: =IF(MONTH(LstMachines[[#This Row],[DatePaie]])<10,"0","") & MONTH(LstMachines[[#This Row],[DatePaie]])&"-"&YEAR(LstMachines[[#This Row],[DatePaie]]) -> 03-2018 | AB53: =LstMachines[[#This Row],[DateLivr]]+1 -> 43116 | AC53: =IF(MONTH(LstMachines[[#This Row],[Distrib]])<10,"0","") & MONTH(LstMachines[[#This Row],[Distrib]]) & "-" & YEAR(LstMachines[[#This Row],[Distrib]]) -> 01-2018 | AD53: =LstMachines[[#This Row],[DateLivr]]+Délai_Vente -> 43235 | AE53: =IF(MONTH(LstMachines[[#This Row],[VteESM]])<10,"0","") & MONTH(LstMachines[[#This Row],[VteESM]]) & "-" & YEAR(LstMachines[[#This Row],[VteESM]]) -> 05-2018 | AF53: =LstMachines[[#This Row],[DateLivr]]+Rglt_à_ESMTP -> 43175 | AG53: =IF(MONTH(LstMachines[[#This Row],[RgltDistrib]])<10,"0","") & MONTH(LstMachines[[#This Row],[RgltDistrib]]) & "-" & YEAR(LstMachines[[#This Row],[RgltDistrib]]) -> 03-2018 | AH53: =LstMachines[[#This Row],[VteESM]]+Rglt_à_ESMTP -> 43295 | AI53: =IF(MONTH(LstMachines[[#This Row],[RgltVteESM]])<10,"0","") & MONTH(LstMachines[[#This Row],[RgltVteESM]]) & "-" & YEAR(LstMachines[[#This Row],[RgltVteESM]]) -> 07-2018 | AJ53: =MONTH(LstMachines[[#This Row],[DatePaie]]) -> 3 | AK53: =FIXED(YEAR(LstMachines[[#This Row],[DatePaie]]),0,TRUE) -> 2018
B54: Mini Pelle | C54: ZX48 | D54: 48 | E54: ZX48U-5-CLR | F54: XMTP | G54: BORDEAUX | H54: 1 | I54: =IF(LstMachines[[#This Row],[Delivery]]<Début_HCME, 0, IFERROR( LstMachines[[#This Row],[Nbre]] * INDEX(TabModelSpecs[],MATCH(LstMachines[[#This Row],[Model-Spec]],TabModelSpecs[ModelSpec],0),MATCH("2018",TabModelSpecs[#Headers],0)), LstMachines[[#This Row],[Nbre]]*ROUND(AVERAGEIF(TabModelSpecs[Machine],LstMachines[[#This Row],[Model]],TabModelSpecs[Price]),0) ) ) -> 41 | J54: 43115 | K54: 5-Livrée | L54: 2017-12 XMTP | O54: =MONTH(LstMachines[[#This Row],[Delivery]]) -> 1 | P54: =FIXED(YEAR(LstMachines[[#This Row],[Delivery]]),0,TRUE) -> 2018 | X54: =LstMachines[[#This Row],[Delivery]] -> 43115 | Y54: =IF(MONTH(LstMachines[[#This Row],[DateLivr]])<10,"0","") & MONTH(LstMachines[[#This Row],[DateLivr]]) &"-"&YEAR(LstMachines[[#This Row],[DateLivr]]) -> 01-2018 | Z54: =LstMachines[[#This Row],[Delivery]]+Rglt_à_HCME -> 43175 | AA54: =IF(MONTH(LstMachines[[#This Row],[DatePaie]])<10,"0","") & MONTH(LstMachines[[#This Row],[DatePaie]])&"-"&YEAR(LstMachines[[#This Row],[DatePaie]]) -> 03-2018 | AB54: =LstMachines[[#This Row],[DateLivr]]+1 -> 43116 | AC54: =IF(MONTH(LstMachines[[#This Row],[Distrib]])<10,"0","") & MONTH(LstMachines[[#This Row],[Distrib]]) & "-" & YEAR(LstMachines[[#This Row],[Distrib]]) -> 01-2018 | AD54: =LstMachines[[#This Row],[DateLivr]]+Délai_Vente -> 43235 | AE54: =IF(MONTH(LstMachines[[#This Row],[VteESM]])<10,"0","") & MONTH(LstMachines[[#This Row],[VteESM]]) & "-" & YEAR(LstMachines[[#This Row],[VteESM]]) -> 05-2018 | AF54: =LstMachines[[#This Row],[DateLivr]]+Rglt_à_ESMTP -> 43175 | AG54: =IF(MONTH(LstMachines[[#This Row],[RgltDistrib]])<10,"0","") & MONTH(LstMachines[[#This Row],[RgltDistrib]]) & "-" & YEAR(LstMachines[[#This Row],[RgltDistrib]]) -> 03-2018 | AH54: =LstMachines[[#This Row],[VteESM]]+Rglt_à_ESMTP -> 43295 | AI54: =IF(MONTH(LstMachines[[#This Row],[RgltVteESM]])<10,"0","") & MONTH(LstMachines[[#This Row],[RgltVteESM]]) & "-" & YEAR(LstMachines[[#This Row],[RgltVteESM]]) -> 07-2018 | AJ54: =MONTH(LstMachines[[#This Row],[DatePaie]]) -> 3 | AK54: =FIXED(YEAR(LstMachines[[#This Row],[DatePaie]]),0,TRUE) -> 2018
B55: Mini Pelle | C55: ZX48 | D55: 48 | E55: ZX48U-5-CLR | F55: XMTP | G55: BORDEAUX | H55: 1 | I55: =IF(LstMachines[[#This Row],[Delivery]]<Début_HCME, 0, IFERROR( LstMachines[[#This Row],[Nbre]] * INDEX(TabModelSpecs[],MATCH(LstMachines[[#This Row],[Model-Spec]],TabModelSpecs[ModelSpec],0),MATCH("2018",TabModelSpecs[#Headers],0)), LstMachines[[#This Row],[Nbre]]*ROUND(AVERAGEIF(TabModelSpecs[Machine],LstMachines[[#This Row],[Model]],TabModelSpecs[Price]),0) ) ) -> 41 | J55: 43115 | K55: 5-Livrée | L55: 2017-12 XMTP | O55: =MONTH(LstMachines[[#This Row],[Delivery]]) -> 1 | P55: =FIXED(YEAR(LstMachines[[#This Row],[Delivery]]),0,TRUE) -> 2018 | X55: =LstMachines[[#This Row],[Delivery]] -> 43115 | Y55: =IF(MONTH(LstMachines[[#This Row],[DateLivr]])<10,"0","") & MONTH(LstMachines[[#This Row],[DateLivr]]) &"-"&YEAR(LstMachines[[#This Row],[DateLivr]]) -> 01-2018 | Z55: =LstMachines[[#This Row],[Delivery]]+Rglt_à_HCME -> 43175 | AA55: =IF(MONTH(LstMachines[[#This Row],[DatePaie]])<10,"0","") & MONTH(LstMachines[[#This Row],[DatePaie]])&"-"&YEAR(LstMachines[[#This Row],[DatePaie]]) -> 03-2018 | AB55: =LstMachines[[#This Row],[DateLivr]]+1 -> 43116 | AC55: =IF(MONTH(LstMachines[[#This Row],[Distrib]])<10,"0","") & MONTH(LstMachines[[#This Row],[Distrib]]) & "-" & YEAR(LstMachines[[#This Row],[Distrib]]) -> 01-2018 | AD55: =LstMachines[[#This Row],[DateLivr]]+Délai_Vente -> 43235 | AE55: =IF(MONTH(LstMachines[[#This Row],[VteESM]])<10,"0","") & MONTH(LstMachines[[#This Row],[VteESM]]) & "-" & YEAR(LstMachines[[#This Row],[VteESM]]) -> 05-2018 | AF55: =LstMachines[[#This Row],[DateLivr]]+Rglt_à_ESMTP -> 43175 | AG55: =IF(MONTH(LstMachines[[#This Row],[RgltDistrib]])<10,"0","") & MONTH(LstMachines[[#This Row],[RgltDistrib]]) & "-" & YEAR(LstMachines[[#This Row],[RgltDistrib]]) -> 03-2018 | AH55: =LstMachines[[#This Row],[VteESM]]+Rglt_à_ESMTP -> 43295 | AI55: =IF(MONTH(LstMachines[[#This Row],[RgltVteESM]])<10,"0","") & MONTH(LstMachines[[#This Row],[RgltVteESM]]) & "-" & YEAR(LstMachines[[#This Row],[RgltVteESM]]) -> 07-2018 | AJ55: =MONTH(LstMachines[[#This Row],[DatePaie]]) -> 3 | AK55: =FIXED(YEAR(LstMachines[[#This Row],[DatePaie]]),0,TRUE) -> 2018
B56: Mini Pelle | C56: ZX26 | D56: 26 | E56: ZX26U-5-YLR | F56: BTPS | G56: ORTHEZ | H56: 1 | I56: =IF(LstMachines[[#This Row],[Delivery]]<Début_HCME, 0, IFERROR( LstMachines[[#This Row],[Nbre]] * INDEX(TabModelSpecs[],MATCH(LstMachines[[#This Row],[Model-Spec]],TabModelSpecs[ModelSpec],0),MATCH("2018",TabModelSpecs[#Headers],0)), LstMachines[[#This Row],[Nbre]]*ROUND(AVERAGEIF(TabModelSpecs[Machine],LstMachines[[#This Row],[Model]],TabModelSpecs[Price]),0) ) ) -> 22 | J56: 43146 | K56: 1-Forecast | L56: 2017-11 BTPS | O56: =MONTH(LstMachines[[#This Row],[Delivery]]) -> 2 | P56: =FIXED(YEAR(LstMachines[[#This Row],[Delivery]]),0,TRUE) -> 2018 | X56: =LstMachines[[#This Row],[Delivery]] -> 43146 | Y56: =IF(MONTH(LstMachines[[#This Row],[DateLivr]])<10,"0","") & MONTH(LstMachines[[#This Row],[DateLivr]]) &"-"&YEAR(LstMachines[[#This Row],[DateLivr]]) -> 02-2018 | Z56: =LstMachines[[#This Row],[Delivery]]+Rglt_à_HCME -> 43206 | AA56: =IF(MONTH(LstMachines[[#This Row],[DatePaie]])<10,"0","") & MONTH(LstMachines[[#This Row],[DatePaie]])&"-"&YEAR(LstMachines[[#This Row],[DatePaie]]) -> 04-2018 | AB56: =LstMachines[[#This Row],[DateLivr]]+1 -> 43147 | AC56: =IF(MONTH(LstMachines[[#This Row],[Distrib]])<10,"0","") & MONTH(LstMachines[[#This Row],[Distrib]]) & "-" & YEAR(LstMachines[[#This Row],[Distrib]]) -> 02-2018 | AD56: =LstMachines[[#This Row],[DateLivr]]+Délai_Vente -> 43266 | AE56: =IF(MONTH(LstMachines[[#This Row],[VteESM]])<10,"0","") & MONTH(LstMachines[[#This Row],[VteESM]]) & "-" & YEAR(LstMachines[[#This Row],[VteESM]]) -> 06-2018 | AF56: =LstMachines[[#This Row],[DateLivr]]+Rglt_à_ESMTP -> 43206 | AG56: =IF(MONTH(LstMachines[[#This Row],[RgltDistrib]])<10,"0","") & MONTH(LstMachines[[#This Row],[RgltDistrib]]) & "-" & YEAR(LstMachines[[#This Row],[RgltDistrib]]) -> 04-2018 | AH56: =LstMachines[[#This Row],[VteESM]]+Rglt_à_ESMTP -> 43326 | AI56: =IF(MONTH(LstMachines[[#This Row],[RgltVteESM]])<10,"0","") & MONTH(LstMachines[[#This Row],[RgltVteESM]]) & "-" & YEAR(LstMachines[[#This Row],[RgltVteESM]]) -> 08-2018 | AJ56: =MONTH(LstMachines[[#This Row],[DatePaie]]) -> 4 | AK56: =FIXED(YEAR(LstMachines[[#This Row],[DatePaie]]),0,TRUE) -> 2018
B57: Mini Pelle | C57: ZX48 | D57: 48 | E57: ZX48U-5-CLRNH | F57: BTPS | G57: ORTHEZ | H57: 1 | I57: =IF(LstMachines[[#This Row],[Delivery]]<Début_HCME, 0, IFERROR( LstMachines[[#This Row],[Nbre]] * INDEX(TabModelSpecs[],MATCH(LstMachines[[#This Row],[Model-Spec]],TabModelSpecs[ModelSpec],0),MATCH("2018",TabModelSpecs[#Headers],0)), LstMachines[[#This Row],[Nbre]]*ROUND(AVERAGEIF(TabModelSpecs[Machine],LstMachines[[#This Row],[Model]],TabModelSpecs[Price]),0) ) ) -> 41 | J57: 43146 | K57: 1-Forecast | L57: 2017-11 BTPS | O57: =MONTH(LstMachines[[#This Row],[Delivery]]) -> 2 | P57: =FIXED(YEAR(LstMachines[[#This Row],[Delivery]]),0,TRUE) -> 2018 | X57: =LstMachines[[#This Row],[Delivery]] -> 43146 | Y57: =IF(MONTH(LstMachines[[#This Row],[DateLivr]])<10,"0","") & MONTH(LstMachines[[#This Row],[DateLivr]]) &"-"&YEAR(LstMachines[[#This Row],[DateLivr]]) -> 02-2018 | Z57: =LstMachines[[#This Row],[Delivery]]+Rglt_à_HCME -> 43206 | AA57: =IF(MONTH(LstMachines[[#This Row],[DatePaie]])<10,"0","") & MONTH(LstMachines[[#This Row],[DatePaie]])&"-"&YEAR(LstMachines[[#This Row],[DatePaie]]) -> 04-2018 | AB57: =LstMachines[[#This Row],[DateLivr]]+1 -> 43147 | AC57: =IF(MONTH(LstMachines[[#This Row],[Distrib]])<10,"0","") & MONTH(LstMachines[[#This Row],[Distrib]]) & "-" & YEAR(LstMachines[[#This Row],[Distrib]]) -> 02-2018 | AD57: =LstMachines[[#This Row],[DateLivr]]+Délai_Vente -> 43266 | AE57: =IF(MONTH(LstMachines[[#This Row],[VteESM]])<10,"0","") & MONTH(LstMachines[[#This Row],[VteESM]]) & "-" & YEAR(LstMachines[[#This Row],[VteESM]]) -> 06-2018 | AF57: =LstMachines[[#This Row],[DateLivr]]+Rglt_à_ESMTP -> 43206 | AG57: =IF(MONTH(LstMachines[[#This Row],[RgltDistrib]])<10,"0","") & MONTH(LstMachines[[#This Row],[RgltDistrib]]) & "-" & YEAR(LstMachines[[#This Row],[RgltDistrib]]) -> 04-2018 | AH57: =LstMachines[[#This Row],[VteESM]]+Rglt_à_ESMTP -> 43326 | AI57: =IF(MONTH(LstMachines[[#This Row],[RgltVteESM]])<10,"0","") & MONTH(LstMachines[[#This Row],[RgltVteESM]]) & "-" & YEAR(LstMachines[[#This Row],[RgltVteESM]]) -> 08-2018 | AJ57: =MONTH(LstMachines[[#This Row],[DatePaie]]) -> 4 | AK57: =FIXED(YEAR(LstMachines[[#This Row],[DatePaie]]),0,TRUE) -> 2018
B58: Mini Pelle | C58: ZX26 | D58: 26 | E58: ZX26U-5-YLR | F58: SETP | G58: RABASTENS | H58: 1 | I58: =IF(LstMachines[[#This Row],[Delivery]]<Début_HCME, 0, IFERROR( LstMachines[[#This Row],[Nbre]] * INDEX(TabModelSpecs[],MATCH(LstMachines[[#This Row],[Model-Spec]],TabModelSpecs[ModelSpec],0),MATCH("2018",TabModelSpecs[#Headers],0)), LstMachines[[#This Row],[Nbre]]*ROUND(AVERAGEIF(TabModelSpecs[Machine],LstMachines[[#This Row],[Model]],TabModelSpecs[Price]),0) ) ) -> 22 | J58: 43146 | K58: 3-Commande | L58: 2017-12-06 ADV | N58: 42944 | O58: =MONTH(LstMachines[[#This Row],[Delivery]]) -> 2 | P58: =FIXED(YEAR(LstMachines[[#This Row],[Delivery]]),0,TRUE) -> 2018 | Q58: 17070049 | R58: 20350 | U58: STOCK | V58: 4175 | W58: _Stock | X58: =LstMachines[[#This Row],[Delivery]] -> 43146 | Y58: =IF(MONTH(LstMachines[[#This Row],[DateLivr]])<10,"0","") & MONTH(LstMachines[[#This Row],[DateLivr]]) &"-"&YEAR(LstMachines[[#This Row],[DateLivr]]) -> 02-2018 | Z58: =LstMachines[[#This Row],[Delivery]]+Rglt_à_HCME -> 43206 | AA58: =IF(MONTH(LstMachines[[#This Row],[DatePaie]])<10,"0","") & MONTH(LstMachines[[#This Row],[DatePaie]])&"-"&YEAR(LstMachines[[#This Row],[DatePaie]]) -> 04-2018 | AB58: =LstMachines[[#This Row],[DateLivr]]+1 -> 43147 | AC58: =IF(MONTH(LstMachines[[#This Row],[Distrib]])<10,"0","") & MONTH(LstMachines[[#This Row],[Distrib]]) & "-" & YEAR(LstMachines[[#This Row],[Distrib]]) -> 02-2018 | AD58: =LstMachines[[#This Row],[DateLivr]]+Délai_Vente -> 43266 | AE58: =IF(MONTH(LstMachines[[#This Row],[VteESM]])<10,"0","") & MONTH(LstMachines[[#This Row],[VteESM]]) & "-" & YEAR(LstMachines[[#This Row],[VteESM]]) -> 06-2018 | AF58: =LstMachines[[#This Row],[DateLivr]]+Rglt_à_ESMTP -> 43206 | AG58: =IF(MONTH(LstMachines[[#This Row],[RgltDistrib]])<10,"0","") & MONTH(LstMachines[[#This Row],[RgltDistrib]]) & "-" & YEAR(LstMachines[[#This Row],[RgltDistrib]]) -> 04-2018 | AH58: =LstMachines[[#This Row],[VteESM]]+Rglt_à_ESMTP -> 43326 | AI58: =IF(MONTH(LstMachines[[#This Row],[RgltVteESM]])<10,"0","") & MONTH(LstMachines[[#This Row],[RgltVteESM]]) & "-" & YEAR(LstMachines[[#This Row],[RgltVteESM]]) -> 08-2018 | AJ58: =MONTH(LstMachines[[#This Row],[DatePaie]]) -> 4 | AK58: =FIXED(YEAR(LstMachines[[#This Row],[DatePaie]]),0,TRUE) -> 2018
B59: Mini Pelle | C59: ZX26 | D59: 26 | E59: ZX26U-5-YLR | F59: SETP | G59: RABASTENS | H59: 1 | I59: =IF(LstMachines[[#This Row],[Delivery]]<Début_HCME, 0, IFERROR( LstMachines[[#This Row],[Nbre]] * INDEX(TabModelSpecs[],MATCH(LstMachines[[#This Row],[Model-Spec]],TabModelSpecs[ModelSpec],0),MATCH("2018",TabModelSpecs[#Headers],0)), LstMachines[[#This Row],[Nbre]]*ROUND(AVERAGEIF(TabModelSpecs[Machine],LstMachines[[#This Row],[Model]],TabModelSpecs[Price]),0) ) ) -> 22 | J59: 43146 | K59: 3-Commande | L59: 2017-12-06 ADV | N59: 42944 | O59: =MONTH(LstMachines[[#This Row],[Delivery]]) -> 2 | P59: =FIXED(YEAR(LstMachines[[#This Row],[Delivery]]),0,TRUE) -> 2018 | Q59: 17070050 | R59: 20350 | U59: STOCK | V59: 4176 | W59: LOC PLUS | X59: =LstMachines[[#This Row],[Delivery]] -> 43146 | Y59: =IF(MONTH(LstMachines[[#This Row],[DateLivr]])<10,"0","") & MONTH(LstMachines[[#This Row],[DateLivr]]) &"-"&YEAR(LstMachines[[#This Row],[DateLivr]]) -> 02-2018 | Z59: =LstMachines[[#This Row],[Delivery]]+Rglt_à_HCME -> 43206 | AA59: =IF(MONTH(LstMachines[[#This Row],[DatePaie]])<10,"0","") & MONTH(LstMachines[[#This Row],[DatePaie]])&"-"&YEAR(LstMachines[[#This Row],[DatePaie]]) -> 04-2018 | AB59: =LstMachines[[#This Row],[DateLivr]]+1 -> 43147 | AC59: =IF(MONTH(LstMachines[[#This Row],[Distrib]])<10,"0","") & MONTH(LstMachines[[#This Row],[Distrib]]) & "-" & YEAR(LstMachines[[#This Row],[Distrib]]) -> 02-2018 | AD59: =LstMachines[[#This Row],[DateLivr]]+Délai_Vente -> 43266 | AE59: =IF(MONTH(LstMachines[[#This Row],[VteESM]])<10,"0","") & MONTH(LstMachines[[#This Row],[VteESM]]) & "-" & YEAR(LstMachines[[#This Row],[VteESM]]) -> 06-2018 | AF59: =LstMachines[[#This Row],[DateLivr]]+Rglt_à_ESMTP -> 43206 | AG59: =IF(MONTH(LstMachines[[#This Row],[RgltDistrib]])<10,"0","") & MONTH(LstMachines[[#This Row],[RgltDistrib]]) & "-" & YEAR(LstMachines[[#This Row],[RgltDistrib]]) -> 04-2018 | AH59: =LstMachines[[#This Row],[VteESM]]+Rglt_à_ESMTP -> 43326 | AI59: =IF(MONTH(LstMachines[[#This Row],[RgltVteESM]])<10,"0","") & MONTH(LstMachines[[#This Row],[RgltVteESM]]) & "-" & YEAR(LstMachines[[#This Row],[RgltVteESM]]) -> 08-2018 | AJ59: =MONTH(LstMachines[[#This Row],[DatePaie]]) -> 4 | AK59: =FIXED(YEAR(LstMachines[[#This Row],[DatePaie]]),0,TRUE) -> 2018
B60: Mini Pelle | C60: ZX26 | D60: 26 | E60: ZX26U-5-YLR | F60: SETP | G60: RABASTENS | H60: 1 | I60: =IF(LstMachines[[#This Row],[Delivery]]<Début_HCME, 0, IFERROR( LstMachines[[#This Row],[Nbre]] * INDEX(TabModelSpecs[],MATCH(LstMachines[[#This Row],[Model-Spec]],TabModelSpecs[ModelSpec],0),MATCH("2018",TabModelSpecs[#Headers],0)), LstMachines[[#This Row],[Nbre]]*ROUND(AVERAGEIF(TabModelSpecs[Machine],LstMachines[[#This Row],[Model]],TabModelSpecs[Price]),0) ) ) -> 22 | J60: 43146 | K60: 3-Commande | L60: 2017-12-06 ADV | N60: 42944 | O60: =MONTH(LstMachines[[#This Row],[Delivery]]) -> 2 | P60: =FIXED(YEAR(LstMachines[[#This Row],[Delivery]]),0,TRUE) -> 2018 | Q60: 17070051 | R60: 20350 | U60: STOCK | V60: 4177 | W60: LOC PLUS | X60: =LstMachines[[#This Row],[Delivery]] -> 43146 | Y60: =IF(MONTH(LstMachines[[#This Row],[DateLivr]])<10,"0","") & MONTH(LstMachines[[#This Row],[DateLivr]]) &"-"&YEAR(LstMachines[[#This Row],[DateLivr]]) -> 02-2018 | Z60: =LstMachines[[#This Row],[Delivery]]+Rglt_à_HCME -> 43206 | AA60: =IF(MONTH(LstMachines[[#This Row],[DatePaie]])<10,"0","") & MONTH(LstMachines[[#This Row],[DatePaie]])&"-"&YEAR(LstMachines[[#This Row],[DatePaie]]) -> 04-2018 | AB60: =LstMachines[[#This Row],[DateLivr]]+1 -> 43147 | AC60: =IF(MONTH(LstMachines[[#This Row],[Distrib]])<10,"0","") & MONTH(LstMachines[[#This Row],[Distrib]]) & "-" & YEAR(LstMachines[[#This Row],[Distrib]]) -> 02-2018 | AD60: =LstMachines[[#This Row],[DateLivr]]+Délai_Vente -> 43266 | AE60: =IF(MONTH(LstMachines[[#This Row],[VteESM]])<10,"0","") & MONTH(LstMachines[[#This Row],[VteESM]]) & "-" & YEAR(LstMachines[[#This Row],[VteESM]]) -> 06-2018 | AF60: =LstMachines[[#This Row],[DateLivr]]+Rglt_à_ESMTP -> 43206 | AG60: =IF(MONTH(LstMachines[[#This Row],[RgltDistrib]])<10,"0","") & MONTH(LstMachines[[#This Row],[RgltDistrib]]) & "-" & YEAR(LstMachines[[#This Row],[RgltDistrib]]) -> 04-2018 | AH60: =LstMachines[[#This Row],[VteESM]]+Rglt_à_ESMTP -> 43326 | AI60: =IF(MONTH(LstMachines[[#This Row],[RgltVteESM]])<10,"0","") & MONTH(LstMachines[[#This Row],[RgltVteESM]]) & "-" & YEAR(LstMachines[[#This Row],[RgltVteESM]]) -> 08-2018 | AJ60: =MONTH(LstMachines[[#This Row],[DatePaie]]) -> 4 | AK60: =FIXED(YEAR(LstMachines[[#This Row],[DatePaie]]),0,TRUE) -> 2018
B61: Mini Pelle | C61: ZX26 | D61: 26 | E61: ZX26U-5-YLR | F61: SETP | G61: RABASTENS | H61: 1 | I61: =IF(LstMachines[[#This Row],[Delivery]]<Début_HCME, 0, IFERROR( LstMachines[[#This Row],[Nbre]] * INDEX(TabModelSpecs[],MATCH(LstMachines[[#This Row],[Model-Spec]],TabModelSpecs[ModelSpec],0),MATCH("2018",TabModelSpecs[#Headers],0)), LstMachines[[#This Row],[Nbre]]*ROUND(AVERAGEIF(TabModelSpecs[Machine],LstMachines[[#This Row],[Model]],TabModelSpecs[Price]),0) ) ) -> 22 | J61: 43146 | K61: 3-Commande | L61: 2017-12-06 ADV | N61: 42944 | O61: =MONTH(LstMachines[[#This Row],[Delivery]]) -> 2 | P61: =FIXED(YEAR(LstMachines[[#This Row],[Delivery]]),0,TRUE) -> 2018 | Q61: 17070005 | R61: 20350 | U61: VENTE | V61: 4167 | W61: STOCKBAT | X61: =LstMachines[[#This Row],[Delivery]] -> 43146 | Y61: =IF(MONTH(LstMachines[[#This Row],[DateLivr]])<10,"0","") & MONTH(LstMachines[[#This Row],[DateLivr]]) &"-"&YEAR(LstMachines[[#This Row],[DateLivr]]) -> 02-2018 | Z61: =LstMachines[[#This Row],[Delivery]]+Rglt_à_HCME -> 43206 | AA61: =IF(MONTH(LstMachines[[#This Row],[DatePaie]])<10,"0","") & MONTH(LstMachines[[#This Row],[DatePaie]])&"-"&YEAR(LstMachines[[#This Row],[DatePaie]]) -> 04-2018 | AB61: =LstMachines[[#This Row],[DateLivr]]+1 -> 43147 | AC61: =IF(MONTH(LstMachines[[#This Row],[Distrib]])<10,"0","") & MONTH(LstMachines[[#This Row],[Distrib]]) & "-" & YEAR(LstMachines[[#This Row],[Distrib]]) -> 02-2018 | AD61: =LstMachines[[#This Row],[DateLivr]]+Délai_Vente -> 43266 | AE61: =IF(MONTH(LstMachines[[#This Row],[VteESM]])<10,"0","") & MONTH(LstMachines[[#This Row],[VteESM]]) & "-" & YEAR(LstMachines[[#This Row],[VteESM]]) -> 06-2018 | AF61: =LstMachines[[#This Row],[DateLivr]]+Rglt_à_ESMTP -> 43206 | AG61: =IF(MONTH(LstMachines[[#This Row],[RgltDistrib]])<10,"0","") & MONTH(LstMachines[[#This Row],[RgltDistrib]]) & "-" & YEAR(LstMachines[[#This Row],[RgltDistrib]]) -> 04-2018 | AH61: =LstMachines[[#This Row],[VteESM]]+Rglt_à_ESMTP -> 43326 | AI61: =IF(MONTH(LstMachines[[#This Row],[RgltVteESM]])<10,"0","") & MONTH(LstMachines[[#This Row],[RgltVteESM]]) & "-" & YEAR(LstMachines[[#This Row],[RgltVteESM]]) -> 08-2018 | AJ61: =MONTH(LstMachines[[#This Row],[DatePaie]]) -> 4 | AK61: =FIXED(YEAR(LstMachines[[#This Row],[DatePaie]]),0,TRUE) -> 2018
B62: Mini Pelle | C62: ZX26 | D62: 26 | E62: ZX26U-5-YLR | F62: SETP | G62: RABASTENS | H62: 1 | I62: =IF(LstMachines[[#This Row],[Delivery]]<Début_HCME, 0, IFERROR( LstMachines[[#This Row],[Nbre]] * INDEX(TabModelSpecs[],MATCH(LstMachines[[#This Row],[Model-Spec]],TabModelSpecs[ModelSpec],0),MATCH("2018",TabModelSpecs[#Headers],0)), LstMachines[[#This Row],[Nbre]]*ROUND(AVERAGEIF(TabModelSpecs[Machine],LstMachines[[#This Row],[Model]],TabModelSpecs[Price]),0) ) ) -> 22 | J62: 43146 | K62: 3-Commande | L62: 2017-12-06 ADV | N62: 42944 | O62: =MONTH(LstMachines[[#This Row],[Delivery]]) -> 2 | P62: =FIXED(YEAR(LstMachines[[#This Row],[Delivery]]),0,TRUE) -> 2018 | Q62: 17070004 | R62: 20350 | U62: VENTE | V62: 4166 | W62: _Location | X62: =LstMachines[[#This Row],[Delivery]] -> 43146 | Y62: =IF(MONTH(LstMachines[[#This Row],[DateLivr]])<10,"0","") & MONTH(LstMachines[[#This Row],[DateLivr]]) &"-"&YEAR(LstMachines[[#This Row],[DateLivr]]) -> 02-2018 | Z62: =LstMachines[[#This Row],[Delivery]]+Rglt_à_HCME -> 43206 | AA62: =IF(MONTH(LstMachines[[#This Row],[DatePaie]])<10,"0","") & MONTH(LstMachines[[#This Row],[DatePaie]])&"-"&YEAR(LstMachines[[#This Row],[DatePaie]]) -> 04-2018 | AB62: =LstMachines[[#This Row],[DateLivr]]+1 -> 43147 | AC62: =IF(MONTH(LstMachines[[#This Row],[Distrib]])<10,"0","") & MONTH(LstMachines[[#This Row],[Distrib]]) & "-" & YEAR(LstMachines[[#This Row],[Distrib]]) -> 02-2018 | AD62: =LstMachines[[#This Row],[DateLivr]]+Délai_Vente -> 43266 | AE62: =IF(MONTH(LstMachines[[#This Row],[VteESM]])<10,"0","") & MONTH(LstMachines[[#This Row],[VteESM]]) & "-" & YEAR(LstMachines[[#This Row],[VteESM]]) -> 06-2018 | AF62: =LstMachines[[#This Row],[DateLivr]]+Rglt_à_ESMTP -> 43206 | AG62: =IF(MONTH(LstMachines[[#This Row],[RgltDistrib]])<10,"0","") & MONTH(LstMachines[[#This Row],[RgltDistrib]]) & "-" & YEAR(LstMachines[[#This Row],[RgltDistrib]]) -> 04-2018 | AH62: =LstMachines[[#This Row],[VteESM]]+Rglt_à_ESMTP -> 43326 | AI62: =IF(MONTH(LstMachines[[#This Row],[RgltVteESM]])<10,"0","") & MONTH(LstMachines[[#This Row],[RgltVteESM]]) & "-" & YEAR(LstMachines[[#This Row],[RgltVteESM]]) -> 08-2018 | AJ62: =MONTH(LstMachines[[#This Row],[DatePaie]]) -> 4 | AK62: =FIXED(YEAR(LstMachines[[#This Row],[DatePaie]]),0,TRUE) -> 2018
B63: Mini Pelle | C63: ZX33 | D63: 33 | E63: ZX33U-5-CLR | F63: SETP | G63: RABASTENS | H63: 1 | I63: =IF(LstMachines[[#This Row],[Delivery]]<Début_HCME, 0, IFERROR( LstMachines[[#This Row],[Nbre]] * INDEX(TabModelSpecs[],MATCH(LstMachines[[#This Row],[Model-Spec]],TabModelSpecs[ModelSpec],0),MATCH("2018",TabModelSpecs[#Headers],0)), LstMachines[[#This Row],[Nbre]]*ROUND(AVERAGEIF(TabModelSpecs[Machine],LstMachines[[#This Row],[Model]],TabModelSpecs[Price]),0) ) ) -> 32 | J63: 43146 | K63: 3-Commande | L63: 2017-12-06 ADV | N63: 43036 | O63: =MONTH(LstMachines[[#This Row],[Delivery]]) -> 2 | P63: =FIXED(YEAR(LstMachines[[#This Row],[Delivery]]),0,TRUE) -> 2018 | Q63: 17100089 | R63: 32431 | U63: STOCK | V63: 4237 | W63: _Stock | X63: =LstMachines[[#This Row],[Delivery]] -> 43146 | Y63: =IF(MONTH(LstMachines[[#This Row],[DateLivr]])<10,"0","") & MONTH(LstMachines[[#This Row],[DateLivr]]) &"-"&YEAR(LstMachines[[#This Row],[DateLivr]]) -> 02-2018 | Z63: =LstMachines[[#This Row],[Delivery]]+Rglt_à_HCME -> 43206 | AA63: =IF(MONTH(LstMachines[[#This Row],[DatePaie]])<10,"0","") & MONTH(LstMachines[[#This Row],[DatePaie]])&"-"&YEAR(LstMachines[[#This Row],[DatePaie]]) -> 04-2018 | AB63: =LstMachines[[#This Row],[DateLivr]]+1 -> 43147 | AC63: =IF(MONTH(LstMachines[[#This Row],[Distrib]])<10,"0","") & MONTH(LstMachines[[#This Row],[Distrib]]) & "-" & YEAR(LstMachines[[#This Row],[Distrib]]) -> 02-2018 | AD63: =LstMachines[[#This Row],[DateLivr]]+Délai_Vente -> 43266 | AE63: =IF(MONTH(LstMachines[[#This Row],[VteESM]])<10,"0","") & MONTH(LstMachines[[#This Row],[VteESM]]) & "-" & YEAR(LstMachines[[#This Row],[VteESM]]) -> 06-2018 | AF63: =LstMachines[[#This Row],[DateLivr]]+Rglt_à_ESMTP -> 43206 | AG63: =IF(MONTH(LstMachines[[#This Row],[RgltDistrib]])<10,"0","") & MONTH(LstMachines[[#This Row],[RgltDistrib]]) & "-" & YEAR(LstMachines[[#This Row],[RgltDistrib]]) -> 04-2018 | AH63: =LstMachines[[#This Row],[VteESM]]+Rglt_à_ESMTP -> 43326 | AI63: =IF(MONTH(LstMachines[[#This Row],[RgltVteESM]])<10,"0","") & MONTH(LstMachines[[#This Row],[RgltVteESM]]) & "-" & YEAR(LstMachines[[#This Row],[RgltVteESM]]) -> 08-2018 | AJ63: =MONTH(LstMachines[[#This Row],[DatePaie]]) -> 4 | AK63: =FIXED(YEAR(LstMachines[[#This Row],[DatePaie]]),0,TRUE) -> 2018
B64: Mini Pelle | C64: ZX65 | D64: 65 | E64: ZX65USB-5-CLR | F64: SETP | G64: RABASTENS | H64: 1 | I64: =IF(LstMachines[[#This Row],[Delivery]]<Début_HCME, 0, IFERROR( LstMachines[[#This Row],[Nbre]] * INDEX(TabModelSpecs[],MATCH(LstMachines[[#This Row],[Model-Spec]],TabModelSpecs[ModelSpec],0),MATCH("2018",TabModelSpecs[#Headers],0)), LstMachines[[#This Row],[Nbre]]*ROUND(AVERAGEIF(TabModelSpecs[Machine],LstMachines[[#This Row],[Model]],TabModelSpecs[Price]),0) ) ) -> 45 | J64: 43146 | K64: 3-Commande | L64: 2017-12-06 ADV | N64: 43036 | O64: =MONTH(LstMachines[[#This Row],[Delivery]]) -> 2 | P64: =FIXED(YEAR(LstMachines[[#This Row],[Delivery]]),0,TRUE) -> 2018 | Q64: 17100092 | R64: 48776 | U64: STOCK | V64: 4240 | W64: _Stock | X64: =LstMachines[[#This Row],[Delivery]] -> 43146 | Y64: =IF(MONTH(LstMachines[[#This Row],[DateLivr]])<10,"0","") & MONTH(LstMachines[[#This Row],[DateLivr]]) &"-"&YEAR(LstMachines[[#This Row],[DateLivr]]) -> 02-2018 | Z64: =LstMachines[[#This Row],[Delivery]]+Rglt_à_HCME -> 43206 | AA64: =IF(MONTH(LstMachines[[#This Row],[DatePaie]])<10,"0","") & MONTH(LstMachines[[#This Row],[DatePaie]])&"-"&YEAR(LstMachines[[#This Row],[DatePaie]]) -> 04-2018 | AB64: =LstMachines[[#This Row],[DateLivr]]+1 -> 43147 | AC64: =IF(MONTH(LstMachines[[#This Row],[Distrib]])<10,"0","") & MONTH(LstMachines[[#This Row],[Distrib]]) & "-" & YEAR(LstMachines[[#This Row],[Distrib]]) -> 02-2018 | AD64: =LstMachines[[#This Row],[DateLivr]]+Délai_Vente -> 43266 | AE64: =IF(MONTH(LstMachines[[#This Row],[VteESM]])<10,"0","") & MONTH(LstMachines[[#This Row],[VteESM]]) & "-" & YEAR(LstMachines[[#This Row],[VteESM]]) -> 06-2018 | AF64: =LstMachines[[#This Row],[DateLivr]]+Rglt_à_ESMTP -> 43206 | AG64: =IF(MONTH(LstMachines[[#This Row],[RgltDistrib]])<10,"0","") & MONTH(LstMachines[[#This Row],[RgltDistrib]]) & "-" & YEAR(LstMachines[[#This Row],[RgltDistrib]]) -> 04-2018 | AH64: =LstMachines[[#This Row],[VteESM]]+Rglt_à_ESMTP -> 43326 | AI64: =IF(MONTH(LstMachines[[#This Row],[RgltVteESM]])<10,"0","") & MONTH(LstMachines[[#This Row],[RgltVteESM]]) & "-" & YEAR(LstMachines[[#This Row],[RgltVteESM]]) -> 08-2018 | AJ64: =MONTH(LstMachines[[#This Row],[DatePaie]]) -> 4 | AK64: =FIXED(YEAR(LstMachines[[#This Row],[DatePaie]]),0,TRUE) -> 2018
B65: Mini Pelle | C65: ZX65 | D65: 65 | E65: ZX65USB-5-CLR | F65: SETP | G65: RABASTENS | H65: 1 | I65: =IF(LstMachines[[#This Row],[Delivery]]<Début_HCME, 0, IFERROR( LstMachines[[#This Row],[Nbre]] * INDEX(TabModelSpecs[],MATCH(LstMachines[[#This Row],[Model-Spec]],TabModelSpecs[ModelSpec],0),MATCH("2018",TabModelSpecs[#Headers],0)), LstMachines[[#This Row],[Nbre]]*ROUND(AVERAGEIF(TabModelSpecs[Machine],LstMachines[[#This Row],[Model]],TabModelSpecs[Price]),0) ) ) -> 45 | J65: 43146 | K65: 3-Commande | L65: 2017-12-06 ADV | N65: 43036 | O65: =MONTH(LstMachines[[#This Row],[Delivery]]) -> 2 | P65: =FIXED(YEAR(LstMachines[[#This Row],[Delivery]]),0,TRUE) -> 2018 | Q65: 17100093 | R65: 48776 | U65: STOCK | V65: 4241 | W65: _Location | X65: =LstMachines[[#This Row],[Delivery]] -> 43146 | Y65: =IF(MONTH(LstMachines[[#This Row],[DateLivr]])<10,"0","") & MONTH(LstMachines[[#This Row],[DateLivr]]) &"-"&YEAR(LstMachines[[#This Row],[DateLivr]]) -> 02-2018 | Z65: =LstMachines[[#This Row],[Delivery]]+Rglt_à_HCME -> 43206 | AA65: =IF(MONTH(LstMachines[[#This Row],[DatePaie]])<10,"0","") & MONTH(LstMachines[[#This Row],[DatePaie]])&"-"&YEAR(LstMachines[[#This Row],[DatePaie]]) -> 04-2018 | AB65: =LstMachines[[#This Row],[DateLivr]]+1 -> 43147 | AC65: =IF(MONTH(LstMachines[[#This Row],[Distrib]])<10,"0","") & MONTH(LstMachines[[#This Row],[Distrib]]) & "-" & YEAR(LstMachines[[#This Row],[Distrib]]) -> 02-2018 | AD65: =LstMachines[[#This Row],[DateLivr]]+Délai_Vente -> 43266 | AE65: =IF(MONTH(LstMachines[[#This Row],[VteESM]])<10,"0","") & MONTH(LstMachines[[#This Row],[VteESM]]) & "-" & YEAR(LstMachines[[#This Row],[VteESM]]) -> 06-2018 | AF65: =LstMachines[[#This Row],[DateLivr]]+Rglt_à_ESMTP -> 43206 | AG65: =IF(MONTH(LstMachines[[#This Row],[RgltDistrib]])<10,"0","") & MONTH(LstMachines[[#This Row],[RgltDistrib]]) & "-" & YEAR(LstMachines[[#This Row],[RgltDistrib]]) -> 04-2018 | AH65: =LstMachines[[#This Row],[VteESM]]+Rglt_à_ESMTP -> 43326 | AI65: =IF(MONTH(LstMachines[[#This Row],[RgltVteESM]])<10,"0","") & MONTH(LstMachines[[#This Row],[RgltVteESM]]) & "-" & YEAR(LstMachines[[#This Row],[RgltVteESM]]) -> 08-2018 | AJ65: =MONTH(LstMachines[[#This Row],[DatePaie]]) -> 4 | AK65: =FIXED(YEAR(LstMachines[[#This Row],[DatePaie]]),0,TRUE) -> 2018
B66: Chargeuse | C66: ZW75 | D66: 75 | E66: ZW75-6-TPD | F66: SETP | G66: RABASTENS | H66: 1 | I66: =IF(LstMachines[[#This Row],[Delivery]]<Début_HCME, 0, IFERROR( LstMachines[[#This Row],[Nbre]] * INDEX(TabModelSpecs[],MATCH(LstMachines[[#This Row],[Model-Spec]],TabModelSpecs[ModelSpec],0),MATCH("2018",TabModelSpecs[#Headers],0)), LstMachines[[#This Row],[Nbre]]*ROUND(AVERAGEIF(TabModelSpecs[Machine],LstMachines[[#This Row],[Model]],TabModelSpecs[Price]),0) ) ) -> 45 | J66: 43146 | K66: 3-Commande | L66: 2017-12-06 ADV | N66: 43067 | O66: =MONTH(LstMachines[[#This Row],[Delivery]]) -> 2 | P66: =FIXED(YEAR(LstMachines[[#This Row],[Delivery]]),0,TRUE) -> 2018 | Q66: 17110005 | R66: 38070 | U66: STOCK | V66: 4245 | W66: _Stock | X66: =LstMachines[[#This Row],[Delivery]] -> 43146 | Y66: =IF(MONTH(LstMachines[[#This Row],[DateLivr]])<10,"0","") & MONTH(LstMachines[[#This Row],[DateLivr]]) &"-"&YEAR(LstMachines[[#This Row],[DateLivr]]) -> 02-2018 | Z66: =LstMachines[[#This Row],[Delivery]]+Rglt_à_HCME -> 43206 | AA66: =IF(MONTH(LstMachines[[#This Row],[DatePaie]])<10,"0","") & MONTH(LstMachines[[#This Row],[DatePaie]])&"-"&YEAR(LstMachines[[#This Row],[DatePaie]]) -> 04-2018 | AB66: =LstMachines[[#This Row],[DateLivr]]+1 -> 43147 | AC66: =IF(MONTH(LstMachines[[#This Row],[Distrib]])<10,"0","") & MONTH(LstMachines[[#This Row],[Distrib]]) & "-" & YEAR(LstMachines[[#This Row],[Distrib]]) -> 02-2018 | AD66: =LstMachines[[#This Row],[DateLivr]]+Délai_Vente -> 43266 | AE66: =IF(MONTH(LstMachines[[#This Row],[VteESM]])<10,"0","") & MONTH(LstMachines[[#This Row],[VteESM]]) & "-" & YEAR(LstMachines[[#This Row],[VteESM]]) -> 06-2018 | AF66: =LstMachines[[#This Row],[DateLivr]]+Rglt_à_ESMTP -> 43206 | AG66: =IF(MONTH(LstMachines[[#This Row],[RgltDistrib]])<10,"0","") & MONTH(LstMachines[[#This Row],[RgltDistrib]]) & "-" & YEAR(LstMachines[[#This Row],[RgltDistrib]]) -> 04-2018 | AH66: =LstMachines[[#This Row],[VteESM]]+Rglt_à_ESMTP -> 43326 | AI66: =IF(MONTH(LstMachines[[#This Row],[RgltVteESM]])<10,"0","") & MONTH(LstMachines[[#This Row],[RgltVteESM]]) & "-" & YEAR(LstMachines[[#This Row],[RgltVteESM]]) -> 08-2018 | AJ66: =MONTH(LstMachines[[#This Row],[DatePaie]]) -> 4 | AK66: =FIXED(YEAR(LstMachines[[#This Row],[DatePaie]]),0,TRUE) -> 2018
B67: Pelle/Chenilles | C67: ZX210 | D67: 210 | E67: ZX210LC-6-MN | F67: SETP | G67: RABASTENS | H67: 1 | I67: =IF(LstMachines[[#This Row],[Delivery]]<Début_HCME, 0, IFERROR( LstMachines[[#This Row],[Nbre]] * INDEX(TabModelSpecs[],MATCH(LstMachines[[#This Row],[Model-Spec]],TabModelSpecs[ModelSpec],0),MATCH("2018",TabModelSpecs[#Headers],0)), LstMachines[[#This Row],[Nbre]]*ROUND(AVERAGEIF(TabModelSpecs[Machine],LstMachines[[#This Row],[Model]],TabModelSpecs[Price]),0) ) ) -> 118 | J67: 43146 | K67: 3-Commande | L67: 2017-12-06 ADV | N67: 43036 | O67: =MONTH(LstMachines[[#This Row],[Delivery]]) -> 2 | P67: =FIXED(YEAR(LstMachines[[#This Row],[Delivery]]),0,TRUE) -> 2018 | Q67: 17100063 | R67: 112553 | U67: STOCK | V67: 4230 | W67: _Stock | X67: =LstMachines[[#This Row],[Delivery]] -> 43146 | Y67: =IF(MONTH(LstMachines[[#This Row],[DateLivr]])<10,"0","") & MONTH(LstMachines[[#This Row],[DateLivr]]) &"-"&YEAR(LstMachines[[#This Row],[DateLivr]]) -> 02-2018 | Z67: =LstMachines[[#This Row],[Delivery]]+Rglt_à_HCME -> 43206 | AA67: =IF(MONTH(LstMachines[[#This Row],[DatePaie]])<10,"0","") & MONTH(LstMachines[[#This Row],[DatePaie]])&"-"&YEAR(LstMachines[[#This Row],[DatePaie]]) -> 04-2018 | AB67: =LstMachines[[#This Row],[DateLivr]]+1 -> 43147 | AC67: =IF(MONTH(LstMachines[[#This Row],[Distrib]])<10,"0","") & MONTH(LstMachines[[#This Row],[Distrib]]) & "-" & YEAR(LstMachines[[#This Row],[Distrib]]) -> 02-2018 | AD67: =LstMachines[[#This Row],[DateLivr]]+Délai_Vente -> 43266 | AE67: =IF(MONTH(LstMachines[[#This Row],[VteESM]])<10,"0","") & MONTH(LstMachines[[#This Row],[VteESM]]) & "-" & YEAR(LstMachines[[#This Row],[VteESM]]) -> 06-2018 | AF67: =LstMachines[[#This Row],[DateLivr]]+Rglt_à_ESMTP -> 43206 | AG67: =IF(MONTH(LstMachines[[#This Row],[RgltDistrib]])<10,"0","") & MONTH(LstMachines[[#This Row],[RgltDistrib]]) & "-" & YEAR(LstMachines[[#This Row],[RgltDistrib]]) -> 04-2018 | AH67: =LstMachines[[#This Row],[VteESM]]+Rglt_à_ESMTP -> 43326 | AI67: =IF(MONTH(LstMachines[[#This Row],[RgltVteESM]])<10,"0","") & MONTH(LstMachines[[#This Row],[RgltVteESM]]) & "-" & YEAR(LstMachines[[#This Row],[RgltVteESM]]) -> 08-2018 | AJ67: =MONTH(LstMachines[[#This Row],[DatePaie]]) -> 4 | AK67: =FIXED(YEAR(LstMachines[[#This Row],[DatePaie]]),0,TRUE) -> 2018
B68: Pelle/Chenilles | C68: ZX225 | D68: 225 | E68: ZX225USLC-6-2P-BL | F68: SETP | G68: LÉZIGNAN | H68: 1 | I68: =IF(LstMachines[[#This Row],[Delivery]]<Début_HCME, 0, IFERROR( LstMachines[[#This Row],[Nbre]] * INDEX(TabModelSpecs[],MATCH(LstMachines[[#This Row],[Model-Spec]],TabModelSpecs[ModelSpec],0),MATCH("2018",TabModelSpecs[#Headers],0)), LstMachines[[#This Row],[Nbre]]*ROUND(AVERAGEIF(TabModelSpecs[Machine],LstMachines[[#This Row],[Model]],TabModelSpecs[Price]),0) ) ) -> 128 | J68: 43146 | K68: 3-Commande | L68: 2017-12-06 ADV | N68: 42944 | O68: =MONTH(LstMachines[[#This Row],[Delivery]]) -> 2 | P68: =FIXED(YEAR(LstMachines[[#This Row],[Delivery]]),0,TRUE) -> 2018 | Q68: 17070001 | R68: 141543 | U68: VENTE | V68: 4168 | W68: SOL FRERES | X68: =LstMachines[[#This Row],[Delivery]] -> 43146 | Y68: =IF(MONTH(LstMachines[[#This Row],[DateLivr]])<10,"0","") & MONTH(LstMachines[[#This Row],[DateLivr]]) &"-"&YEAR(LstMachines[[#This Row],[DateLivr]]) -> 02-2018 | Z68: =LstMachines[[#This Row],[Delivery]]+Rglt_à_HCME -> 43206 | AA68: =IF(MONTH(LstMachines[[#This Row],[DatePaie]])<10,"0","") & MONTH(LstMachines[[#This Row],[DatePaie]])&"-"&YEAR(LstMachines[[#This Row],[DatePaie]]) -> 04-2018 | AB68: =LstMachines[[#This Row],[DateLivr]]+1 -> 43147 | AC68: =IF(MONTH(LstMachines[[#This Row],[Distrib]])<10,"0","") & MONTH(LstMachines[[#This Row],[Distrib]]) & "-" & YEAR(LstMachines[[#This Row],[Distrib]]) -> 02-2018 | AD68: =LstMachines[[#This Row],[DateLivr]]+Délai_Vente -> 43266 | AE68: =IF(MONTH(LstMachines[[#This Row],[VteESM]])<10,"0","") & MONTH(LstMachines[[#This Row],[VteESM]]) & "-" & YEAR(LstMachines[[#This Row],[VteESM]]) -> 06-2018 | AF68: =LstMachines[[#This Row],[DateLivr]]+Rglt_à_ESMTP -> 43206 | AG68: =IF(MONTH(LstMachines[[#This Row],[RgltDistrib]])<10,"0","") & MONTH(LstMachines[[#This Row],[RgltDistrib]]) & "-" & YEAR(LstMachines[[#This Row],[RgltDistrib]]) -> 04-2018 | AH68: =LstMachines[[#This Row],[VteESM]]+Rglt_à_ESMTP -> 43326 | AI68: =IF(MONTH(LstMachines[[#This Row],[RgltVteESM]])<10,"0","") & MONTH(LstMachines[[#This Row],[RgltVteESM]]) & "-" & YEAR(LstMachines[[#This Row],[RgltVteESM]]) -> 08-2018 | AJ68: =MONTH(LstMachines[[#This Row],[DatePaie]]) -> 4 | AK68: =FIXED(YEAR(LstMachines[[#This Row],[DatePaie]]),0,TRUE) -> 2018
B69: Pelle/Chenilles | C69: ZX210 | D69: 210 | E69: ZX210LC-6-MN | F69: XMTP | G69: BORDEAUX | H69: 1 | I69: =IF(LstMachines[[#This Row],[Delivery]]<Début_HCME, 0, IFERROR( LstMachines[[#This Row],[Nbre]] * INDEX(TabModelSpecs[],MATCH(LstMachines[[#This Row],[Model-Spec]],TabModelSpecs[ModelSpec],0),MATCH("2018",TabModelSpecs[#Headers],0)), LstMachines[[#This Row],[Nbre]]*ROUND(AVERAGEIF(TabModelSpecs[Machine],LstMachines[[#This Row],[Model]],TabModelSpecs[Price]),0) ) ) -> 118 | J69: 43146 | K69: 3-Commande | L69: 2018-02-06 XMTP | O69: =MONTH(LstMachines[[#This Row],[Delivery]]) -> 2 | P69: =FIXED(YEAR(LstMachines[[#This Row],[Delivery]]),0,TRUE) -> 2018 | U69: VENTE | W69: _Stock | X69: =LstMachines[[#This Row],[Delivery]] -> 43146 | Y69: =IF(MONTH(LstMachines[[#This Row],[DateLivr]])<10,"0","") & MONTH(LstMachines[[#This Row],[DateLivr]]) &"-"&YEAR(LstMachines[[#This Row],[DateLivr]]) -> 02-2018 | Z69: =LstMachines[[#This Row],[Delivery]]+Rglt_à_HCME -> 43206 | AA69: =IF(MONTH(LstMachines[[#This Row],[DatePaie]])<10,"0","") & MONTH(LstMachines[[#This Row],[DatePaie]])&"-"&YEAR(LstMachines[[#This Row],[DatePaie]]) -> 04-2018 | AB69: =LstMachines[[#This Row],[DateLivr]]+1 -> 43147 | AC69: =IF(MONTH(LstMachines[[#This Row],[Distrib]])<10,"0","") & MONTH(LstMachines[[#This Row],[Distrib]]) & "-" & YEAR(LstMachines[[#This Row],[Distrib]]) -> 02-2018 | AD69: =LstMachines[[#This Row],[DateLivr]]+Délai_Vente -> 43266 | AE69: =IF(MONTH(LstMachines[[#This Row],[VteESM]])<10,"0","") & MONTH(LstMachines[[#This Row],[VteESM]]) & "-" & YEAR(LstMachines[[#This Row],[VteESM]]) -> 06-2018 | AF69: =LstMachines[[#This Row],[DateLivr]]+Rglt_à_ESMTP -> 43206 | AG69: =IF(MONTH(LstMachines[[#This Row],[RgltDistrib]])<10,"0","") & MONTH(LstMachines[[#This Row],[RgltDistrib]]) & "-" & YEAR(LstMachines[[#This Row],[RgltDistrib]]) -> 04-2018 | AH69: =LstMachines[[#This Row],[VteESM]]+Rglt_à_ESMTP -> 43326 | AI69: =IF(MONTH(LstMachines[[#This Row],[RgltVteESM]])<10,"0","") & MONTH(LstMachines[[#This Row],[RgltVteESM]]) & "-" & YEAR(LstMachines[[#This Row],[RgltVteESM]]) -> 08-2018 | AJ69: =MONTH(LstMachines[[#This Row],[DatePaie]]) -> 4 | AK69: =FIXED(YEAR(LstMachines[[#This Row],[DatePaie]]),0,TRUE) -> 2018
B70: Pelle/Pneus | C70: ZX19 | D70: 19 | E70: ZX19-5A | F70: XMTP | G70: BORDEAUX | H70: 1 | I70: =IF(LstMachines[[#This Row],[Delivery]]<Début_HCME, 0, IFERROR( LstMachines[[#This Row],[Nbre]] * INDEX(TabModelSpecs[],MATCH(LstMachines[[#This Row],[Model-Spec]],TabModelSpecs[ModelSpec],0),MATCH("2018",TabModelSpecs[#Headers],0)), LstMachines[[#This Row],[Nbre]]*ROUND(AVERAGEIF(TabModelSpecs[Machine],LstMachines[[#This Row],[Model]],TabModelSpecs[Price]),0) ) ) -> 18 | J70: 43146 | K70: 5-Livrée | L70: 2018-02-06 XMTP | O70: =MONTH(LstMachines[[#This Row],[Delivery]]) -> 2 | P70: =FIXED(YEAR(LstMachines[[#This Row],[Delivery]]),0,TRUE) -> 2018 | X70: =LstMachines[[#This Row],[Delivery]] -> 43146 | Y70: =IF(MONTH(LstMachines[[#This Row],[DateLivr]])<10,"0","") & MONTH(LstMachines[[#This Row],[DateLivr]]) &"-"&YEAR(LstMachines[[#This Row],[DateLivr]]) -> 02-2018 | Z70: =LstMachines[[#This Row],[Delivery]]+Rglt_à_HCME -> 43206 | AA70: =IF(MONTH(LstMachines[[#This Row],[DatePaie]])<10,"0","") & MONTH(LstMachines[[#This Row],[DatePaie]])&"-"&YEAR(LstMachines[[#This Row],[DatePaie]]) -> 04-2018 | AB70: =LstMachines[[#This Row],[DateLivr]]+1 -> 43147 | AC70: =IF(MONTH(LstMachines[[#This Row],[Distrib]])<10,"0","") & MONTH(LstMachines[[#This Row],[Distrib]]) & "-" & YEAR(LstMachines[[#This Row],[Distrib]]) -> 02-2018 | AD70: =LstMachines[[#This Row],[DateLivr]]+Délai_Vente -> 43266 | AE70: =IF(MONTH(LstMachines[[#This Row],[VteESM]])<10,"0","") & MONTH(LstMachines[[#This Row],[VteESM]]) & "-" & YEAR(LstMachines[[#This Row],[VteESM]]) -> 06-2018 | AF70: =LstMachines[[#This Row],[DateLivr]]+Rglt_à_ESMTP -> 43206 | AG70: =IF(MONTH(LstMachines[[#This Row],[RgltDistrib]])<10,"0","") & MONTH(LstMachines[[#This Row],[RgltDistrib]]) & "-" & YEAR(LstMachines[[#This Row],[RgltDistrib]]) -> 04-2018 | AH70: =LstMachines[[#This Row],[VteESM]]+Rglt_à_ESMTP -> 43326 | AI70: =IF(MONTH(LstMachines[[#This Row],[RgltVteESM]])<10,"0","") & MONTH(LstMachines[[#This Row],[RgltVteESM]]) & "-" & YEAR(LstMachines[[#This Row],[RgltVteESM]]) -> 08-2018 | AJ70: =MONTH(LstMachines[[#This Row],[DatePaie]]) -> 4 | AK70: =FIXED(YEAR(LstMachines[[#This Row],[DatePaie]]),0,TRUE) -> 2018
B71: Pelle/Pneus | C71: ZX19 | D71: 19 | E71: ZX19U-5 | F71: XMTP | G71: BORDEAUX | H71: 1 | I71: =IF(LstMachines[[#This Row],[Delivery]]<Début_HCME, 0, IFERROR( LstMachines[[#This Row],[Nbre]] * INDEX(TabModelSpecs[],MATCH(LstMachines[[#This Row],[Model-Spec]],TabModelSpecs[ModelSpec],0),MATCH("2018",TabModelSpecs[#Headers],0)), LstMachines[[#This Row],[Nbre]]*ROUND(AVERAGEIF(TabModelSpecs[Machine],LstMachines[[#This Row],[Model]],TabModelSpecs[Price]),0) ) ) -> 18 | J71: 43146 | K71: 5-Livrée | L71: 2018-02-06 XMTP | O71: =MONTH(LstMachines[[#This Row],[Delivery]]) -> 2 | P71: =FIXED(YEAR(LstMachines[[#This Row],[Delivery]]),0,TRUE) -> 2018 | X71: =LstMachines[[#This Row],[Delivery]] -> 43146 | Y71: =IF(MONTH(LstMachines[[#This Row],[DateLivr]])<10,"0","") & MONTH(LstMachines[[#This Row],[DateLivr]]) &"-"&YEAR(LstMachines[[#This Row],[DateLivr]]) -> 02-2018 | Z71: =LstMachines[[#This Row],[Delivery]]+Rglt_à_HCME -> 43206 | AA71: =IF(MONTH(LstMachines[[#This Row],[DatePaie]])<10,"0","") & MONTH(LstMachines[[#This Row],[DatePaie]])&"-"&YEAR(LstMachines[[#This Row],[DatePaie]]) -> 04-2018 | AB71: =LstMachines[[#This Row],[DateLivr]]+1 -> 43147 | AC71: =IF(MONTH(LstMachines[[#This Row],[Distrib]])<10,"0","") & MONTH(LstMachines[[#This Row],[Distrib]]) & "-" & YEAR(LstMachines[[#This Row],[Distrib]]) -> 02-2018 | AD71: =LstMachines[[#This Row],[DateLivr]]+Délai_Vente -> 43266 | AE71: =IF(MONTH(LstMachines[[#This Row],[VteESM]])<10,"0","") & MONTH(LstMachines[[#This Row],[VteESM]]) & "-" & YEAR(LstMachines[[#This Row],[VteESM]]) -> 06-2018 | AF71: =LstMachines[[#This Row],[DateLivr]]+Rglt_à_ESMTP -> 43206 | AG71: =IF(MONTH(LstMachines[[#This Row],[RgltDistrib]])<10,"0","") & MONTH(LstMachines[[#This Row],[RgltDistrib]]) & "-" & YEAR(LstMachines[[#This Row],[RgltDistrib]]) -> 04-2018 | AH71: =LstMachines[[#This Row],[VteESM]]+Rglt_à_ESMTP -> 43326 | AI71: =IF(MONTH(LstMachines[[#This Row],[RgltVteESM]])<10,"0","") & MONTH(LstMachines[[#This Row],[RgltVteESM]]) & "-" & YEAR(LstMachines[[#This Row],[RgltVteESM]]) -> 08-2018 | AJ71: =MONTH(LstMachines[[#This Row],[DatePaie]]) -> 4 | AK71: =FIXED(YEAR(LstMachines[[#This Row],[DatePaie]]),0,TRUE) -> 2018
B72: Pelle/Pneus | C72: ZX145 | D72: 145 | E72: ZX145W-6-2P | F72: XMTP | G72: BORDEAUX | H72: 1 | I72: =IF(LstMachines[[#This Row],[Delivery]]<Début_HCME, 0, IFERROR( LstMachines[[#This Row],[Nbre]] * INDEX(TabModelSpecs[],MATCH(LstMachines[[#This Row],[Model-Spec]],TabModelSpecs[ModelSpec],0),MATCH("2018",TabModelSpecs[#Headers],0)), LstMachines[[#This Row],[Nbre]]*ROUND(AVERAGEIF(TabModelSpecs[Machine],LstMachines[[#This Row],[Model]],TabModelSpecs[Price]),0) ) ) -> 115 | J72: 43146 | K72: 3-Commande | L72: 2017-12 XMTP | O72: =MONTH(LstMachines[[#This Row],[Delivery]]) -> 2 | P72: =FIXED(YEAR(LstMachines[[#This Row],[Delivery]]),0,TRUE) -> 2018 | U72: VENTE | W72: _Stock | X72: =LstMachines[[#This Row],[Delivery]] -> 43146 | Y72: =IF(MONTH(LstMachines[[#This Row],[DateLivr]])<10,"0","") & MONTH(LstMachines[[#This Row],[DateLivr]]) &"-"&YEAR(LstMachines[[#This Row],[DateLivr]]) -> 02-2018 | Z72: =LstMachines[[#This Row],[Delivery]]+Rglt_à_HCME -> 43206 | AA72: =IF(MONTH(LstMachines[[#This Row],[DatePaie]])<10,"0","") & MONTH(LstMachines[[#This Row],[DatePaie]])&"-"&YEAR(LstMachines[[#This Row],[DatePaie]]) -> 04-2018 | AB72: =LstMachines[[#This Row],[DateLivr]]+1 -> 43147 | AC72: =IF(MONTH(LstMachines[[#This Row],[Distrib]])<10,"0","") & MONTH(LstMachines[[#This Row],[Distrib]]) & "-" & YEAR(LstMachines[[#This Row],[Distrib]]) -> 02-2018 | AD72: =LstMachines[[#This Row],[DateLivr]]+Délai_Vente -> 43266 | AE72: =IF(MONTH(LstMachines[[#This Row],[VteESM]])<10,"0","") & MONTH(LstMachines[[#This Row],[VteESM]]) & "-" & YEAR(LstMachines[[#This Row],[VteESM]]) -> 06-2018 | AF72: =LstMachines[[#This Row],[DateLivr]]+Rglt_à_ESMTP -> 43206 | AG72: =IF(MONTH(LstMachines[[#This Row],[RgltDistrib]])<10,"0","") & MONTH(LstMachines[[#This Row],[RgltDistrib]]) & "-" & YEAR(LstMachines[[#This Row],[RgltDistrib]]) -> 04-2018 | AH72: =LstMachines[[#This Row],[VteESM]]+Rglt_à_ESMTP -> 43326 | AI72: =IF(MONTH(LstMachines[[#This Row],[RgltVteESM]])<10,"0","") & MONTH(LstMachines[[#This Row],[RgltVteESM]]) & "-" & YEAR(LstMachines[[#This Row],[RgltVteESM]]) -> 08-2018 | AJ72: =MONTH(LstMachines[[#This Row],[DatePaie]]) -> 4 | AK72: =FIXED(YEAR(LstMachines[[#This Row],[DatePaie]]),0,TRUE) -> 2018
B73: Pelle/Chenilles | C73: ZX135 | D73: 135 | E73: ZX135US-6-MN-BL | F73: XMTP | G73: BORDEAUX | H73: 1 | I73: =IF(LstMachines[[#This Row],[Delivery]]<Début_HCME, 0, IFERROR( LstMachines[[#This Row],[Nbre]] * INDEX(TabModelSpecs[],MATCH(LstMachines[[#This Row],[Model-Spec]],TabModelSpecs[ModelSpec],0),MATCH("2018",TabModelSpecs[#Headers],0)), LstMachines[[#This Row],[Nbre]]*ROUND(AVERAGEIF(TabModelSpecs[Machine],LstMachines[[#This Row],[Model]],TabModelSpecs[Price]),0) ) ) -> 102 | J73: 43146 | K73: 3-Commande | L73: 2017-12 XMTP | O73: =MONTH(LstMachines[[#This Row],[Delivery]]) -> 2 | P73: =FIXED(YEAR(LstMachines[[#This Row],[Delivery]]),0,TRUE) -> 2018 | U73: VENTE | W73: _Stock | X73: =LstMachines[[#This Row],[Delivery]] -> 43146 | Y73: =IF(MONTH(LstMachines[[#This Row],[DateLivr]])<10,"0","") & MONTH(LstMachines[[#This Row],[DateLivr]]) &"-"&YEAR(LstMachines[[#This Row],[DateLivr]]) -> 02-2018 | Z73: =LstMachines[[#This Row],[Delivery]]+Rglt_à_HCME -> 43206 | AA73: =IF(MONTH(LstMachines[[#This Row],[DatePaie]])<10,"0","") & MONTH(LstMachines[[#This Row],[DatePaie]])&"-"&YEAR(LstMachines[[#This Row],[DatePaie]]) -> 04-2018 | AB73: =LstMachines[[#This Row],[DateLivr]]+1 -> 43147 | AC73: =IF(MONTH(LstMachines[[#This Row],[Distrib]])<10,"0","") & MONTH(LstMachines[[#This Row],[Distrib]]) & "-" & YEAR(LstMachines[[#This Row],[Distrib]]) -> 02-2018 | AD73: =LstMachines[[#This Row],[DateLivr]]+Délai_Vente -> 43266 | AE73: =IF(MONTH(LstMachines[[#This Row],[VteESM]])<10,"0","") & MONTH(LstMachines[[#This Row],[VteESM]]) & "-" & YEAR(LstMachines[[#This Row],[VteESM]]) -> 06-2018 | AF73: =LstMachines[[#This Row],[DateLivr]]+Rglt_à_ESMTP -> 43206 | AG73: =IF(MONTH(LstMachines[[#This Row],[RgltDistrib]])<10,"0","") & MONTH(LstMachines[[#This Row],[RgltDistrib]]) & "-" & YEAR(LstMachines[[#This Row],[RgltDistrib]]) -> 04-2018 | AH73: =LstMachines[[#This Row],[VteESM]]+Rglt_à_ESMTP -> 43326 | AI73: =IF(MONTH(LstMachines[[#This Row],[RgltVteESM]])<10,"0","") & MONTH(LstMachines[[#This Row],[RgltVteESM]]) & "-" & YEAR(LstMachines[[#This Row],[RgltVteESM]]) -> 08-2018 | AJ73: =MONTH(LstMachines[[#This Row],[DatePaie]]) -> 4 | AK73: =FIXED(YEAR(LstMachines[[#This Row],[DatePaie]]),0,TRUE) -> 2018
B74: Pelle/Chenilles | C74: ZX85 | D74: 85 | E74: ZX85USB-5A-Mono | F74: XMTP | G74: BORDEAUX | H74: 2 | I74: =IF(LstMachines[[#This Row],[Delivery]]<Début_HCME, 0, IFERROR( LstMachines[[#This Row],[Nbre]] * INDEX(TabModelSpecs[],MATCH(LstMachines[[#This Row],[Model-Spec]],TabModelSpecs[ModelSpec],0),MATCH("2018",TabModelSpecs[#Headers],0)), LstMachines[[#This Row],[Nbre]]*ROUND(AVERAGEIF(TabModelSpecs[Machine],LstMachines[[#This Row],[Model]],TabModelSpecs[Price]),0) ) ) -> 128 | J74: 43146 | K74: 3-Commande | L74: 2017-12 XMTP | O74: =MONTH(LstMachines[[#This Row],[Delivery]]) -> 2 | P74: =FIXED(YEAR(LstMachines[[#This Row],[Delivery]]),0,TRUE) -> 2018 | U74: VENTE | W74: _Stock | X74: =LstMachines[[#This Row],[Delivery]] -> 43146 | Y74: =IF(MONTH(LstMachines[[#This Row],[DateLivr]])<10,"0","") & MONTH(LstMachines[[#This Row],[DateLivr]]) &"-"&YEAR(LstMachines[[#This Row],[DateLivr]]) -> 02-2018 | Z74: =LstMachines[[#This Row],[Delivery]]+Rglt_à_HCME -> 43206 | AA74: =IF(MONTH(LstMachines[[#This Row],[DatePaie]])<10,"0","") & MONTH(LstMachines[[#This Row],[DatePaie]])&"-"&YEAR(LstMachines[[#This Row],[DatePaie]]) -> 04-2018 | AB74: =LstMachines[[#This Row],[DateLivr]]+1 -> 43147 | AC74: =IF(MONTH(LstMachines[[#This Row],[Distrib]])<10,"0","") & MONTH(LstMachines[[#This Row],[Distrib]]) & "-" & YEAR(LstMachines[[#This Row],[Distrib]]) -> 02-2018 | AD74: =LstMachines[[#This Row],[DateLivr]]+Délai_Vente -> 43266 | AE74: =IF(MONTH(LstMachines[[#This Row],[VteESM]])<10,"0","") & MONTH(LstMachines[[#This Row],[VteESM]]) & "-" & YEAR(LstMachines[[#This Row],[VteESM]]) -> 06-2018 | AF74: =LstMachines[[#This Row],[DateLivr]]+Rglt_à_ESMTP -> 43206 | AG74: =IF(MONTH(LstMachines[[#This Row],[RgltDistrib]])<10,"0","") & MONTH(LstMachines[[#This Row],[RgltDistrib]]) & "-" & YEAR(LstMachines[[#This Row],[RgltDistrib]]) -> 04-2018 | AH74: =LstMachines[[#This Row],[VteESM]]+Rglt_à_ESMTP -> 43326 | AI74: =IF(MONTH(LstMachines[[#This Row],[RgltVteESM]])<10,"0","") & MONTH(LstMachines[[#This Row],[RgltVteESM]]) & "-" & YEAR(LstMachines[[#This Row],[RgltVteESM]]) -> 08-2018 | AJ74: =MONTH(LstMachines[[#This Row],[DatePaie]]) -> 4 | AK74: =FIXED(YEAR(LstMachines[[#This Row],[DatePaie]]),0,TRUE) -> 2018
B75: Mini Pelle | C75: ZX26 | D75: 26 | E75: ZX26U-5-YLR | F75: XMTP | G75: BORDEAUX | H75: 4 | I75: =IF(LstMachines[[#This Row],[Delivery]]<Début_HCME, 0, IFERROR( LstMachines[[#This Row],[Nbre]] * INDEX(TabModelSpecs[],MATCH(LstMachines[[#This Row],[Model-Spec]],TabModelSpecs[ModelSpec],0),MATCH("2018",TabModelSpecs[#Headers],0)), LstMachines[[#This Row],[Nbre]]*ROUND(AVERAGEIF(TabModelSpecs[Machine],LstMachines[[#This Row],[Model]],TabModelSpecs[Price]),0) ) ) -> 88 | J75: 43146 | K75: 5-Livrée | L75: 2017-12 XMTP | O75: =MONTH(LstMachines[[#This Row],[Delivery]]) -> 2 | P75: =FIXED(YEAR(LstMachines[[#This Row],[Delivery]]),0,TRUE) -> 2018 | U75: VENTE | W75: _Stock | X75: =LstMachines[[#This Row],[Delivery]] -> 43146 | Y75: =IF(MONTH(LstMachines[[#This Row],[DateLivr]])<10,"0","") & MONTH(LstMachines[[#This Row],[DateLivr]]) &"-"&YEAR(LstMachines[[#This Row],[DateLivr]]) -> 02-2018 | Z75: =LstMachines[[#This Row],[Delivery]]+Rglt_à_HCME -> 43206 | AA75: =IF(MONTH(LstMachines[[#This Row],[DatePaie]])<10,"0","") & MONTH(LstMachines[[#This Row],[DatePaie]])&"-"&YEAR(LstMachines[[#This Row],[DatePaie]]) -> 04-2018 | AB75: =LstMachines[[#This Row],[DateLivr]]+1 -> 43147 | AC75: =IF(MONTH(LstMachines[[#This Row],[Distrib]])<10,"0","") & MONTH(LstMachines[[#This Row],[Distrib]]) & "-" & YEAR(LstMachines[[#This Row],[Distrib]]) -> 02-2018 | AD75: =LstMachines[[#This Row],[DateLivr]]+Délai_Vente -> 43266 | AE75: =IF(MONTH(LstMachines[[#This Row],[VteESM]])<10,"0","") & MONTH(LstMachines[[#This Row],[VteESM]]) & "-" & YEAR(LstMachines[[#This Row],[VteESM]]) -> 06-2018 | AF75: =LstMachines[[#This Row],[DateLivr]]+Rglt_à_ESMTP -> 43206 | AG75: =IF(MONTH(LstMachines[[#This Row],[RgltDistrib]])<10,"0","") & MONTH(LstMachines[[#This Row],[RgltDistrib]]) & "-" & YEAR(LstMachines[[#This Row],[RgltDistrib]]) -> 04-2018 | AH75: =LstMachines[[#This Row],[VteESM]]+Rglt_à_ESMTP -> 43326 | AI75: =IF(MONTH(LstMachines[[#This Row],[RgltVteESM]])<10,"0","") & MONTH(LstMachines[[#This Row],[RgltVteESM]]) & "-" & YEAR(LstMachines[[#This Row],[RgltVteESM]]) -> 08-2018 | AJ75: =MONTH(LstMachines[[#This Row],[DatePaie]]) -> 4 | AK75: =FIXED(YEAR(LstMachines[[#This Row],[DatePaie]]),0,TRUE) -> 2018
B76: Pelle/Chenilles | C76: ZX85 | D76: 85 | E76: ZX85USB-5A-Mono | F76: BTPS | G76: ORTHEZ | H76: 1 | I76: =IF(LstMachines[[#This Row],[Delivery]]<Début_HCME, 0, IFERROR( LstMachines[[#This Row],[Nbre]] * INDEX(TabModelSpecs[],MATCH(LstMachines[[#This Row],[Model-Spec]],TabModelSpecs[ModelSpec],0),MATCH("2018",TabModelSpecs[#Headers],0)), LstMachines[[#This Row],[Nbre]]*ROUND(AVERAGEIF(TabModelSpecs[Machine],LstMachines[[#This Row],[Model]],TabModelSpecs[Price]),0) ) ) -> 64 | J76: 43174 | K76: 3-Commande | L76: 2017-11 BTPS | O76: =MONTH(LstMachines[[#This Row],[Delivery]]) -> 3 | P76: =FIXED(YEAR(LstMachines[[#This Row],[Delivery]]),0,TRUE) -> 2018 | X76: =LstMachines[[#This Row],[Delivery]] -> 43174 | Y76: =IF(MONTH(LstMachines[[#This Row],[DateLivr]])<10,"0","") & MONTH(LstMachines[[#This Row],[DateLivr]]) &"-"&YEAR(LstMachines[[#This Row],[DateLivr]]) -> 03-2018 | Z76: =LstMachines[[#This Row],[Delivery]]+Rglt_à_HCME -> 43234 | AA76: =IF(MONTH(LstMachines[[#This Row],[DatePaie]])<10,"0","") & MONTH(LstMachines[[#This Row],[DatePaie]])&"-"&YEAR(LstMachines[[#This Row],[DatePaie]]) -> 05-2018 | AB76: =LstMachines[[#This Row],[DateLivr]]+1 -> 43175 | AC76: =IF(MONTH(LstMachines[[#This Row],[Distrib]])<10,"0","") & MONTH(LstMachines[[#This Row],[Distrib]]) & "-" & YEAR(LstMachines[[#This Row],[Distrib]]) -> 03-2018 | AD76: =LstMachines[[#This Row],[DateLivr]]+Délai_Vente -> 43294 | AE76: =IF(MONTH(LstMachines[[#This Row],[VteESM]])<10,"0","") & MONTH(LstMachines[[#This Row],[VteESM]]) & "-" & YEAR(LstMachines[[#This Row],[VteESM]]) -> 07-2018 | AF76: =LstMachines[[#This Row],[DateLivr]]+Rglt_à_ESMTP -> 43234 | AG76: =IF(MONTH(LstMachines[[#This Row],[RgltDistrib]])<10,"0","") & MONTH(LstMachines[[#This Row],[RgltDistrib]]) & "-" & YEAR(LstMachines[[#This Row],[RgltDistrib]]) -> 05-2018 | AH76: =LstMachines[[#This Row],[VteESM]]+Rglt_à_ESMTP -> 43354 | AI76: =IF(MONTH(LstMachines[[#This Row],[RgltVteESM]])<10,"0","") & MONTH(LstMachines[[#This Row],[RgltVteESM]]) & "-" & YEAR(LstMachines[[#This Row],[RgltVteESM]]) -> 09-2018 | AJ76: =MONTH(LstMachines[[#This Row],[DatePaie]]) -> 5 | AK76: =FIXED(YEAR(LstMachines[[#This Row],[DatePaie]]),0,TRUE) -> 2018
B77: Mini Pelle | C77: ZX19 | D77: 19 | E77: ZX19U-5 | F77: BTPS | G77: ORTHEZ | H77: 1 | I77: =IF(LstMachines[[#This Row],[Delivery]]<Début_HCME, 0, IFERROR( LstMachines[[#This Row],[Nbre]] * INDEX(TabModelSpecs[],MATCH(LstMachines[[#This Row],[Model-Spec]],TabModelSpecs[ModelSpec],0),MATCH("2018",TabModelSpecs[#Headers],0)), LstMachines[[#This Row],[Nbre]]*ROUND(AVERAGEIF(TabModelSpecs[Machine],LstMachines[[#This Row],[Model]],TabModelSpecs[Price]),0) ) ) -> 18 | J77: 43174 | K77: 1-Forecast | L77: 2017-11 BTPS | O77: =MONTH(LstMachines[[#This Row],[Delivery]]) -> 3 | P77: =FIXED(YEAR(LstMachines[[#This Row],[Delivery]]),0,TRUE) -> 2018 | X77: =LstMachines[[#This Row],[Delivery]] -> 43174 | Y77: =IF(MONTH(LstMachines[[#This Row],[DateLivr]])<10,"0","") & MONTH(LstMachines[[#This Row],[DateLivr]]) &"-"&YEAR(LstMachines[[#This Row],[DateLivr]]) -> 03-2018 | Z77: =LstMachines[[#This Row],[Delivery]]+Rglt_à_HCME -> 43234 | AA77: =IF(MONTH(LstMachines[[#This Row],[DatePaie]])<10,"0","") & MONTH(LstMachines[[#This Row],[DatePaie]])&"-"&YEAR(LstMachines[[#This Row],[DatePaie]]) -> 05-2018 | AB77: =LstMachines[[#This Row],[DateLivr]]+1 -> 43175 | AC77: =IF(MONTH(LstMachines[[#This Row],[Distrib]])<10,"0","") & MONTH(LstMachines[[#This Row],[Distrib]]) & "-" & YEAR(LstMachines[[#This Row],[Distrib]]) -> 03-2018 | AD77: =LstMachines[[#This Row],[DateLivr]]+Délai_Vente -> 43294 | AE77: =IF(MONTH(LstMachines[[#This Row],[VteESM]])<10,"0","") & MONTH(LstMachines[[#This Row],[VteESM]]) & "-" & YEAR(LstMachines[[#This Row],[VteESM]]) -> 07-2018 | AF77: =LstMachines[[#This Row],[DateLivr]]+Rglt_à_ESMTP -> 43234 | AG77: =IF(MONTH(LstMachines[[#This Row],[RgltDistrib]])<10,"0","") & MONTH(LstMachines[[#This Row],[RgltDistrib]]) & "-" & YEAR(LstMachines[[#This Row],[RgltDistrib]]) -> 05-2018 | AH77: =LstMachines[[#This Row],[VteESM]]+Rglt_à_ESMTP -> 43354 | AI77: =IF(MONTH(LstMachines[[#This Row],[RgltVteESM]])<10,"0","") & MONTH(LstMachines[[#This Row],[RgltVteESM]]) & "-" & YEAR(LstMachines[[#This Row],[RgltVteESM]]) -> 09-2018 | AJ77: =MONTH(LstMachines[[#This Row],[DatePaie]]) -> 5 | AK77: =FIXED(YEAR(LstMachines[[#This Row],[DatePaie]]),0,TRUE) -> 2018
B78: Mini Pelle | C78: ZX65 | D78: 65 | E78: ZX65USB-5-CLRNH | F78: BTPS | G78: ORTHEZ | H78: 1 | I78: =IF(LstMachines[[#This Row],[Delivery]]<Début_HCME, 0, IFERROR( LstMachines[[#This Row],[Nbre]] * INDEX(TabModelSpecs[],MATCH(LstMachines[[#This Row],[Model-Spec]],TabModelSpecs[ModelSpec],0),MATCH("2018",TabModelSpecs[#Headers],0)), LstMachines[[#This Row],[Nbre]]*ROUND(AVERAGEIF(TabModelSpecs[Machine],LstMachines[[#This Row],[Model]],TabModelSpecs[Price]),0) ) ) -> 45 | J78: 43174 | K78: 1-Forecast | L78: 2017-11 BTPS | O78: =MONTH(LstMachines[[#This Row],[Delivery]]) -> 3 | P78: =FIXED(YEAR(LstMachines[[#This Row],[Delivery]]),0,TRUE) -> 2018 | X78: =LstMachines[[#This Row],[Delivery]] -> 43174 | Y78: =IF(MONTH(LstMachines[[#This Row],[DateLivr]])<10,"0","") & MONTH(LstMachines[[#This Row],[DateLivr]]) &"-"&YEAR(LstMachines[[#This Row],[DateLivr]]) -> 03-2018 | Z78: =LstMachines[[#This Row],[Delivery]]+Rglt_à_HCME -> 43234 | AA78: =IF(MONTH(LstMachines[[#This Row],[DatePaie]])<10,"0","") & MONTH(LstMachines[[#This Row],[DatePaie]])&"-"&YEAR(LstMachines[[#This Row],[DatePaie]]) -> 05-2018 | AB78: =LstMachines[[#This Row],[DateLivr]]+1 -> 43175 | AC78: =IF(MONTH(LstMachines[[#This Row],[Distrib]])<10,"0","") & MONTH(LstMachines[[#This Row],[Distrib]]) & "-" & YEAR(LstMachines[[#This Row],[Distrib]]) -> 03-2018 | AD78: =LstMachines[[#This Row],[DateLivr]]+Délai_Vente -> 43294 | AE78: =IF(MONTH(LstMachines[[#This Row],[VteESM]])<10,"0","") & MONTH(LstMachines[[#This Row],[VteESM]]) & "-" & YEAR(LstMachines[[#This Row],[VteESM]]) -> 07-2018 | AF78: =LstMachines[[#This Row],[DateLivr]]+Rglt_à_ESMTP -> 43234 | AG78: =IF(MONTH(LstMachines[[#This Row],[RgltDistrib]])<10,"0","") & MONTH(LstMachines[[#This Row],[RgltDistrib]]) & "-" & YEAR(LstMachines[[#This Row],[RgltDistrib]]) -> 05-2018 | AH78: =LstMachines[[#This Row],[VteESM]]+Rglt_à_ESMTP -> 43354 | AI78: =IF(MONTH(LstMachines[[#This Row],[RgltVteESM]])<10,"0","") & MONTH(LstMachines[[#This Row],[RgltVteESM]]) & "-" & YEAR(LstMachines[[#This Row],[RgltVteESM]]) -> 09-2018 | AJ78: =MONTH(LstMachines[[#This Row],[DatePaie]]) -> 5 | AK78: =FIXED(YEAR(LstMachines[[#This Row],[DatePaie]]),0,TRUE) -> 2018
B79: Pelle/Chenilles | C79: ZX85 | D79: 85 | E79: ZX85USB-5A-Mono | F79: BTPS | G79: ORTHEZ | H79: 1 | I79: =IF(LstMachines[[#This Row],[Delivery]]<Début_HCME, 0, IFERROR( LstMachines[[#This Row],[Nbre]] * INDEX(TabModelSpecs[],MATCH(LstMachines[[#This Row],[Model-Spec]],TabModelSpecs[ModelSpec],0),MATCH("2018",TabModelSpecs[#Headers],0)), LstMachines[[#This Row],[Nbre]]*ROUND(AVERAGEIF(TabModelSpecs[Machine],LstMachines[[#This Row],[Model]],TabModelSpecs[Price]),0) ) ) -> 64 | J79: 43174 | K79: 1-Forecast | L79: 2017-11 BTPS | O79: =MONTH(LstMachines[[#This Row],[Delivery]]) -> 3 | P79: =FIXED(YEAR(LstMachines[[#This Row],[Delivery]]),0,TRUE) -> 2018 | X79: =LstMachines[[#This Row],[Delivery]] -> 43174 | Y79: =IF(MONTH(LstMachines[[#This Row],[DateLivr]])<10,"0","") & MONTH(LstMachines[[#This Row],[DateLivr]]) &"-"&YEAR(LstMachines[[#This Row],[DateLivr]]) -> 03-2018 | Z79: =LstMachines[[#This Row],[Delivery]]+Rglt_à_HCME -> 43234 | AA79: =IF(MONTH(LstMachines[[#This Row],[DatePaie]])<10,"0","") & MONTH(LstMachines[[#This Row],[DatePaie]])&"-"&YEAR(LstMachines[[#This Row],[DatePaie]]) -> 05-2018 | AB79: =LstMachines[[#This Row],[DateLivr]]+1 -> 43175 | AC79: =IF(MONTH(LstMachines[[#This Row],[Distrib]])<10,"0","") & MONTH(LstMachines[[#This Row],[Distrib]]) & "-" & YEAR(LstMachines[[#This Row],[Distrib]]) -> 03-2018 | AD79: =LstMachines[[#This Row],[DateLivr]]+Délai_Vente -> 43294 | AE79: =IF(MONTH(LstMachines[[#This Row],[VteESM]])<10,"0","") & MONTH(LstMachines[[#This Row],[VteESM]]) & "-" & YEAR(LstMachines[[#This Row],[VteESM]]) -> 07-2018 | AF79: =LstMachines[[#This Row],[DateLivr]]+Rglt_à_ESMTP -> 43234 | AG79: =IF(MONTH(LstMachines[[#This Row],[RgltDistrib]])<10,"0","") & MONTH(LstMachines[[#This Row],[RgltDistrib]]) & "-" & YEAR(LstMachines[[#This Row],[RgltDistrib]]) -> 05-2018 | AH79: =LstMachines[[#This Row],[VteESM]]+Rglt_à_ESMTP -> 43354 | AI79: =IF(MONTH(LstMachines[[#This Row],[RgltVteESM]])<10,"0","") & MONTH(LstMachines[[#This Row],[RgltVteESM]]) & "-" & YEAR(LstMachines[[#This Row],[RgltVteESM]]) -> 09-2018 | AJ79: =MONTH(LstMachines[[#This Row],[DatePaie]]) -> 5 | AK79: =FIXED(YEAR(LstMachines[[#This Row],[DatePaie]]),0,TRUE) -> 2018
B80: Pelle/Chenilles | C80: ZX65 | D80: 65 | E80: ZX65U-5-CLR | F80: LIMA TP | G80: BOISSEUIL | H80: 1 | I80: 47 | J80: 43174 | K80: 3-Commande | L80: 2017-12-29 LIMA | O80: =MONTH(LstMachines[[#This Row],[Delivery]]) -> 3 | P80: =FIXED(YEAR(LstMachines[[#This Row],[Delivery]]),0,TRUE) -> 2018 | W80: _Stock | X80: =LstMachines[[#This Row],[Delivery]] -> 43174 | Y80: =IF(MONTH(LstMachines[[#This Row],[DateLivr]])<10,"0","") & MONTH(LstMachines[[#This Row],[DateLivr]]) &"-"&YEAR(LstMachines[[#This Row],[DateLivr]]) -> 03-2018 | Z80: =LstMachines[[#This Row],[Delivery]]+Rglt_à_HCME -> 43234 | AA80: =IF(MONTH(LstMachines[[#This Row],[DatePaie]])<10,"0","") & MONTH(LstMachines[[#This Row],[DatePaie]])&"-"&YEAR(LstMachines[[#This Row],[DatePaie]]) -> 05-2018 | AB80: =LstMachines[[#This Row],[DateLivr]]+1 -> 43175 | AC80: =IF(MONTH(LstMachines[[#This Row],[Distrib]])<10,"0","") & MONTH(LstMachines[[#This Row],[Distrib]]) & "-" & YEAR(LstMachines[[#This Row],[Distrib]]) -> 03-2018 | AD80: =LstMachines[[#This Row],[DateLivr]]+Délai_Vente -> 43294 | AE80: =IF(MONTH(LstMachines[[#This Row],[VteESM]])<10,"0","") & MONTH(LstMachines[[#This Row],[VteESM]]) & "-" & YEAR(LstMachines[[#This Row],[VteESM]]) -> 07-2018 | AF80: =LstMachines[[#This Row],[DateLivr]]+Rglt_à_ESMTP -> 43234 | AG80: =IF(MONTH(LstMachines[[#This Row],[RgltDistrib]])<10,"0","") & MONTH(LstMachines[[#This Row],[RgltDistrib]]) & "-" & YEAR(LstMachines[[#This Row],[RgltDistrib]]) -> 05-2018 | AH80: =LstMachines[[#This Row],[VteESM]]+Rglt_à_ESMTP -> 43354 | AI80: =IF(MONTH(LstMachines[[#This Row],[RgltVteESM]])<10,"0","") & MONTH(LstMachines[[#This Row],[RgltVteESM]]) & "-" & YEAR(LstMachines[[#This Row],[RgltVteESM]]) -> 09-2018 | AJ80: =MONTH(LstMachines[[#This Row],[DatePaie]]) -> 5 | AK80: =FIXED(YEAR(LstMachines[[#This Row],[DatePaie]]),0,TRUE) -> 2018
B81: Mini Pelle | C81: ZX19 | D81: 19 | E81: ZX19U-5 | F81: SETP | G81: RABASTENS | H81: 1 | I81: =IF(LstMachines[[#This Row],[Delivery]]<Début_HCME, 0, IFERROR( LstMachines[[#This Row],[Nbre]] * INDEX(TabModelSpecs[],MATCH(LstMachines[[#This Row],[Model-Spec]],TabModelSpecs[ModelSpec],0),MATCH("2018",TabModelSpecs[#Headers],0)), LstMachines[[#This Row],[Nbre]]*ROUND(AVERAGEIF(TabModelSpecs[Machine],LstMachines[[#This Row],[Model]],TabModelSpecs[Price]),0) ) ) -> 18 | J81: 43174 | K81: 3-Commande | L81: 2017-12-06 ADV | N81: 43036 | O81: =MONTH(LstMachines[[#This Row],[Delivery]]) -> 3 | P81: =FIXED(YEAR(LstMachines[[#This Row],[Delivery]]),0,TRUE) -> 2018 | Q81: 17100087 | R81: 16198 | U81: STOCK | V81: 4235 | W81: _Stock | X81: =LstMachines[[#This Row],[Delivery]] -> 43174 | Y81: =IF(MONTH(LstMachines[[#This Row],[DateLivr]])<10,"0","") & MONTH(LstMachines[[#This Row],[DateLivr]]) &"-"&YEAR(LstMachines[[#This Row],[DateLivr]]) -> 03-2018 | Z81: =LstMachines[[#This Row],[Delivery]]+Rglt_à_HCME -> 43234 | AA81: =IF(MONTH(LstMachines[[#This Row],[DatePaie]])<10,"0","") & MONTH(LstMachines[[#This Row],[DatePaie]])&"-"&YEAR(LstMachines[[#This Row],[DatePaie]]) -> 05-2018 | AB81: =LstMachines[[#This Row],[DateLivr]]+1 -> 43175 | AC81: =IF(MONTH(LstMachines[[#This Row],[Distrib]])<10,"0","") & MONTH(LstMachines[[#This Row],[Distrib]]) & "-" & YEAR(LstMachines[[#This Row],[Distrib]]) -> 03-2018 | AD81: =LstMachines[[#This Row],[DateLivr]]+Délai_Vente -> 43294 | AE81: =IF(MONTH(LstMachines[[#This Row],[VteESM]])<10,"0","") & MONTH(LstMachines[[#This Row],[VteESM]]) & "-" & YEAR(LstMachines[[#This Row],[VteESM]]) -> 07-2018 | AF81: =LstMachines[[#This Row],[DateLivr]]+Rglt_à_ESMTP -> 43234 | AG81: =IF(MONTH(LstMachines[[#This Row],[RgltDistrib]])<10,"0","") & MONTH(LstMachines[[#This Row],[RgltDistrib]]) & "-" & YEAR(LstMachines[[#This Row],[RgltDistrib]]) -> 05-2018 | AH81: =LstMachines[[#This Row],[VteESM]]+Rglt_à_ESMTP -> 43354 | AI81: =IF(MONTH(LstMachines[[#This Row],[RgltVteESM]])<10,"0","") & MONTH(LstMachines[[#This Row],[RgltVteESM]]) & "-" & YEAR(LstMachines[[#This Row],[RgltVteESM]]) -> 09-2018 | AJ81: =MONTH(LstMachines[[#This Row],[DatePaie]]) -> 5 | AK81: =FIXED(YEAR(LstMachines[[#This Row],[DatePaie]]),0,TRUE) -> 2018
B82: Mini Pelle | C82: ZX26 | D82: 26 | E82: ZX26U-5-CLR | F82: SETP | G82: RABASTENS | H82: 1 | I82: =IF(LstMachines[[#This Row],[Delivery]]<Début_HCME, 0, IFERROR( LstMachines[[#This Row],[Nbre]] * INDEX(TabModelSpecs[],MATCH(LstMachines[[#This Row],[Model-Spec]],TabModelSpecs[ModelSpec],0),MATCH("2018",TabModelSpecs[#Headers],0)), LstMachines[[#This Row],[Nbre]]*ROUND(AVERAGEIF(TabModelSpecs[Machine],LstMachines[[#This Row],[Model]],TabModelSpecs[Price]),0) ) ) -> 22 | J82: 43174 | K82: 3-Commande | L82: 2017-12-06 ADV | N82: 43036 | O82: =MONTH(LstMachines[[#This Row],[Delivery]]) -> 3 | P82: =FIXED(YEAR(LstMachines[[#This Row],[Delivery]]),0,TRUE) -> 2018 | Q82: 17100088 | R82: 23608 | U82: VENTE | V82: 4236 | W82: STOCKBAT | X82: =LstMachines[[#This Row],[Delivery]] -> 43174 | Y82: =IF(MONTH(LstMachines[[#This Row],[DateLivr]])<10,"0","") & MONTH(LstMachines[[#This Row],[DateLivr]]) &"-"&YEAR(LstMachines[[#This Row],[DateLivr]]) -> 03-2018 | Z82: =LstMachines[[#This Row],[Delivery]]+Rglt_à_HCME -> 43234 | AA82: =IF(MONTH(LstMachines[[#This Row],[DatePaie]])<10,"0","") & MONTH(LstMachines[[#This Row],[DatePaie]])&"-"&YEAR(LstMachines[[#This Row],[DatePaie]]) -> 05-2018 | AB82: =LstMachines[[#This Row],[DateLivr]]+1 -> 43175 | AC82: =IF(MONTH(LstMachines[[#This Row],[Distrib]])<10,"0","") & MONTH(LstMachines[[#This Row],[Distrib]]) & "-" & YEAR(LstMachines[[#This Row],[Distrib]]) -> 03-2018 | AD82: =LstMachines[[#This Row],[DateLivr]]+Délai_Vente -> 43294 | AE82: =IF(MONTH(LstMachines[[#This Row],[VteESM]])<10,"0","") & MONTH(LstMachines[[#This Row],[VteESM]]) & "-" & YEAR(LstMachines[[#This Row],[VteESM]]) -> 07-2018 | AF82: =LstMachines[[#This Row],[DateLivr]]+Rglt_à_ESMTP -> 43234 | AG82: =IF(MONTH(LstMachines[[#This Row],[RgltDistrib]])<10,"0","") & MONTH(LstMachines[[#This Row],[RgltDistrib]]) & "-" & YEAR(LstMachines[[#This Row],[RgltDistrib]]) -> 05-2018 | AH82: =LstMachines[[#This Row],[VteESM]]+Rglt_à_ESMTP -> 43354 | AI82: =IF(MONTH(LstMachines[[#This Row],[RgltVteESM]])<10,"0","") & MONTH(LstMachines[[#This Row],[RgltVteESM]]) & "-" & YEAR(LstMachines[[#This Row],[RgltVteESM]]) -> 09-2018 | AJ82: =MONTH(LstMachines[[#This Row],[DatePaie]]) -> 5 | AK82: =FIXED(YEAR(LstMachines[[#This Row],[DatePaie]]),0,TRUE) -> 2018
B83: Mini Pelle | C83: ZX33 | D83: 33 | E83: ZX33U-5-CLR | F83: SETP | G83: RABASTENS | H83: 1 | I83: =IF(LstMachines[[#This Row],[Delivery]]<Début_HCME, 0, IFERROR( LstMachines[[#This Row],[Nbre]] * INDEX(TabModelSpecs[],MATCH(LstMachines[[#This Row],[Model-Spec]],TabModelSpecs[ModelSpec],0),MATCH("2018",TabModelSpecs[#Headers],0)), LstMachines[[#This Row],[Nbre]]*ROUND(AVERAGEIF(TabModelSpecs[Machine],LstMachines[[#This Row],[Model]],TabModelSpecs[Price]),0) ) ) -> 32 | J83: 43174 | K83: 3-Commande | L83: 2017-12-06 ADV | N83: 43036 | O83: =MONTH(LstMachines[[#This Row],[Delivery]]) -> 3 | P83: =FIXED(YEAR(LstMachines[[#This Row],[Delivery]]),0,TRUE) -> 2018 | Q83: 17100090 | R83: 32431 | U83: STOCK | V83: 4238 | W83: _Stock | X83: =LstMachines[[#This Row],[Delivery]] -> 43174 | Y83: =IF(MONTH(LstMachines[[#This Row],[DateLivr]])<10,"0","") & MONTH(LstMachines[[#This Row],[DateLivr]]) &"-"&YEAR(LstMachines[[#This Row],[DateLivr]]) -> 03-2018 | Z83: =LstMachines[[#This Row],[Delivery]]+Rglt_à_HCME -> 43234 | AA83: =IF(MONTH(LstMachines[[#This Row],[DatePaie]])<10,"0","") & MONTH(LstMachines[[#This Row],[DatePaie]])&"-"&YEAR(LstMachines[[#This Row],[DatePaie]]) -> 05-2018 | AB83: =LstMachines[[#This Row],[DateLivr]]+1 -> 43175 | AC83: =IF(MONTH(LstMachines[[#This Row],[Distrib]])<10,"0","") & MONTH(LstMachines[[#This Row],[Distrib]]) & "-" & YEAR(LstMachines[[#This Row],[Distrib]]) -> 03-2018 | AD83: =LstMachines[[#This Row],[DateLivr]]+Délai_Vente -> 43294 | AE83: =IF(MONTH(LstMachines[[#This Row],[VteESM]])<10,"0","") & MONTH(LstMachines[[#This Row],[VteESM]]) & "-" & YEAR(LstMachines[[#This Row],[VteESM]]) -> 07-2018 | AF83: =LstMachines[[#This Row],[DateLivr]]+Rglt_à_ESMTP -> 43234 | AG83: =IF(MONTH(LstMachines[[#This Row],[RgltDistrib]])<10,"0","") & MONTH(LstMachines[[#This Row],[RgltDistrib]]) & "-" & YEAR(LstMachines[[#This Row],[RgltDistrib]]) -> 05-2018 | AH83: =LstMachines[[#This Row],[VteESM]]+Rglt_à_ESMTP -> 43354 | AI83: =IF(MONTH(LstMachines[[#This Row],[RgltVteESM]])<10,"0","") & MONTH(LstMachines[[#This Row],[RgltVteESM]]) & "-" & YEAR(LstMachines[[#This Row],[RgltVteESM]]) -> 09-2018 | AJ83: =MONTH(LstMachines[[#This Row],[DatePaie]]) -> 5 | AK83: =FIXED(YEAR(LstMachines[[#This Row],[DatePaie]]),0,TRUE) -> 2018
B84: Mini Pelle | C84: ZX48 | D84: 48 | E84: ZX48U-5-CLR | F84: SETP | G84: RABASTENS | H84: 1 | I84: =IF(LstMachines[[#This Row],[Delivery]]<Début_HCME, 0, IFERROR( LstMachines[[#This Row],[Nbre]] * INDEX(TabModelSpecs[],MATCH(LstMachines[[#This Row],[Model-Spec]],TabModelSpecs[ModelSpec],0),MATCH("2018",TabModelSpecs[#Headers],0)), LstMachines[[#This Row],[Nbre]]*ROUND(AVERAGEIF(TabModelSpecs[Machine],LstMachines[[#This Row],[Model]],TabModelSpecs[Price]),0) ) ) -> 41 | J84: 43174 | K84: 3-Commande | L84: 2017-12-06 ADV | N84: 43036 | O84: =MONTH(LstMachines[[#This Row],[Delivery]]) -> 3 | P84: =FIXED(YEAR(LstMachines[[#This Row],[Delivery]]),0,TRUE) -> 2018 | Q84: 17100091 | R84: 42459 | U84: STOCK | V84: 4239 | W84: _Stock | X84: =LstMachines[[#This Row],[Delivery]] -> 43174 | Y84: =IF(MONTH(LstMachines[[#This Row],[DateLivr]])<10,"0","") & MONTH(LstMachines[[#This Row],[DateLivr]]) &"-"&YEAR(LstMachines[[#This Row],[DateLivr]]) -> 03-2018 | Z84: =LstMachines[[#This Row],[Delivery]]+Rglt_à_HCME -> 43234 | AA84: =IF(MONTH(LstMachines[[#This Row],[DatePaie]])<10,"0","") & MONTH(LstMachines[[#This Row],[DatePaie]])&"-"&YEAR(LstMachines[[#This Row],[DatePaie]]) -> 05-2018 | AB84: =LstMachines[[#This Row],[DateLivr]]+1 -> 43175 | AC84: =IF(MONTH(LstMachines[[#This Row],[Distrib]])<10,"0","") & MONTH(LstMachines[[#This Row],[Distrib]]) & "-" & YEAR(LstMachines[[#This Row],[Distrib]]) -> 03-2018 | AD84: =LstMachines[[#This Row],[DateLivr]]+Délai_Vente -> 43294 | AE84: =IF(MONTH(LstMachines[[#This Row],[VteESM]])<10,"0","") & MONTH(LstMachines[[#This Row],[VteESM]]) & "-" & YEAR(LstMachines[[#This Row],[VteESM]]) -> 07-2018 | AF84: =LstMachines[[#This Row],[DateLivr]]+Rglt_à_ESMTP -> 43234 | AG84: =IF(MONTH(LstMachines[[#This Row],[RgltDistrib]])<10,"0","") & MONTH(LstMachines[[#This Row],[RgltDistrib]]) & "-" & YEAR(LstMachines[[#This Row],[RgltDistrib]]) -> 05-2018 | AH84: =LstMachines[[#This Row],[VteESM]]+Rglt_à_ESMTP -> 43354 | AI84: =IF(MONTH(LstMachines[[#This Row],[RgltVteESM]])<10,"0","") & MONTH(LstMachines[[#This Row],[RgltVteESM]]) & "-" & YEAR(LstMachines[[#This Row],[RgltVteESM]]) -> 09-2018 | AJ84: =MONTH(LstMachines[[#This Row],[DatePaie]]) -> 5 | AK84: =FIXED(YEAR(LstMachines[[#This Row],[DatePaie]]),0,TRUE) -> 2018
B85: Mini Pelle | C85: ZX48 | D85: 48 | E85: ZX48U-5-CLR | F85: SETP | G85: RABASTENS | H85: 1 | I85: =IF(LstMachines[[#This Row],[Delivery]]<Début_HCME, 0, IFERROR( LstMachines[[#This Row],[Nbre]] * INDEX(TabModelSpecs[],MATCH(LstMachines[[#This Row],[Model-Spec]],TabModelSpecs[ModelSpec],0),MATCH("2018",TabModelSpecs[#Headers],0)), LstMachines[[#This Row],[Nbre]]*ROUND(AVERAGEIF(TabModelSpecs[Machine],LstMachines[[#This Row],[Model]],TabModelSpecs[Price]),0) ) ) -> 41 | J85: 43174 | K85: 3-Commande | L85: 2017-12-06 ADV | N85: 43067 | O85: =MONTH(LstMachines[[#This Row],[Delivery]]) -> 3 | P85: =FIXED(YEAR(LstMachines[[#This Row],[Delivery]]),0,TRUE) -> 2018 | Q85: 17110008 | R85: 42459 | U85: STOCK | V85: 4247 | W85: _Stock | X85: =LstMachines[[#This Row],[Delivery]] -> 43174 | Y85: =IF(MONTH(LstMachines[[#This Row],[DateLivr]])<10,"0","") & MONTH(LstMachines[[#This Row],[DateLivr]]) &"-"&YEAR(LstMachines[[#This Row],[DateLivr]]) -> 03-2018 | Z85: =LstMachines[[#This Row],[Delivery]]+Rglt_à_HCME -> 43234 | AA85: =IF(MONTH(LstMachines[[#This Row],[DatePaie]])<10,"0","") & MONTH(LstMachines[[#This Row],[DatePaie]])&"-"&YEAR(LstMachines[[#This Row],[DatePaie]]) -> 05-2018 | AB85: =LstMachines[[#This Row],[DateLivr]]+1 -> 43175 | AC85: =IF(MONTH(LstMachines[[#This Row],[Distrib]])<10,"0","") & MONTH(LstMachines[[#This Row],[Distrib]]) & "-" & YEAR(LstMachines[[#This Row],[Distrib]]) -> 03-2018 | AD85: =LstMachines[[#This Row],[DateLivr]]+Délai_Vente -> 43294 | AE85: =IF(MONTH(LstMachines[[#This Row],[VteESM]])<10,"0","") & MONTH(LstMachines[[#This Row],[VteESM]]) & "-" & YEAR(LstMachines[[#This Row],[VteESM]]) -> 07-2018 | AF85: =LstMachines[[#This Row],[DateLivr]]+Rglt_à_ESMTP -> 43234 | AG85: =IF(MONTH(LstMachines[[#This Row],[RgltDistrib]])<10,"0","") & MONTH(LstMachines[[#This Row],[RgltDistrib]]) & "-" & YEAR(LstMachines[[#This Row],[RgltDistrib]]) -> 05-2018 | AH85: =LstMachines[[#This Row],[VteESM]]+Rglt_à_ESMTP -> 43354 | AI85: =IF(MONTH(LstMachines[[#This Row],[RgltVteESM]])<10,"0","") & MONTH(LstMachines[[#This Row],[RgltVteESM]]) & "-" & YEAR(LstMachines[[#This Row],[RgltVteESM]]) -> 09-2018 | AJ85: =MONTH(LstMachines[[#This Row],[DatePaie]]) -> 5 | AK85: =FIXED(YEAR(LstMachines[[#This Row],[DatePaie]]),0,TRUE) -> 2018
B86: Pelle/Chenilles | C86: ZX85 | D86: 85 | E86: ZX85USB-5A-Mono | F86: SETP | G86: Rabastens | H86: 1 | I86: =IF(LstMachines[[#This Row],[Delivery]]<Début_HCME, 0, IFERROR( LstMachines[[#This Row],[Nbre]] * INDEX(TabModelSpecs[],MATCH(LstMachines[[#This Row],[Model-Spec]],TabModelSpecs[ModelSpec],0),MATCH("2018",TabModelSpecs[#Headers],0)), LstMachines[[#This Row],[Nbre]]*ROUND(AVERAGEIF(TabModelSpecs[Machine],LstMachines[[#This Row],[Model]],TabModelSpecs[Price]),0) ) ) -> 64 | J86: 43174 | K86: 3-Commande | L86: 2018-02-07 ADV | O86: =MONTH(LstMachines[[#This Row],[Delivery]]) -> 3 | P86: =FIXED(YEAR(LstMachines[[#This Row],[Delivery]]),0,TRUE) -> 2018 | R86: 59482 | U86: VENTE | W86: _Client x | X86: =LstMachines[[#This Row],[Delivery]] -> 43174 | Y86: =IF(MONTH(LstMachines[[#This Row],[DateLivr]])<10,"0","") & MONTH(LstMachines[[#This Row],[DateLivr]]) &"-"&YEAR(LstMachines[[#This Row],[DateLivr]]) -> 03-2018 | Z86: =LstMachines[[#This Row],[Delivery]]+Rglt_à_HCME -> 43234 | AA86: =IF(MONTH(LstMachines[[#This Row],[DatePaie]])<10,"0","") & MONTH(LstMachines[[#This Row],[DatePaie]])&"-"&YEAR(LstMachines[[#This Row],[DatePaie]]) -> 05-2018 | AB86: =LstMachines[[#This Row],[DateLivr]]+1 -> 43175 | AC86: =IF(MONTH(LstMachines[[#This Row],[Distrib]])<10,"0","") & MONTH(LstMachines[[#This Row],[Distrib]]) & "-" & YEAR(LstMachines[[#This Row],[Distrib]]) -> 03-2018 | AD86: =LstMachines[[#This Row],[DateLivr]]+Délai_Vente -> 43294 | AE86: =IF(MONTH(LstMachines[[#This Row],[VteESM]])<10,"0","") & MONTH(LstMachines[[#This Row],[VteESM]]) & "-" & YEAR(LstMachines[[#This Row],[VteESM]]) -> 07-2018 | AF86: =LstMachines[[#This Row],[DateLivr]]+Rglt_à_ESMTP -> 43234 | AG86: =IF(MONTH(LstMachines[[#This Row],[RgltDistrib]])<10,"0","") & MONTH(LstMachines[[#This Row],[RgltDistrib]]) & "-" & YEAR(LstMachines[[#This Row],[RgltDistrib]]) -> 05-2018 | AH86: =LstMachines[[#This Row],[VteESM]]+Rglt_à_ESMTP -> 43354 | AI86: =IF(MONTH(LstMachines[[#This Row],[RgltVteESM]])<10,"0","") & MONTH(LstMachines[[#This Row],[RgltVteESM]]) & "-" & YEAR(LstMachines[[#This Row],[RgltVteESM]]) -> 09-2018 | AJ86: =MONTH(LstMachines[[#This Row],[DatePaie]]) -> 5 | AK86: =FIXED(YEAR(LstMachines[[#This Row],[DatePaie]]),0,TRUE) -> 2018
B87: Pelle/Chenilles | C87: ZX225 | D87: 225 | E87: ZX225USLC-6-MN-BL | F87: SETP | G87: RABASTENS | H87: 1 | I87: =IF(LstMachines[[#This Row],[Delivery]]<Début_HCME, 0, IFERROR( LstMachines[[#This Row],[Nbre]] * INDEX(TabModelSpecs[],MATCH(LstMachines[[#This Row],[Model-Spec]],TabModelSpecs[ModelSpec],0),MATCH("2018",TabModelSpecs[#Headers],0)), LstMachines[[#This Row],[Nbre]]*ROUND(AVERAGEIF(TabModelSpecs[Machine],LstMachines[[#This Row],[Model]],TabModelSpecs[Price]),0) ) ) -> 128 | J87: 43174 | K87: 3-Commande | L87: 2017-12-06 ADV | N87: 43036 | O87: =MONTH(LstMachines[[#This Row],[Delivery]]) -> 3 | P87: =FIXED(YEAR(LstMachines[[#This Row],[Delivery]]),0,TRUE) -> 2018 | Q87: 17100084 | R87: 120482 | U87: STOCK | V87: 4232 | W87: _Stock | X87: =LstMachines[[#This Row],[Delivery]] -> 43174 | Y87: =IF(MONTH(LstMachines[[#This Row],[DateLivr]])<10,"0","") & MONTH(LstMachines[[#This Row],[DateLivr]]) &"-"&YEAR(LstMachines[[#This Row],[DateLivr]]) -> 03-2018 | Z87: =LstMachines[[#This Row],[Delivery]]+Rglt_à_HCME -> 43234 | AA87: =IF(MONTH(LstMachines[[#This Row],[DatePaie]])<10,"0","") & MONTH(LstMachines[[#This Row],[DatePaie]])&"-"&YEAR(LstMachines[[#This Row],[DatePaie]]) -> 05-2018 | AB87: =LstMachines[[#This Row],[DateLivr]]+1 -> 43175 | AC87: =IF(MONTH(LstMachines[[#This Row],[Distrib]])<10,"0","") & MONTH(LstMachines[[#This Row],[Distrib]]) & "-" & YEAR(LstMachines[[#This Row],[Distrib]]) -> 03-2018 | AD87: =LstMachines[[#This Row],[DateLivr]]+Délai_Vente -> 43294 | AE87: =IF(MONTH(LstMachines[[#This Row],[VteESM]])<10,"0","") & MONTH(LstMachines[[#This Row],[VteESM]]) & "-" & YEAR(LstMachines[[#This Row],[VteESM]]) -> 07-2018 | AF87: =LstMachines[[#This Row],[DateLivr]]+Rglt_à_ESMTP -> 43234 | AG87: =IF(MONTH(LstMachines[[#This Row],[RgltDistrib]])<10,"0","") & MONTH(LstMachines[[#This Row],[RgltDistrib]]) & "-" & YEAR(LstMachines[[#This Row],[RgltDistrib]]) -> 05-2018 | AH87: =LstMachines[[#This Row],[VteESM]]+Rglt_à_ESMTP -> 43354 | AI87: =IF(MONTH(LstMachines[[#This Row],[RgltVteESM]])<10,"0","") & MONTH(LstMachines[[#This Row],[RgltVteESM]]) & "-" & YEAR(LstMachines[[#This Row],[RgltVteESM]]) -> 09-2018 | AJ87: =MONTH(LstMachines[[#This Row],[DatePaie]]) -> 5 | AK87: =FIXED(YEAR(LstMachines[[#This Row],[DatePaie]]),0,TRUE) -> 2018
B88: Mini Pelle | C88: ZX26 | D88: 26 | E88: ZX26U-5-CLR | F88: SETP | G88: RABASTENS | H88: 1 | I88: =IF(LstMachines[[#This Row],[Delivery]]<Début_HCME, 0, IFERROR( LstMachines[[#This Row],[Nbre]] * INDEX(TabModelSpecs[],MATCH(LstMachines[[#This Row],[Model-Spec]],TabModelSpecs[ModelSpec],0),MATCH("2018",TabModelSpecs[#Headers],0)), LstMachines[[#This Row],[Nbre]]*ROUND(AVERAGEIF(TabModelSpecs[Machine],LstMachines[[#This Row],[Model]],TabModelSpecs[Price]),0) ) ) -> 22 | J88: 43174 | K88: 1-Forecast | L88: 2017-12-06 ADV | O88: =MONTH(LstMachines[[#This Row],[Delivery]]) -> 3 | P88: =FIXED(YEAR(LstMachines[[#This Row],[Delivery]]),0,TRUE) -> 2018 | W88: _Location | X88: =LstMachines[[#This Row],[Delivery]] -> 43174 | Y88: =IF(MONTH(LstMachines[[#This Row],[DateLivr]])<10,"0","") & MONTH(LstMachines[[#This Row],[DateLivr]]) &"-"&YEAR(LstMachines[[#This Row],[DateLivr]]) -> 03-2018 | Z88: =LstMachines[[#This Row],[Delivery]]+Rglt_à_HCME -> 43234 | AA88: =IF(MONTH(LstMachines[[#This Row],[DatePaie]])<10,"0","") & MONTH(LstMachines[[#This Row],[DatePaie]])&"-"&YEAR(LstMachines[[#This Row],[DatePaie]]) -> 05-2018 | AB88: =LstMachines[[#This Row],[DateLivr]]+1 -> 43175 | AC88: =IF(MONTH(LstMachines[[#This Row],[Distrib]])<10,"0","") & MONTH(LstMachines[[#This Row],[Distrib]]) & "-" & YEAR(LstMachines[[#This Row],[Distrib]]) -> 03-2018 | AD88: =LstMachines[[#This Row],[DateLivr]]+Délai_Vente -> 43294 | AE88: =IF(MONTH(LstMachines[[#This Row],[VteESM]])<10,"0","") & MONTH(LstMachines[[#This Row],[VteESM]]) & "-" & YEAR(LstMachines[[#This Row],[VteESM]]) -> 07-2018 | AF88: =LstMachines[[#This Row],[DateLivr]]+Rglt_à_ESMTP -> 43234 | AG88: =IF(MONTH(LstMachines[[#This Row],[RgltDistrib]])<10,"0","") & MONTH(LstMachines[[#This Row],[RgltDistrib]]) & "-" & YEAR(LstMachines[[#This Row],[RgltDistrib]]) -> 05-2018 | AH88: =LstMachines[[#This Row],[VteESM]]+Rglt_à_ESMTP -> 43354 | AI88: =IF(MONTH(LstMachines[[#This Row],[RgltVteESM]])<10,"0","") & MONTH(LstMachines[[#This Row],[RgltVteESM]]) & "-" & YEAR(LstMachines[[#This Row],[RgltVteESM]]) -> 09-2018 | AJ88: =MONTH(LstMachines[[#This Row],[DatePaie]]) -> 5 | AK88: =FIXED(YEAR(LstMachines[[#This Row],[DatePaie]]),0,TRUE) -> 2018
B89: Pelle/Chenilles | C89: ZX210 | D89: 210 | E89: ZX210LC-6-MN | F89: XMTP | G89: BORDEAUX | H89: 1 | I89: =IF(LstMachines[[#This Row],[Delivery]]<Début_HCME, 0, IFERROR( LstMachines[[#This Row],[Nbre]] * INDEX(TabModelSpecs[],MATCH(LstMachines[[#This Row],[Model-Spec]],TabModelSpecs[ModelSpec],0),MATCH("2018",TabModelSpecs[#Headers],0)), LstMachines[[#This Row],[Nbre]]*ROUND(AVERAGEIF(TabModelSpecs[Machine],LstMachines[[#This Row],[Model]],TabModelSpecs[Price]),0) ) ) -> 118 | J89: 43174 | K89: 3-Commande | L89: 2017-12 XMTP | O89: =MONTH(LstMachines[[#This Row],[Delivery]]) -> 3 | P89: =FIXED(YEAR(LstMachines[[#This Row],[Delivery]]),0,TRUE) -> 2018 | U89: VENTE | W89: _Stock | X89: =LstMachines[[#This Row],[Delivery]] -> 43174 | Y89: =IF(MONTH(LstMachines[[#This Row],[DateLivr]])<10,"0","") & MONTH(LstMachines[[#This Row],[DateLivr]]) &"-"&YEAR(LstMachines[[#This Row],[DateLivr]]) -> 03-2018 | Z89: =LstMachines[[#This Row],[Delivery]]+Rglt_à_HCME -> 43234 | AA89: =IF(MONTH(LstMachines[[#This Row],[DatePaie]])<10,"0","") & MONTH(LstMachines[[#This Row],[DatePaie]])&"-"&YEAR(LstMachines[[#This Row],[DatePaie]]) -> 05-2018 | AB89: =LstMachines[[#This Row],[DateLivr]]+1 -> 43175 | AC89: =IF(MONTH(LstMachines[[#This Row],[Distrib]])<10,"0","") & MONTH(LstMachines[[#This Row],[Distrib]]) & "-" & YEAR(LstMachines[[#This Row],[Distrib]]) -> 03-2018 | AD89: =LstMachines[[#This Row],[DateLivr]]+Délai_Vente -> 43294 | AE89: =IF(MONTH(LstMachines[[#This Row],[VteESM]])<10,"0","") & MONTH(LstMachines[[#This Row],[VteESM]]) & "-" & YEAR(LstMachines[[#This Row],[VteESM]]) -> 07-2018 | AF89: =LstMachines[[#This Row],[DateLivr]]+Rglt_à_ESMTP -> 43234 | AG89: =IF(MONTH(LstMachines[[#This Row],[RgltDistrib]])<10,"0","") & MONTH(LstMachines[[#This Row],[RgltDistrib]]) & "-" & YEAR(LstMachines[[#This Row],[RgltDistrib]]) -> 05-2018 | AH89: =LstMachines[[#This Row],[VteESM]]+Rglt_à_ESMTP -> 43354 | AI89: =IF(MONTH(LstMachines[[#This Row],[RgltVteESM]])<10,"0","") & MONTH(LstMachines[[#This Row],[RgltVteESM]]) & "-" & YEAR(LstMachines[[#This Row],[RgltVteESM]]) -> 09-2018 | AJ89: =MONTH(LstMachines[[#This Row],[DatePaie]]) -> 5 | AK89: =FIXED(YEAR(LstMachines[[#This Row],[DatePaie]]),0,TRUE) -> 2018
B90: Mini Pelle | C90: ZX65 | D90: 65 | E90: ZX65USB-5-CLR | F90: XMTP | G90: BORDEAUX | H90: 1 | I90: =IF(LstMachines[[#This Row],[Delivery]]<Début_HCME, 0, IFERROR( LstMachines[[#This Row],[Nbre]] * INDEX(TabModelSpecs[],MATCH(LstMachines[[#This Row],[Model-Spec]],TabModelSpecs[ModelSpec],0),MATCH("2018",TabModelSpecs[#Headers],0)), LstMachines[[#This Row],[Nbre]]*ROUND(AVERAGEIF(TabModelSpecs[Machine],LstMachines[[#This Row],[Model]],TabModelSpecs[Price]),0) ) ) -> 45 | J90: 43174 | K90: 1-Forecast | L90: 2017-12 XMTP | O90: =MONTH(LstMachines[[#This Row],[Delivery]]) -> 3 | P90: =FIXED(YEAR(LstMachines[[#This Row],[Delivery]]),0,TRUE) -> 2018 | U90: VENTE | W90: _Stock | X90: =LstMachines[[#This Row],[Delivery]] -> 43174 | Y90: =IF(MONTH(LstMachines[[#This Row],[DateLivr]])<10,"0","") & MONTH(LstMachines[[#This Row],[DateLivr]]) &"-"&YEAR(LstMachines[[#This Row],[DateLivr]]) -> 03-2018 | Z90: =LstMachines[[#This Row],[Delivery]]+Rglt_à_HCME -> 43234 | AA90: =IF(MONTH(LstMachines[[#This Row],[DatePaie]])<10,"0","") & MONTH(LstMachines[[#This Row],[DatePaie]])&"-"&YEAR(LstMachines[[#This Row],[DatePaie]]) -> 05-2018 | AB90: =LstMachines[[#This Row],[DateLivr]]+1 -> 43175 | AC90: =IF(MONTH(LstMachines[[#This Row],[Distrib]])<10,"0","") & MONTH(LstMachines[[#This Row],[Distrib]]) & "-" & YEAR(LstMachines[[#This Row],[Distrib]]) -> 03-2018 | AD90: =LstMachines[[#This Row],[DateLivr]]+Délai_Vente -> 43294 | AE90: =IF(MONTH(LstMachines[[#This Row],[VteESM]])<10,"0","") & MONTH(LstMachines[[#This Row],[VteESM]]) & "-" & YEAR(LstMachines[[#This Row],[VteESM]]) -> 07-2018 | AF90: =LstMachines[[#This Row],[DateLivr]]+Rglt_à_ESMTP -> 43234 | AG90: =IF(MONTH(LstMachines[[#This Row],[RgltDistrib]])<10,"0","") & MONTH(LstMachines[[#This Row],[RgltDistrib]]) & "-" & YEAR(LstMachines[[#This Row],[RgltDistrib]]) -> 05-2018 | AH90: =LstMachines[[#This Row],[VteESM]]+Rglt_à_ESMTP -> 43354 | AI90: =IF(MONTH(LstMachines[[#This Row],[RgltVteESM]])<10,"0","") & MONTH(LstMachines[[#This Row],[RgltVteESM]]) & "-" & YEAR(LstMachines[[#This Row],[RgltVteESM]]) -> 09-2018 | AJ90: =MONTH(LstMachines[[#This Row],[DatePaie]]) -> 5 | AK90: =FIXED(YEAR(LstMachines[[#This Row],[DatePaie]]),0,TRUE) -> 2018
B91: Mini Pelle | C91: ZX48 | D91: 48 | E91: ZX48U-5-CLR | F91: XMTP | G91: BORDEAUX | H91: 2 | I91: =IF(LstMachines[[#This Row],[Delivery]]<Début_HCME, 0, IFERROR( LstMachines[[#This Row],[Nbre]] * INDEX(TabModelSpecs[],MATCH(LstMachines[[#This Row],[Model-Spec]],TabModelSpecs[ModelSpec],0),MATCH("2018",TabModelSpecs[#Headers],0)), LstMachines[[#This Row],[Nbre]]*ROUND(AVERAGEIF(TabModelSpecs[Machine],LstMachines[[#This Row],[Model]],TabModelSpecs[Price]),0) ) ) -> 82 | J91: 43174 | K91: 1-Forecast | L91: 2017-12 XMTP | O91: =MONTH(LstMachines[[#This Row],[Delivery]]) -> 3 | P91: =FIXED(YEAR(LstMachines[[#This Row],[Delivery]]),0,TRUE) -> 2018 | U91: VENTE | W91: _Stock | X91: =LstMachines[[#This Row],[Delivery]] -> 43174 | Y91: =IF(MONTH(LstMachines[[#This Row],[DateLivr]])<10,"0","") & MONTH(LstMachines[[#This Row],[DateLivr]]) &"-"&YEAR(LstMachines[[#This Row],[DateLivr]]) -> 03-2018 | Z91: =LstMachines[[#This Row],[Delivery]]+Rglt_à_HCME -> 43234 | AA91: =IF(MONTH(LstMachines[[#This Row],[DatePaie]])<10,"0","") & MONTH(LstMachines[[#This Row],[DatePaie]])&"-"&YEAR(LstMachines[[#This Row],[DatePaie]]) -> 05-2018 | AB91: =LstMachines[[#This Row],[DateLivr]]+1 -> 43175 | AC91: =IF(MONTH(LstMachines[[#This Row],[Distrib]])<10,"0","") & MONTH(LstMachines[[#This Row],[Distrib]]) & "-" & YEAR(LstMachines[[#This Row],[Distrib]]) -> 03-2018 | AD91: =LstMachines[[#This Row],[DateLivr]]+Délai_Vente -> 43294 | AE91: =IF(MONTH(LstMachines[[#This Row],[VteESM]])<10,"0","") & MONTH(LstMachines[[#This Row],[VteESM]]) & "-" & YEAR(LstMachines[[#This Row],[VteESM]]) -> 07-2018 | AF91: =LstMachines[[#This Row],[DateLivr]]+Rglt_à_ESMTP -> 43234 | AG91: =IF(MONTH(LstMachines[[#This Row],[RgltDistrib]])<10,"0","") & MONTH(LstMachines[[#This Row],[RgltDistrib]]) & "-" & YEAR(LstMachines[[#This Row],[RgltDistrib]]) -> 05-2018 | AH91: =LstMachines[[#This Row],[VteESM]]+Rglt_à_ESMTP -> 43354 | AI91: =IF(MONTH(LstMachines[[#This Row],[RgltVteESM]])<10,"0","") & MONTH(LstMachines[[#This Row],[RgltVteESM]]) & "-" & YEAR(LstMachines[[#This Row],[RgltVteESM]]) -> 09-2018 | AJ91: =MONTH(LstMachines[[#This Row],[DatePaie]]) -> 5 | AK91: =FIXED(YEAR(LstMachines[[#This Row],[DatePaie]]),0,TRUE) -> 2018
B92: Mini Pelle | C92: ZX33 | D92: 33 | E92: ZX33U-5-YLR | F92: XMTP | G92: BORDEAUX | H92: 1 | I92: =IF(LstMachines[[#This Row],[Delivery]]<Début_HCME, 0, IFERROR( LstMachines[[#This Row],[Nbre]] * INDEX(TabModelSpecs[],MATCH(LstMachines[[#This Row],[Model-Spec]],TabModelSpecs[ModelSpec],0),MATCH("2018",TabModelSpecs[#Headers],0)), LstMachines[[#This Row],[Nbre]]*ROUND(AVERAGEIF(TabModelSpecs[Machine],LstMachines[[#This Row],[Model]],TabModelSpecs[Price]),0) ) ) -> 32 | J92: 43174 | K92: 3-Commande | L92: 2017-12 XMTP | O92: =MONTH(LstMachines[[#This Row],[Delivery]]) -> 3 | P92: =FIXED(YEAR(LstMachines[[#This Row],[Delivery]]),0,TRUE) -> 2018 | U92: VENTE | W92: _Stock | X92: =LstMachines[[#This Row],[Delivery]] -> 43174 | Y92: =IF(MONTH(LstMachines[[#This Row],[DateLivr]])<10,"0","") & MONTH(LstMachines[[#This Row],[DateLivr]]) &"-"&YEAR(LstMachines[[#This Row],[DateLivr]]) -> 03-2018 | Z92: =LstMachines[[#This Row],[Delivery]]+Rglt_à_HCME -> 43234 | AA92: =IF(MONTH(LstMachines[[#This Row],[DatePaie]])<10,"0","") & MONTH(LstMachines[[#This Row],[DatePaie]])&"-"&YEAR(LstMachines[[#This Row],[DatePaie]]) -> 05-2018 | AB92: =LstMachines[[#This Row],[DateLivr]]+1 -> 43175 | AC92: =IF(MONTH(LstMachines[[#This Row],[Distrib]])<10,"0","") & MONTH(LstMachines[[#This Row],[Distrib]]) & "-" & YEAR(LstMachines[[#This Row],[Distrib]]) -> 03-2018 | AD92: =LstMachines[[#This Row],[DateLivr]]+Délai_Vente -> 43294 | AE92: =IF(MONTH(LstMachines[[#This Row],[VteESM]])<10,"0","") & MONTH(LstMachines[[#This Row],[VteESM]]) & "-" & YEAR(LstMachines[[#This Row],[VteESM]]) -> 07-2018 | AF92: =LstMachines[[#This Row],[DateLivr]]+Rglt_à_ESMTP -> 43234 | AG92: =IF(MONTH(LstMachines[[#This Row],[RgltDistrib]])<10,"0","") & MONTH(LstMachines[[#This Row],[RgltDistrib]]) & "-" & YEAR(LstMachines[[#This Row],[RgltDistrib]]) -> 05-2018 | AH92: =LstMachines[[#This Row],[VteESM]]+Rglt_à_ESMTP -> 43354 | AI92: =IF(MONTH(LstMachines[[#This Row],[RgltVteESM]])<10,"0","") & MONTH(LstMachines[[#This Row],[RgltVteESM]]) & "-" & YEAR(LstMachines[[#This Row],[RgltVteESM]]) -> 09-2018 | AJ92: =MONTH(LstMachines[[#This Row],[DatePaie]]) -> 5 | AK92: =FIXED(YEAR(LstMachines[[#This Row],[DatePaie]]),0,TRUE) -> 2018
